Workbook

Sheet Total Price List (v2)
M1: =Dimension!B2 -> 0 | N1: =Dimension!C2 -> 0 | O1: =Dimension!D2 -> 0 | P1: =Dimension!E2 -> 0 | Q1: =Dimension!F2 -> 0 | R1: =Dimension!G2 -> 0 | S1: =Dimension!H2 -> 0 | T1: =Dimension!I2 -> 0 | ... FB1: =Dimension!EQ2 -> 0
M2: =Dimension!B3 -> 0 | N2: =Dimension!C3 -> 0 | O2: =Dimension!D3 -> 0 | P2: =Dimension!E3 -> 0 | Q2: =Dimension!F3 -> 0 | R2: =Dimension!G3 -> 0 | S2: =Dimension!H3 -> 0 | T2: =Dimension!I3 -> 0 | ... FB2: =Dimension!EQ3 -> 0
M3: =Dimension!B4 -> 0 | N3: =Dimension!C4 -> 0 | O3: =Dimension!D4 -> 0 | P3: =Dimension!E4 -> 0 | Q3: =Dimension!F4 -> 0 | R3: =Dimension!G4 -> 0 | S3: =Dimension!H4 -> 0 | T3: =Dimension!I4 -> 0 | ... FB3: =Dimension!EQ4 -> 0
M4: =Dimension!B5 -> 0 | N4: =Dimension!C5 -> 0 | O4: =Dimension!D5 -> 0 | P4: =Dimension!E5 -> 0 | Q4: =Dimension!F5 -> 0 | R4: =Dimension!G5 -> 0 | S4: =Dimension!H5 -> 0 | T4: =Dimension!I5 -> 0 | ... FB4: =Dimension!EQ5 -> 0
A5: Name | B5: Index | C5: ID | D5: Product Code | E5: Location Code | F5: Internal Reference | G5: eCommerce Description | H5: Price computation | I5: Cost | J5: Associated Service | K5: Associated Work Center | L5: Associated Cost per Employee per Hour | M5: Margin | N5: =Dimension!C6 -> 0 | O5: =Dimension!D6 -> 0 | P5: =Dimension!E6 -> 0 | Q5: =Dimension!F6 -> 0 | R5: =Dimension!G6 -> 0 | S5: =Dimension!H6 -> 0 | T5: =Dimension!I6 -> 0 | U5: =Dimension!J6 -> 0 | ... FB5: =Dimension!EQ6 -> 0
A6: "COLORBOX" BAKLIJST GROEN DONKERGRIJS 40X33 | B6: 1 | C6: 9896 | D6: 76130 | E6: .C04+C25 | G6: <div data-oe-version="2.0">Test description</div> | H6: Circumference | I6: 3.06 | J6: Lijst snijden | K6: Lijst snijden | L6: 40 | M6: =('Pricelists by Sequence'!$D$2*(-1)/100) -> 0 | N6: {=(IF($H6=$M$4,N$4*$I6,N$3*$I6)+(INDEX(_xlfn._xlws.FILTER('Service Duration by unit'!$D$1:$D$400,('Service Duration by unit'!$A$1:$A$400=$J6)*('Service Duration by unit'!$C$1:$C$400=_xlfn.MINIFS('Service Duration by unit'!$C$1:$C$400,'Service Duration by unit'!$A$1:$A$400,$J6,'Service Duration by unit'!$C$1:$C$400,">="&IF($H6=$M$4,N$4,N$3)))),1))*$L6/3600)*(1+$M6)} -> 0 | O6: {=(IF($H6=$M$4,N$4*$I6,N$3*$I6)+(INDEX(_xlfn._xlws.FILTER('Service Duration by unit'!$D$1:$D$400,('Service Duration by unit'!$A$1:$A$400=$J6)*('Service Duration by unit'!$C$1:$C$400=_xlfn.MINIFS('Service Duration by unit'!$C$1:$C$400,'Service Duration by unit'!$A$1:$A$400,$J6,'Service Duration by unit'!$C$1:$C$400,">="&IF($H6=$M$4,N$4,N$3)))),1))*$L6/3600)*(1+$M6)} -> 0 | P6: {=(IF($H6=$M$4,N$4*$I6,N$3*$I6)+(INDEX(_xlfn._xlws.FILTER('Service Duration by unit'!$D$1:$D$400,('Service Duration by unit'!$A$1:$A$400=$J6)*('Service Duration by unit'!$C$1:$C$400=_xlfn.MINIFS('Service Duration by unit'!$C$1:$C$400,'Service Duration by unit'!$A$1:$A$400,$J6,'Service Duration by unit'!$C$1:$C$400,">="&IF($H6=$M$4,N$4,N$3)))),1))*$L6/3600)*(1+$M6)} -> 0 | Q6: {=(IF($H6=$M$4,N$4*$I6,N$3*$I6)+(INDEX(_xlfn._xlws.FILTER('Service Duration by unit'!$D$1:$D$400,('Service Duration by unit'!$A$1:$A$400=$J6)*('Service Duration by unit'!$C$1:$C$400=_xlfn.MINIFS('Service Duration by unit'!$C$1:$C$400,'Service Duration by unit'!$A$1:$A$400,$J6,'Service Duration by unit'!$C$1:$C$400,">="&IF($H6=$M$4,N$4,N$3)))),1))*$L6/3600)*(1+$M6)} -> 0 | R6: {=(IF($H6=$M$4,N$4*$I6,N$3*$I6)+(INDEX(_xlfn._xlws.FILTER('Service Duration by unit'!$D$1:$D$400,('Service Duration by unit'!$A$1:$A$400=$J6)*('Service Duration by unit'!$C$1:$C$400=_xlfn.MINIFS('Service Duration by unit'!$C$1:$C$400,'Service Duration by unit'!$A$1:$A$400,$J6,'Service Duration by unit'!$C$1:$C$400,">="&IF($H6=$M$4,N$4,N$3)))),1))*$L6/3600)*(1+$M6)} -> 0 | S6: {=(IF($H6=$M$4,N$4*$I6,N$3*$I6)+(INDEX(_xlfn._xlws.FILTER('Service Duration by unit'!$D$1:$D$400,('Service Duration by unit'!$A$1:$A$400=$J6)*('Service Duration by unit'!$C$1:$C$400=_xlfn.MINIFS('Service Duration by unit'!$C$1:$C$400,'Service Duration by unit'!$A$1:$A$400,$J6,'Service Duration by unit'!$C$1:$C$400,">="&IF($H6=$M$4,N$4,N$3)))),1))*$L6/3600)*(1+$M6)} -> 0 | T6: {=(IF($H6=$M$4,N$4*$I6,N$3*$I6)+(INDEX(_xlfn._xlws.FILTER('Service Duration by unit'!$D$1:$D$400,('Service Duration by unit'!$A$1:$A$400=$J6)*('Service Duration by unit'!$C$1:$C$400=_xlfn.MINIFS('Service Duration by unit'!$C$1:$C$400,'Service Duration by unit'!$A$1:$A$400,$J6,'Service Duration by unit'!$C$1:$C$400,">="&IF($H6=$M$4,N$4,N$3)))),1))*$L6/3600)*(1+$M6)} -> 0 | U6: {=(IF($H6=$M$4,N$4*$I6,N$3*$I6)+(INDEX(_xlfn._xlws.FILTER('Service Duration by unit'!$D$1:$D$400,('Service Duration by unit'!$A$1:$A$400=$J6)*('Service Duration by unit'!$C$1:$C$400=_xlfn.MINIFS('Service Duration by unit'!$C$1:$C$400,'Service Duration by unit'!$A$1:$A$400,$J6,'Service Duration by unit'!$C$1:$C$400,">="&IF($H6=$M$4,N$4,N$3)))),1))*$L6/3600)*(1+$M6)} -> 0 | V6: {=(IF($H6=$M$4,N$4*$I6,N$3*$I6)+(INDEX(_xlfn._xlws.FILTER('Service Duration by unit'!$D$1:$D$400,('Service Duration by unit'!$A$1:$A$400=$J6)*('Service Duration by unit'!$C$1:$C$400=_xlfn.MINIFS('Service Duration by unit'!$C$1:$C$400,'Service Duration by unit'!$A$1:$A$400,$J6,'Service Duration by unit'!$C$1:$C$400,">="&IF($H6=$M$4,N$4,N$3)))),1))*$L6/3600)*(1+$M6)} -> 0 | W6: {=(IF($H6=$M$4,N$4*$I6,N$3*$I6)+(INDEX(_xlfn._xlws.FILTER('Service Duration by unit'!$D$1:$D$400,('Service Duration by unit'!$A$1:$A$400=$J6)*('Service Duration by unit'!$C$1:$C$400=_xlfn.MINIFS('Service Duration by unit'!$C$1:$C$400,'Service Duration by unit'!$A$1:$A$400,$J6,'Service Duration by unit'!$C$1:$C$400,">="&IF($H6=$M$4,N$4,N$3)))),1))*$L6/3600)*(1+$M6)} -> 0 | X6: {=(IF($H6=$M$4,N$4*$I6,N$3*$I6)+(INDEX(_xlfn._xlws.FILTER('Service Duration by unit'!$D$1:$D$400,('Service Duration by unit'!$A$1:$A$400=$J6)*('Service Duration by unit'!$C$1:$C$400=_xlfn.MINIFS('Service Duration by unit'!$C$1:$C$400,'Service Duration by unit'!$A$1:$A$400,$J6,'Service Duration by unit'!$C$1:$C$400,">="&IF($H6=$M$4,N$4,N$3)))),1))*$L6/3600)*(1+$M6)} -> 0 | Y6: {=(IF($H6=$M$4,N$4*$I6,N$3*$I6)+(INDEX(_xlfn._xlws.FILTER('Service Duration by unit'!$D$1:$D$400,('Service Duration by unit'!$A$1:$A$400=$J6)*('Service Duration by unit'!$C$1:$C$400=_xlfn.MINIFS('Service Duration by unit'!$C$1:$C$400,'Service Duration by unit'!$A$1:$A$400,$J6,'Service Duration by unit'!$C$1:$C$400,">="&IF($H6=$M$4,N$4,N$3)))),1))*$L6/3600)*(1+$M6)} -> 0 | Z6: {=(IF($H6=$M$4,N$4*$I6,N$3*$I6)+(INDEX(_xlfn._xlws.FILTER('Service Duration by unit'!$D$1:$D$400,('Service Duration by unit'!$A$1:$A$400=$J6)*('Service Duration by unit'!$C$1:$C$400=_xlfn.MINIFS('Service Duration by unit'!$C$1:$C$400,'Service Duration by unit'!$A$1:$A$400,$J6,'Service Duration by unit'!$C$1:$C$400,">="&IF($H6=$M$4,N$4,N$3)))),1))*$L6/3600)*(1+$M6)} -> 0 | AA6: {=(IF($H6=$M$4,N$4*$I6,N$3*$I6)+(INDEX(_xlfn._xlws.FILTER('Service Duration by unit'!$D$1:$D$400,('Service Duration by unit'!$A$1:$A$400=$J6)*('Service Duration by unit'!$C$1:$C$400=_xlfn.MINIFS('Service Duration by unit'!$C$1:$C$400,'Service Duration by unit'!$A$1:$A$400,$J6,'Service Duration by unit'!$C$1:$C$400,">="&IF($H6=$M$4,N$4,N$3)))),1))*$L6/3600)*(1+$M6)} -> 0 | AB6: {=(IF($H6=$M$4,N$4*$I6,N$3*$I6)+(INDEX(_xlfn._xlws.FILTER('Service Duration by unit'!$D$1:$D$400,('Service Duration by unit'!$A$1:$A$400=$J6)*('Service Duration by unit'!$C$1:$C$400=_xlfn.MINIFS('Service Duration by unit'!$C$1:$C$400,'Service Duration by unit'!$A$1:$A$400,$J6,'Service Duration by unit'!$C$1:$C$400,">="&IF($H6=$M$4,N$4,N$3)))),1))*$L6/3600)*(1+$M6)} -> 0 | AC6: {=(IF($H6=$M$4,N$4*$I6,N$3*$I6)+(INDEX(_xlfn._xlws.FILTER('Service Duration by unit'!$D$1:$D$400,('Service Duration by unit'!$A$1:$A$400=$J6)*('Service Duration by unit'!$C$1:$C$400=_xlfn.MINIFS('Service Duration by unit'!$C$1:$C$400,'Service Duration by unit'!$A$1:$A$400,$J6,'Service Duration by unit'!$C$1:$C$400,">="&IF($H6=$M$4,N$4,N$3)))),1))*$L6/3600)*(1+$M6)} -> 0 | AD6: {=(IF($H6=$M$4,N$4*$I6,N$3*$I6)+(INDEX(_xlfn._xlws.FILTER('Service Duration by unit'!$D$1:$D$400,('Service Duration by unit'!$A$1:$A$400=$J6)*('Service Duration by unit'!$C$1:$C$400=_xlfn.MINIFS('Service Duration by unit'!$C$1:$C$400,'Service Duration by unit'!$A$1:$A$400,$J6,'Service Duration by unit'!$C$1:$C$400,">="&IF($H6=$M$4,N$4,N$3)))),1))*$L6/3600)*(1+$M6)} -> 0 | AE6: {=(IF($H6=$M$4,N$4*$I6,N$3*$I6)+(INDEX(_xlfn._xlws.FILTER('Service Duration by unit'!$D$1:$D$400,('Service Duration by unit'!$A$1:$A$400=$J6)*('Service Duration by unit'!$C$1:$C$400=_xlfn.MINIFS('Service Duration by unit'!$C$1:$C$400,'Service Duration by unit'!$A$1:$A$400,$J6,'Service Duration by unit'!$C$1:$C$400,">="&IF($H6=$M$4,N$4,N$3)))),1))*$L6/3600)*(1+$M6)} -> 0 | AF6: {=(IF($H6=$M$4,N$4*$I6,N$3*$I6)+(INDEX(_xlfn._xlws.FILTER('Service Duration by unit'!$D$1:$D$400,('Service Duration by unit'!$A$1:$A$400=$J6)*('Service Duration by unit'!$C$1:$C$400=_xlfn.MINIFS('Service Duration by unit'!$C$1:$C$400,'Service Duration by unit'!$A$1:$A$400,$J6,'Service Duration by unit'!$C$1:$C$400,">="&IF($H6=$M$4,N$4,N$3)))),1))*$L6/3600)*(1+$M6)} -> 0 | AG6: {=(IF($H6=$M$4,N$4*$I6,N$3*$I6)+(INDEX(_xlfn._xlws.FILTER('Service Duration by unit'!$D$1:$D$400,('Service Duration by unit'!$A$1:$A$400=$J6)*('Service Duration by unit'!$C$1:$C$400=_xlfn.MINIFS('Service Duration by unit'!$C$1:$C$400,'Service Duration by unit'!$A$1:$A$400,$J6,'Service Duration by unit'!$C$1:$C$400,">="&IF($H6=$M$4,N$4,N$3)))),1))*$L6/3600)*(1+$M6)} -> 0 | AH6: {=(IF($H6=$M$4,N$4*$I6,N$3*$I6)+(INDEX(_xlfn._xlws.FILTER('Service Duration by unit'!$D$1:$D$400,('Service Duration by unit'!$A$1:$A$400=$J6)*('Service Duration by unit'!$C$1:$C$400=_xlfn.MINIFS('Service Duration by unit'!$C$1:$C$400,'Service Duration by unit'!$A$1:$A$400,$J6,'Service Duration by unit'!$C$1:$C$400,">="&IF($H6=$M$4,N$4,N$3)))),1))*$L6/3600)*(1+$M6)} -> 0 | AI6: {=(IF($H6=$M$4,N$4*$I6,N$3*$I6)+(INDEX(_xlfn._xlws.FILTER('Service Duration by unit'!$D$1:$D$400,('Service Duration by unit'!$A$1:$A$400=$J6)*('Service Duration by unit'!$C$1:$C$400=_xlfn.MINIFS('Service Duration by unit'!$C$1:$C$400,'Service Duration by unit'!$A$1:$A$400,$J6,'Service Duration by unit'!$C$1:$C$400,">="&IF($H6=$M$4,N$4,N$3)))),1))*$L6/3600)*(1+$M6)} -> 0 | AJ6: {=(IF($H6=$M$4,N$4*$I6,N$3*$I6)+(INDEX(_xlfn._xlws.FILTER('Service Duration by unit'!$D$1:$D$400,('Service Duration by unit'!$A$1:$A$400=$J6)*('Service Duration by unit'!$C$1:$C$400=_xlfn.MINIFS('Service Duration by unit'!$C$1:$C$400,'Service Duration by unit'!$A$1:$A$400,$J6,'Service Duration by unit'!$C$1:$C$400,">="&IF($H6=$M$4,N$4,N$3)))),1))*$L6/3600)*(1+$M6)} -> 0 | AK6: {=(IF($H6=$M$4,N$4*$I6,N$3*$I6)+(INDEX(_xlfn._xlws.FILTER('Service Duration by unit'!$D$1:$D$400,('Service Duration by unit'!$A$1:$A$400=$J6)*('Service Duration by unit'!$C$1:$C$400=_xlfn.MINIFS('Service Duration by unit'!$C$1:$C$400,'Service Duration by unit'!$A$1:$A$400,$J6,'Service Duration by unit'!$C$1:$C$400,">="&IF($H6=$M$4,N$4,N$3)))),1))*$L6/3600)*(1+$M6)} -> 0 | AL6: {=(IF($H6=$M$4,N$4*$I6,N$3*$I6)+(INDEX(_xlfn._xlws.FILTER('Service Duration by unit'!$D$1:$D$400,('Service Duration by unit'!$A$1:$A$400=$J6)*('Service Duration by unit'!$C$1:$C$400=_xlfn.MINIFS('Service Duration by unit'!$C$1:$C$400,'Service Duration by unit'!$A$1:$A$400,$J6,'Service Duration by unit'!$C$1:$C$400,">="&IF($H6=$M$4,N$4,N$3)))),1))*$L6/3600)*(1+$M6)} -> 0 | AM6: {=(IF($H6=$M$4,N$4*$I6,N$3*$I6)+(INDEX(_xlfn._xlws.FILTER('Service Duration by unit'!$D$1:$D$400,('Service Duration by unit'!$A$1:$A$400=$J6)*('Service Duration by unit'!$C$1:$C$400=_xlfn.MINIFS('Service Duration by unit'!$C$1:$C$400,'Service Duration by unit'!$A$1:$A$400,$J6,'Service Duration by unit'!$C$1:$C$400,">="&IF($H6=$M$4,N$4,N$3)))),1))*$L6/3600)*(1+$M6)} -> 0 | AN6: {=(IF($H6=$M$4,N$4*$I6,N$3*$I6)+(INDEX(_xlfn._xlws.FILTER('Service Duration by unit'!$D$1:$D$400,('Service Duration by unit'!$A$1:$A$400=$J6)*('Service Duration by unit'!$C$1:$C$400=_xlfn.MINIFS('Service Duration by unit'!$C$1:$C$400,'Service Duration by unit'!$A$1:$A$400,$J6,'Service Duration by unit'!$C$1:$C$400,">="&IF($H6=$M$4,N$4,N$3)))),1))*$L6/3600)*(1+$M6)} -> 0 | AO6: {=(IF($H6=$M$4,N$4*$I6,N$3*$I6)+(INDEX(_xlfn._xlws.FILTER('Service Duration by unit'!$D$1:$D$400,('Service Duration by unit'!$A$1:$A$400=$J6)*('Service Duration by unit'!$C$1:$C$400=_xlfn.MINIFS('Service Duration by unit'!$C$1:$C$400,'Service Duration by unit'!$A$1:$A$400,$J6,'Service Duration by unit'!$C$1:$C$400,">="&IF($H6=$M$4,N$4,N$3)))),1))*$L6/3600)*(1+$M6)} -> 0 | AP6: {=(IF($H6=$M$4,N$4*$I6,N$3*$I6)+(INDEX(_xlfn._xlws.FILTER('Service Duration by unit'!$D$1:$D$400,('Service Duration by unit'!$A$1:$A$400=$J6)*('Service Duration by unit'!$C$1:$C$400=_xlfn.MINIFS('Service Duration by unit'!$C$1:$C$400,'Service Duration by unit'!$A$1:$A$400,$J6,'Service Duration by unit'!$C$1:$C$400,">="&IF($H6=$M$4,N$4,N$3)))),1))*$L6/3600)*(1+$M6)} -> 0 | AQ6: {=(IF($H6=$M$4,N$4*$I6,N$3*$I6)+(INDEX(_xlfn._xlws.FILTER('Service Duration by unit'!$D$1:$D$400,('Service Duration by unit'!$A$1:$A$400=$J6)*('Service Duration by unit'!$C$1:$C$400=_xlfn.MINIFS('Service Duration by unit'!$C$1:$C$400,'Service Duration by unit'!$A$1:$A$400,$J6,'Service Duration by unit'!$C$1:$C$400,">="&IF($H6=$M$4,N$4,N$3)))),1))*$L6/3600)*(1+$M6)} -> 0 | AR6: {=(IF($H6=$M$4,N$4*$I6,N$3*$I6)+(INDEX(_xlfn._xlws.FILTER('Service Duration by unit'!$D$1:$D$400,('Service Duration by unit'!$A$1:$A$400=$J6)*('Service Duration by unit'!$C$1:$C$400=_xlfn.MINIFS('Service Duration by unit'!$C$1:$C$400,'Service Duration by unit'!$A$1:$A$400,$J6,'Service Duration by unit'!$C$1:$C$400,">="&IF($H6=$M$4,N$4,N$3)))),1))*$L6/3600)*(1+$M6)} -> 0 | AS6: {=(IF($H6=$M$4,N$4*$I6,N$3*$I6)+(INDEX(_xlfn._xlws.FILTER('Service Duration by unit'!$D$1:$D$400,('Service Duration by unit'!$A$1:$A$400=$J6)*('Service Duration by unit'!$C$1:$C$400=_xlfn.MINIFS('Service Duration by unit'!$C$1:$C$400,'Service Duration by unit'!$A$1:$A$400,$J6,'Service Duration by unit'!$C$1:$C$400,">="&IF($H6=$M$4,N$4,N$3)))),1))*$L6/3600)*(1+$M6)} -> 0 | AT6: {=(IF($H6=$M$4,N$4*$I6,N$3*$I6)+(INDEX(_xlfn._xlws.FILTER('Service Duration by unit'!$D$1:$D$400,('Service Duration by unit'!$A$1:$A$400=$J6)*('Service Duration by unit'!$C$1:$C$400=_xlfn.MINIFS('Service Duration by unit'!$C$1:$C$400,'Service Duration by unit'!$A$1:$A$400,$J6,'Service Duration by unit'!$C$1:$C$400,">="&IF($H6=$M$4,N$4,N$3)))),1))*$L6/3600)*(1+$M6)} -> 0 | AU6: {=(IF($H6=$M$4,N$4*$I6,N$3*$I6)+(INDEX(_xlfn._xlws.FILTER('Service Duration by unit'!$D$1:$D$400,('Service Duration by unit'!$A$1:$A$400=$J6)*('Service Duration by unit'!$C$1:$C$400=_xlfn.MINIFS('Service Duration by unit'!$C$1:$C$400,'Service Duration by unit'!$A$1:$A$400,$J6,'Service Duration by unit'!$C$1:$C$400,">="&IF($H6=$M$4,N$4,N$3)))),1))*$L6/3600)*(1+$M6)} -> 0 | AV6: {=(IF($H6=$M$4,N$4*$I6,N$3*$I6)+(INDEX(_xlfn._xlws.FILTER('Service Duration by unit'!$D$1:$D$400,('Service Duration by unit'!$A$1:$A$400=$J6)*('Service Duration by unit'!$C$1:$C$400=_xlfn.MINIFS('Service Duration by unit'!$C$1:$C$400,'Service Duration by unit'!$A$1:$A$400,$J6,'Service Duration by unit'!$C$1:$C$400,">="&IF($H6=$M$4,N$4,N$3)))),1))*$L6/3600)*(1+$M6)} -> 0 | AW6: {=(IF($H6=$M$4,N$4*$I6,N$3*$I6)+(INDEX(_xlfn._xlws.FILTER('Service Duration by unit'!$D$1:$D$400,('Service Duration by unit'!$A$1:$A$400=$J6)*('Service Duration by unit'!$C$1:$C$400=_xlfn.MINIFS('Service Duration by unit'!$C$1:$C$400,'Service Duration by unit'!$A$1:$A$400,$J6,'Service Duration by unit'!$C$1:$C$400,">="&IF($H6=$M$4,N$4,N$3)))),1))*$L6/3600)*(1+$M6)} -> 0 | AX6: {=(IF($H6=$M$4,N$4*$I6,N$3*$I6)+(INDEX(_xlfn._xlws.FILTER('Service Duration by unit'!$D$1:$D$400,('Service Duration by unit'!$A$1:$A$400=$J6)*('Service Duration by unit'!$C$1:$C$400=_xlfn.MINIFS('Service Duration by unit'!$C$1:$C$400,'Service Duration by unit'!$A$1:$A$400,$J6,'Service Duration by unit'!$C$1:$C$400,">="&IF($H6=$M$4,N$4,N$3)))),1))*$L6/3600)*(1+$M6)} -> 0 | AY6: {=(IF($H6=$M$4,N$4*$I6,N$3*$I6)+(INDEX(_xlfn._xlws.FILTER('Service Duration by unit'!$D$1:$D$400,('Service Duration by unit'!$A$1:$A$400=$J6)*('Service Duration by unit'!$C$1:$C$400=_xlfn.MINIFS('Service Duration by unit'!$C$1:$C$400,'Service Duration by unit'!$A$1:$A$400,$J6,'Service Duration by unit'!$C$1:$C$400,">="&IF($H6=$M$4,N$4,N$3)))),1))*$L6/3600)*(1+$M6)} -> 0 | AZ6: {=(IF($H6=$M$4,N$4*$I6,N$3*$I6)+(INDEX(_xlfn._xlws.FILTER('Service Duration by unit'!$D$1:$D$400,('Service Duration by unit'!$A$1:$A$400=$J6)*('Service Duration by unit'!$C$1:$C$400=_xlfn.MINIFS('Service Duration by unit'!$C$1:$C$400,'Service Duration by unit'!$A$1:$A$400,$J6,'Service Duration by unit'!$C$1:$C$400,">="&IF($H6=$M$4,N$4,N$3)))),1))*$L6/3600)*(1+$M6)} -> 0 | BA6: {=(IF($H6=$M$4,N$4*$I6,N$3*$I6)+(INDEX(_xlfn._xlws.FILTER('Service Duration by unit'!$D$1:$D$400,('Service Duration by unit'!$A$1:$A$400=$J6)*('Service Duration by unit'!$C$1:$C$400=_xlfn.MINIFS('Service Duration by unit'!$C$1:$C$400,'Service Duration by unit'!$A$1:$A$400,$J6,'Service Duration by unit'!$C$1:$C$400,">="&IF($H6=$M$4,N$4,N$3)))),1))*$L6/3600)*(1+$M6)} -> 0 | BB6: {=(IF($H6=$M$4,N$4*$I6,N$3*$I6)+(INDEX(_xlfn._xlws.FILTER('Service Duration by unit'!$D$1:$D$400,('Service Duration by unit'!$A$1:$A$400=$J6)*('Service Duration by unit'!$C$1:$C$400=_xlfn.MINIFS('Service Duration by unit'!$C$1:$C$400,'Service Duration by unit'!$A$1:$A$400,$J6,'Service Duration by unit'!$C$1:$C$400,">="&IF($H6=$M$4,N$4,N$3)))),1))*$L6/3600)*(1+$M6)} -> 0 | BC6: {=(IF($H6=$M$4,N$4*$I6,N$3*$I6)+(INDEX(_xlfn._xlws.FILTER('Service Duration by unit'!$D$1:$D$400,('Service Duration by unit'!$A$1:$A$400=$J6)*('Service Duration by unit'!$C$1:$C$400=_xlfn.MINIFS('Service Duration by unit'!$C$1:$C$400,'Service Duration by unit'!$A$1:$A$400,$J6,'Service Duration by unit'!$C$1:$C$400,">="&IF($H6=$M$4,N$4,N$3)))),1))*$L6/3600)*(1+$M6)} -> 0 | BD6: {=(IF($H6=$M$4,N$4*$I6,N$3*$I6)+(INDEX(_xlfn._xlws.FILTER('Service Duration by unit'!$D$1:$D$400,('Service Duration by unit'!$A$1:$A$400=$J6)*('Service Duration by unit'!$C$1:$C$400=_xlfn.MINIFS('Service Duration by unit'!$C$1:$C$400,'Service Duration by unit'!$A$1:$A$400,$J6,'Service Duration by unit'!$C$1:$C$400,">="&IF($H6=$M$4,N$4,N$3)))),1))*$L6/3600)*(1+$M6)} -> 0 | BE6: {=(IF($H6=$M$4,N$4*$I6,N$3*$I6)+(INDEX(_xlfn._xlws.FILTER('Service Duration by unit'!$D$1:$D$400,('Service Duration by unit'!$A$1:$A$400=$J6)*('Service Duration by unit'!$C$1:$C$400=_xlfn.MINIFS('Service Duration by unit'!$C$1:$C$400,'Service Duration by unit'!$A$1:$A$400,$J6,'Service Duration by unit'!$C$1:$C$400,">="&IF($H6=$M$4,N$4,N$3)))),1))*$L6/3600)*(1+$M6)} -> 0 | BF6: {=(IF($H6=$M$4,N$4*$I6,N$3*$I6)+(INDEX(_xlfn._xlws.FILTER('Service Duration by unit'!$D$1:$D$400,('Service Duration by unit'!$A$1:$A$400=$J6)*('Service Duration by unit'!$C$1:$C$400=_xlfn.MINIFS('Service Duration by unit'!$C$1:$C$400,'Service Duration by unit'!$A$1:$A$400,$J6,'Service Duration by unit'!$C$1:$C$400,">="&IF($H6=$M$4,N$4,N$3)))),1))*$L6/3600)*(1+$M6)} -> 0 | BG6: {=(IF($H6=$M$4,N$4*$I6,N$3*$I6)+(INDEX(_xlfn._xlws.FILTER('Service Duration by unit'!$D$1:$D$400,('Service Duration by unit'!$A$1:$A$400=$J6)*('Service Duration by unit'!$C$1:$C$400=_xlfn.MINIFS('Service Duration by unit'!$C$1:$C$400,'Service Duration by unit'!$A$1:$A$400,$J6,'Service Duration by unit'!$C$1:$C$400,">="&IF($H6=$M$4,N$4,N$3)))),1))*$L6/3600)*(1+$M6)} -> 0 | BH6: {=(IF($H6=$M$4,N$4*$I6,N$3*$I6)+(INDEX(_xlfn._xlws.FILTER('Service Duration by unit'!$D$1:$D$400,('Service Duration by unit'!$A$1:$A$400=$J6)*('Service Duration by unit'!$C$1:$C$400=_xlfn.MINIFS('Service Duration by unit'!$C$1:$C$400,'Service Duration by unit'!$A$1:$A$400,$J6,'Service Duration by unit'!$C$1:$C$400,">="&IF($H6=$M$4,N$4,N$3)))),1))*$L6/3600)*(1+$M6)} -> 0 | BI6: {=(IF($H6=$M$4,N$4*$I6,N$3*$I6)+(INDEX(_xlfn._xlws.FILTER('Service Duration by unit'!$D$1:$D$400,('Service Duration by unit'!$A$1:$A$400=$J6)*('Service Duration by unit'!$C$1:$C$400=_xlfn.MINIFS('Service Duration by unit'!$C$1:$C$400,'Service Duration by unit'!$A$1:$A$400,$J6,'Service Duration by unit'!$C$1:$C$400,">="&IF($H6=$M$4,N$4,N$3)))),1))*$L6/3600)*(1+$M6)} -> 0 | BJ6: {=(IF($H6=$M$4,N$4*$I6,N$3*$I6)+(INDEX(_xlfn._xlws.FILTER('Service Duration by unit'!$D$1:$D$400,('Service Duration by unit'!$A$1:$A$400=$J6)*('Service Duration by unit'!$C$1:$C$400=_xlfn.MINIFS('Service Duration by unit'!$C$1:$C$400,'Service Duration by unit'!$A$1:$A$400,$J6,'Service Duration by unit'!$C$1:$C$400,">="&IF($H6=$M$4,N$4,N$3)))),1))*$L6/3600)*(1+$M6)} -> 0 | BK6: {=(IF($H6=$M$4,N$4*$I6,N$3*$I6)+(INDEX(_xlfn._xlws.FILTER('Service Duration by unit'!$D$1:$D$400,('Service Duration by unit'!$A$1:$A$400=$J6)*('Service Duration by unit'!$C$1:$C$400=_xlfn.MINIFS('Service Duration by unit'!$C$1:$C$400,'Service Duration by unit'!$A$1:$A$400,$J6,'Service Duration by unit'!$C$1:$C$400,">="&IF($H6=$M$4,N$4,N$3)))),1))*$L6/3600)*(1+$M6)} -> 0 | BL6: {=(IF($H6=$M$4,N$4*$I6,N$3*$I6)+(INDEX(_xlfn._xlws.FILTER('Service Duration by unit'!$D$1:$D$400,('Service Duration by unit'!$A$1:$A$400=$J6)*('Service Duration by unit'!$C$1:$C$400=_xlfn.MINIFS('Service Duration by unit'!$C$1:$C$400,'Service Duration by unit'!$A$1:$A$400,$J6,'Service Duration by unit'!$C$1:$C$400,">="&IF($H6=$M$4,N$4,N$3)))),1))*$L6/3600)*(1+$M6)} -> 0 | BM6: {=(IF($H6=$M$4,N$4*$I6,N$3*$I6)+(INDEX(_xlfn._xlws.FILTER('Service Duration by unit'!$D$1:$D$400,('Service Duration by unit'!$A$1:$A$400=$J6)*('Service Duration by unit'!$C$1:$C$400=_xlfn.MINIFS('Service Duration by unit'!$C$1:$C$400,'Service Duration by unit'!$A$1:$A$400,$J6,'Service Duration by unit'!$C$1:$C$400,">="&IF($H6=$M$4,N$4,N$3)))),1))*$L6/3600)*(1+$M6)} -> 0 | BN6: {=(IF($H6=$M$4,N$4*$I6,N$3*$I6)+(INDEX(_xlfn._xlws.FILTER('Service Duration by unit'!$D$1:$D$400,('Service Duration by unit'!$A$1:$A$400=$J6)*('Service Duration by unit'!$C$1:$C$400=_xlfn.MINIFS('Service Duration by unit'!$C$1:$C$400,'Service Duration by unit'!$A$1:$A$400,$J6,'Service Duration by unit'!$C$1:$C$400,">="&IF($H6=$M$4,N$4,N$3)))),1))*$L6/3600)*(1+$M6)} -> 0 | BO6: {=(IF($H6=$M$4,N$4*$I6,N$3*$I6)+(INDEX(_xlfn._xlws.FILTER('Service Duration by unit'!$D$1:$D$400,('Service Duration by unit'!$A$1:$A$400=$J6)*('Service Duration by unit'!$C$1:$C$400=_xlfn.MINIFS('Service Duration by unit'!$C$1:$C$400,'Service Duration by unit'!$A$1:$A$400,$J6,'Service Duration by unit'!$C$1:$C$400,">="&IF($H6=$M$4,N$4,N$3)))),1))*$L6/3600)*(1+$M6)} -> 0 | BP6: {=(IF($H6=$M$4,N$4*$I6,N$3*$I6)+(INDEX(_xlfn._xlws.FILTER('Service Duration by unit'!$D$1:$D$400,('Service Duration by unit'!$A$1:$A$400=$J6)*('Service Duration by unit'!$C$1:$C$400=_xlfn.MINIFS('Service Duration by unit'!$C$1:$C$400,'Service Duration by unit'!$A$1:$A$400,$J6,'Service Duration by unit'!$C$1:$C$400,">="&IF($H6=$M$4,N$4,N$3)))),1))*$L6/3600)*(1+$M6)} -> 0 | BQ6: {=(IF($H6=$M$4,N$4*$I6,N$3*$I6)+(INDEX(_xlfn._xlws.FILTER('Service Duration by unit'!$D$1:$D$400,('Service Duration by unit'!$A$1:$A$400=$J6)*('Service Duration by unit'!$C$1:$C$400=_xlfn.MINIFS('Service Duration by unit'!$C$1:$C$400,'Service Duration by unit'!$A$1:$A$400,$J6,'Service Duration by unit'!$C$1:$C$400,">="&IF($H6=$M$4,N$4,N$3)))),1))*$L6/3600)*(1+$M6)} -> 0 | BR6: {=(IF($H6=$M$4,N$4*$I6,N$3*$I6)+(INDEX(_xlfn._xlws.FILTER('Service Duration by unit'!$D$1:$D$400,('Service Duration by unit'!$A$1:$A$400=$J6)*('Service Duration by unit'!$C$1:$C$400=_xlfn.MINIFS('Service Duration by unit'!$C$1:$C$400,'Service Duration by unit'!$A$1:$A$400,$J6,'Service Duration by unit'!$C$1:$C$400,">="&IF($H6=$M$4,N$4,N$3)))),1))*$L6/3600)*(1+$M6)} -> 0 | BS6: {=(IF($H6=$M$4,N$4*$I6,N$3*$I6)+(INDEX(_xlfn._xlws.FILTER('Service Duration by unit'!$D$1:$D$400,('Service Duration by unit'!$A$1:$A$400=$J6)*('Service Duration by unit'!$C$1:$C$400=_xlfn.MINIFS('Service Duration by unit'!$C$1:$C$400,'Service Duration by unit'!$A$1:$A$400,$J6,'Service Duration by unit'!$C$1:$C$400,">="&IF($H6=$M$4,N$4,N$3)))),1))*$L6/3600)*(1+$M6)} -> 0 | BT6: {=(IF($H6=$M$4,N$4*$I6,N$3*$I6)+(INDEX(_xlfn._xlws.FILTER('Service Duration by unit'!$D$1:$D$400,('Service Duration by unit'!$A$1:$A$400=$J6)*('Service Duration by unit'!$C$1:$C$400=_xlfn.MINIFS('Service Duration by unit'!$C$1:$C$400,'Service Duration by unit'!$A$1:$A$400,$J6,'Service Duration by unit'!$C$1:$C$400,">="&IF($H6=$M$4,N$4,N$3)))),1))*$L6/3600)*(1+$M6)} -> 0 | BU6: {=(IF($H6=$M$4,N$4*$I6,N$3*$I6)+(INDEX(_xlfn._xlws.FILTER('Service Duration by unit'!$D$1:$D$400,('Service Duration by unit'!$A$1:$A$400=$J6)*('Service Duration by unit'!$C$1:$C$400=_xlfn.MINIFS('Service Duration by unit'!$C$1:$C$400,'Service Duration by unit'!$A$1:$A$400,$J6,'Service Duration by unit'!$C$1:$C$400,">="&IF($H6=$M$4,N$4,N$3)))),1))*$L6/3600)*(1+$M6)} -> 0 | BV6: {=(IF($H6=$M$4,N$4*$I6,N$3*$I6)+(INDEX(_xlfn._xlws.FILTER('Service Duration by unit'!$D$1:$D$400,('Service Duration by unit'!$A$1:$A$400=$J6)*('Service Duration by unit'!$C$1:$C$400=_xlfn.MINIFS('Service Duration by unit'!$C$1:$C$400,'Service Duration by unit'!$A$1:$A$400,$J6,'Service Duration by unit'!$C$1:$C$400,">="&IF($H6=$M$4,N$4,N$3)))),1))*$L6/3600)*(1+$M6)} -> 0 | BW6: {=(IF($H6=$M$4,N$4*$I6,N$3*$I6)+(INDEX(_xlfn._xlws.FILTER('Service Duration by unit'!$D$1:$D$400,('Service Duration by unit'!$A$1:$A$400=$J6)*('Service Duration by unit'!$C$1:$C$400=_xlfn.MINIFS('Service Duration by unit'!$C$1:$C$400,'Service Duration by unit'!$A$1:$A$400,$J6,'Service Duration by unit'!$C$1:$C$400,">="&IF($H6=$M$4,N$4,N$3)))),1))*$L6/3600)*(1+$M6)} -> 0 | BX6: {=(IF($H6=$M$4,N$4*$I6,N$3*$I6)+(INDEX(_xlfn._xlws.FILTER('Service Duration by unit'!$D$1:$D$400,('Service Duration by unit'!$A$1:$A$400=$J6)*('Service Duration by unit'!$C$1:$C$400=_xlfn.MINIFS('Service Duration by unit'!$C$1:$C$400,'Service Duration by unit'!$A$1:$A$400,$J6,'Service Duration by unit'!$C$1:$C$400,">="&IF($H6=$M$4,N$4,N$3)))),1))*$L6/3600)*(1+$M6)} -> 0 | BY6: {=(IF($H6=$M$4,N$4*$I6,N$3*$I6)+(INDEX(_xlfn._xlws.FILTER('Service Duration by unit'!$D$1:$D$400,('Service Duration by unit'!$A$1:$A$400=$J6)*('Service Duration by unit'!$C$1:$C$400=_xlfn.MINIFS('Service Duration by unit'!$C$1:$C$400,'Service Duration by unit'!$A$1:$A$400,$J6,'Service Duration by unit'!$C$1:$C$400,">="&IF($H6=$M$4,N$4,N$3)))),1))*$L6/3600)*(1+$M6)} -> 0 | BZ6: {=(IF($H6=$M$4,N$4*$I6,N$3*$I6)+(INDEX(_xlfn._xlws.FILTER('Service Duration by unit'!$D$1:$D$400,('Service Duration by unit'!$A$1:$A$400=$J6)*('Service Duration by unit'!$C$1:$C$400=_xlfn.MINIFS('Service Duration by unit'!$C$1:$C$400,'Service Duration by unit'!$A$1:$A$400,$J6,'Service Duration by unit'!$C$1:$C$400,">="&IF($H6=$M$4,N$4,N$3)))),1))*$L6/3600)*(1+$M6)} -> 0 | CA6: {=(IF($H6=$M$4,N$4*$I6,N$3*$I6)+(INDEX(_xlfn._xlws.FILTER('Service Duration by unit'!$D$1:$D$400,('Service Duration by unit'!$A$1:$A$400=$J6)*('Service Duration by unit'!$C$1:$C$400=_xlfn.MINIFS('Service Duration by unit'!$C$1:$C$400,'Service Duration by unit'!$A$1:$A$400,$J6,'Service Duration by unit'!$C$1:$C$400,">="&IF($H6=$M$4,N$4,N$3)))),1))*$L6/3600)*(1+$M6)} -> 0 | CB6: {=(IF($H6=$M$4,N$4*$I6,N$3*$I6)+(INDEX(_xlfn._xlws.FILTER('Service Duration by unit'!$D$1:$D$400,('Service Duration by unit'!$A$1:$A$400=$J6)*('Service Duration by unit'!$C$1:$C$400=_xlfn.MINIFS('Service Duration by unit'!$C$1:$C$400,'Service Duration by unit'!$A$1:$A$400,$J6,'Service Duration by unit'!$C$1:$C$400,">="&IF($H6=$M$4,N$4,N$3)))),1))*$L6/3600)*(1+$M6)} -> 0 | CC6: {=(IF($H6=$M$4,N$4*$I6,N$3*$I6)+(INDEX(_xlfn._xlws.FILTER('Service Duration by unit'!$D$1:$D$400,('Service Duration by unit'!$A$1:$A$400=$J6)*('Service Duration by unit'!$C$1:$C$400=_xlfn.MINIFS('Service Duration by unit'!$C$1:$C$400,'Service Duration by unit'!$A$1:$A$400,$J6,'Service Duration by unit'!$C$1:$C$400,">="&IF($H6=$M$4,N$4,N$3)))),1))*$L6/3600)*(1+$M6)} -> 0 | CD6: {=(IF($H6=$M$4,N$4*$I6,N$3*$I6)+(INDEX(_xlfn._xlws.FILTER('Service Duration by unit'!$D$1:$D$400,('Service Duration by unit'!$A$1:$A$400=$J6)*('Service Duration by unit'!$C$1:$C$400=_xlfn.MINIFS('Service Duration by unit'!$C$1:$C$400,'Service Duration by unit'!$A$1:$A$400,$J6,'Service Duration by unit'!$C$1:$C$400,">="&IF($H6=$M$4,N$4,N$3)))),1))*$L6/3600)*(1+$M6)} -> 0 | CE6: {=(IF($H6=$M$4,N$4*$I6,N$3*$I6)+(INDEX(_xlfn._xlws.FILTER('Service Duration by unit'!$D$1:$D$400,('Service Duration by unit'!$A$1:$A$400=$J6)*('Service Duration by unit'!$C$1:$C$400=_xlfn.MINIFS('Service Duration by unit'!$C$1:$C$400,'Service Duration by unit'!$A$1:$A$400,$J6,'Service Duration by unit'!$C$1:$C$400,">="&IF($H6=$M$4,N$4,N$3)))),1))*$L6/3600)*(1+$M6)} -> 0 | CF6: {=(IF($H6=$M$4,N$4*$I6,N$3*$I6)+(INDEX(_xlfn._xlws.FILTER('Service Duration by unit'!$D$1:$D$400,('Service Duration by unit'!$A$1:$A$400=$J6)*('Service Duration by unit'!$C$1:$C$400=_xlfn.MINIFS('Service Duration by unit'!$C$1:$C$400,'Service Duration by unit'!$A$1:$A$400,$J6,'Service Duration by unit'!$C$1:$C$400,">="&IF($H6=$M$4,N$4,N$3)))),1))*$L6/3600)*(1+$M6)} -> 0 | CG6: {=(IF($H6=$M$4,N$4*$I6,N$3*$I6)+(INDEX(_xlfn._xlws.FILTER('Service Duration by unit'!$D$1:$D$400,('Service Duration by unit'!$A$1:$A$400=$J6)*('Service Duration by unit'!$C$1:$C$400=_xlfn.MINIFS('Service Duration by unit'!$C$1:$C$400,'Service Duration by unit'!$A$1:$A$400,$J6,'Service Duration by unit'!$C$1:$C$400,">="&IF($H6=$M$4,N$4,N$3)))),1))*$L6/3600)*(1+$M6)} -> 0 | CH6: {=(IF($H6=$M$4,N$4*$I6,N$3*$I6)+(INDEX(_xlfn._xlws.FILTER('Service Duration by unit'!$D$1:$D$400,('Service Duration by unit'!$A$1:$A$400=$J6)*('Service Duration by unit'!$C$1:$C$400=_xlfn.MINIFS('Service Duration by unit'!$C$1:$C$400,'Service Duration by unit'!$A$1:$A$400,$J6,'Service Duration by unit'!$C$1:$C$400,">="&IF($H6=$M$4,N$4,N$3)))),1))*$L6/3600)*(1+$M6)} -> 0 | CI6: {=(IF($H6=$M$4,N$4*$I6,N$3*$I6)+(INDEX(_xlfn._xlws.FILTER('Service Duration by unit'!$D$1:$D$400,('Service Duration by unit'!$A$1:$A$400=$J6)*('Service Duration by unit'!$C$1:$C$400=_xlfn.MINIFS('Service Duration by unit'!$C$1:$C$400,'Service Duration by unit'!$A$1:$A$400,$J6,'Service Duration by unit'!$C$1:$C$400,">="&IF($H6=$M$4,N$4,N$3)))),1))*$L6/3600)*(1+$M6)} -> 0 | CJ6: {=(IF($H6=$M$4,N$4*$I6,N$3*$I6)+(INDEX(_xlfn._xlws.FILTER('Service Duration by unit'!$D$1:$D$400,('Service Duration by unit'!$A$1:$A$400=$J6)*('Service Duration by unit'!$C$1:$C$400=_xlfn.MINIFS('Service Duration by unit'!$C$1:$C$400,'Service Duration by unit'!$A$1:$A$400,$J6,'Service Duration by unit'!$C$1:$C$400,">="&IF($H6=$M$4,N$4,N$3)))),1))*$L6/3600)*(1+$M6)} -> 0 | CK6: {=(IF($H6=$M$4,N$4*$I6,N$3*$I6)+(INDEX(_xlfn._xlws.FILTER('Service Duration by unit'!$D$1:$D$400,('Service Duration by unit'!$A$1:$A$400=$J6)*('Service Duration by unit'!$C$1:$C$400=_xlfn.MINIFS('Service Duration by unit'!$C$1:$C$400,'Service Duration by unit'!$A$1:$A$400,$J6,'Service Duration by unit'!$C$1:$C$400,">="&IF($H6=$M$4,N$4,N$3)))),1))*$L6/3600)*(1+$M6)} -> 0 | CL6: {=(IF($H6=$M$4,N$4*$I6,N$3*$I6)+(INDEX(_xlfn._xlws.FILTER('Service Duration by unit'!$D$1:$D$400,('Service Duration by unit'!$A$1:$A$400=$J6)*('Service Duration by unit'!$C$1:$C$400=_xlfn.MINIFS('Service Duration by unit'!$C$1:$C$400,'Service Duration by unit'!$A$1:$A$400,$J6,'Service Duration by unit'!$C$1:$C$400,">="&IF($H6=$M$4,N$4,N$3)))),1))*$L6/3600)*(1+$M6)} -> 0 | CM6: {=(IF($H6=$M$4,N$4*$I6,N$3*$I6)+(INDEX(_xlfn._xlws.FILTER('Service Duration by unit'!$D$1:$D$400,('Service Duration by unit'!$A$1:$A$400=$J6)*('Service Duration by unit'!$C$1:$C$400=_xlfn.MINIFS('Service Duration by unit'!$C$1:$C$400,'Service Duration by unit'!$A$1:$A$400,$J6,'Service Duration by unit'!$C$1:$C$400,">="&IF($H6=$M$4,N$4,N$3)))),1))*$L6/3600)*(1+$M6)} -> 0 | CN6: {=(IF($H6=$M$4,N$4*$I6,N$3*$I6)+(INDEX(_xlfn._xlws.FILTER('Service Duration by unit'!$D$1:$D$400,('Service Duration by unit'!$A$1:$A$400=$J6)*('Service Duration by unit'!$C$1:$C$400=_xlfn.MINIFS('Service Duration by unit'!$C$1:$C$400,'Service Duration by unit'!$A$1:$A$400,$J6,'Service Duration by unit'!$C$1:$C$400,">="&IF($H6=$M$4,N$4,N$3)))),1))*$L6/3600)*(1+$M6)} -> 0 | CO6: {=(IF($H6=$M$4,N$4*$I6,N$3*$I6)+(INDEX(_xlfn._xlws.FILTER('Service Duration by unit'!$D$1:$D$400,('Service Duration by unit'!$A$1:$A$400=$J6)*('Service Duration by unit'!$C$1:$C$400=_xlfn.MINIFS('Service Duration by unit'!$C$1:$C$400,'Service Duration by unit'!$A$1:$A$400,$J6,'Service Duration by unit'!$C$1:$C$400,">="&IF($H6=$M$4,N$4,N$3)))),1))*$L6/3600)*(1+$M6)} -> 0 | CP6: {=(IF($H6=$M$4,N$4*$I6,N$3*$I6)+(INDEX(_xlfn._xlws.FILTER('Service Duration by unit'!$D$1:$D$400,('Service Duration by unit'!$A$1:$A$400=$J6)*('Service Duration by unit'!$C$1:$C$400=_xlfn.MINIFS('Service Duration by unit'!$C$1:$C$400,'Service Duration by unit'!$A$1:$A$400,$J6,'Service Duration by unit'!$C$1:$C$400,">="&IF($H6=$M$4,N$4,N$3)))),1))*$L6/3600)*(1+$M6)} -> 0 | CQ6: {=(IF($H6=$M$4,N$4*$I6,N$3*$I6)+(INDEX(_xlfn._xlws.FILTER('Service Duration by unit'!$D$1:$D$400,('Service Duration by unit'!$A$1:$A$400=$J6)*('Service Duration by unit'!$C$1:$C$400=_xlfn.MINIFS('Service Duration by unit'!$C$1:$C$400,'Service Duration by unit'!$A$1:$A$400,$J6,'Service Duration by unit'!$C$1:$C$400,">="&IF($H6=$M$4,N$4,N$3)))),1))*$L6/3600)*(1+$M6)} -> 0 | CR6: {=(IF($H6=$M$4,N$4*$I6,N$3*$I6)+(INDEX(_xlfn._xlws.FILTER('Service Duration by unit'!$D$1:$D$400,('Service Duration by unit'!$A$1:$A$400=$J6)*('Service Duration by unit'!$C$1:$C$400=_xlfn.MINIFS('Service Duration by unit'!$C$1:$C$400,'Service Duration by unit'!$A$1:$A$400,$J6,'Service Duration by unit'!$C$1:$C$400,">="&IF($H6=$M$4,N$4,N$3)))),1))*$L6/3600)*(1+$M6)} -> 0 | CS6: {=(IF($H6=$M$4,N$4*$I6,N$3*$I6)+(INDEX(_xlfn._xlws.FILTER('Service Duration by unit'!$D$1:$D$400,('Service Duration by unit'!$A$1:$A$400=$J6)*('Service Duration by unit'!$C$1:$C$400=_xlfn.MINIFS('Service Duration by unit'!$C$1:$C$400,'Service Duration by unit'!$A$1:$A$400,$J6,'Service Duration by unit'!$C$1:$C$400,">="&IF($H6=$M$4,N$4,N$3)))),1))*$L6/3600)*(1+$M6)} -> 0 | CT6: {=(IF($H6=$M$4,N$4*$I6,N$3*$I6)+(INDEX(_xlfn._xlws.FILTER('Service Duration by unit'!$D$1:$D$400,('Service Duration by unit'!$A$1:$A$400=$J6)*('Service Duration by unit'!$C$1:$C$400=_xlfn.MINIFS('Service Duration by unit'!$C$1:$C$400,'Service Duration by unit'!$A$1:$A$400,$J6,'Service Duration by unit'!$C$1:$C$400,">="&IF($H6=$M$4,N$4,N$3)))),1))*$L6/3600)*(1+$M6)} -> 0 | CU6: {=(IF($H6=$M$4,N$4*$I6,N$3*$I6)+(INDEX(_xlfn._xlws.FILTER('Service Duration by unit'!$D$1:$D$400,('Service Duration by unit'!$A$1:$A$400=$J6)*('Service Duration by unit'!$C$1:$C$400=_xlfn.MINIFS('Service Duration by unit'!$C$1:$C$400,'Service Duration by unit'!$A$1:$A$400,$J6,'Service Duration by unit'!$C$1:$C$400,">="&IF($H6=$M$4,N$4,N$3)))),1))*$L6/3600)*(1+$M6)} -> 0 | CV6: {=(IF($H6=$M$4,N$4*$I6,N$3*$I6)+(INDEX(_xlfn._xlws.FILTER('Service Duration by unit'!$D$1:$D$400,('Service Duration by unit'!$A$1:$A$400=$J6)*('Service Duration by unit'!$C$1:$C$400=_xlfn.MINIFS('Service Duration by unit'!$C$1:$C$400,'Service Duration by unit'!$A$1:$A$400,$J6,'Service Duration by unit'!$C$1:$C$400,">="&IF($H6=$M$4,N$4,N$3)))),1))*$L6/3600)*(1+$M6)} -> 0 | CW6: {=(IF($H6=$M$4,N$4*$I6,N$3*$I6)+(INDEX(_xlfn._xlws.FILTER('Service Duration by unit'!$D$1:$D$400,('Service Duration by unit'!$A$1:$A$400=$J6)*('Service Duration by unit'!$C$1:$C$400=_xlfn.MINIFS('Service Duration by unit'!$C$1:$C$400,'Service Duration by unit'!$A$1:$A$400,$J6,'Service Duration by unit'!$C$1:$C$400,">="&IF($H6=$M$4,N$4,N$3)))),1))*$L6/3600)*(1+$M6)} -> 0 | CX6: {=(IF($H6=$M$4,N$4*$I6,N$3*$I6)+(INDEX(_xlfn._xlws.FILTER('Service Duration by unit'!$D$1:$D$400,('Service Duration by unit'!$A$1:$A$400=$J6)*('Service Duration by unit'!$C$1:$C$400=_xlfn.MINIFS('Service Duration by unit'!$C$1:$C$400,'Service Duration by unit'!$A$1:$A$400,$J6,'Service Duration by unit'!$C$1:$C$400,">="&IF($H6=$M$4,N$4,N$3)))),1))*$L6/3600)*(1+$M6)} -> 0 | CY6: {=(IF($H6=$M$4,N$4*$I6,N$3*$I6)+(INDEX(_xlfn._xlws.FILTER('Service Duration by unit'!$D$1:$D$400,('Service Duration by unit'!$A$1:$A$400=$J6)*('Service Duration by unit'!$C$1:$C$400=_xlfn.MINIFS('Service Duration by unit'!$C$1:$C$400,'Service Duration by unit'!$A$1:$A$400,$J6,'Service Duration by unit'!$C$1:$C$400,">="&IF($H6=$M$4,N$4,N$3)))),1))*$L6/3600)*(1+$M6)} -> 0 | CZ6: {=(IF($H6=$M$4,N$4*$I6,N$3*$I6)+(INDEX(_xlfn._xlws.FILTER('Service Duration by unit'!$D$1:$D$400,('Service Duration by unit'!$A$1:$A$400=$J6)*('Service Duration by unit'!$C$1:$C$400=_xlfn.MINIFS('Service Duration by unit'!$C$1:$C$400,'Service Duration by unit'!$A$1:$A$400,$J6,'Service Duration by unit'!$C$1:$C$400,">="&IF($H6=$M$4,N$4,N$3)))),1))*$L6/3600)*(1+$M6)} -> 0 | DA6: {=(IF($H6=$M$4,N$4*$I6,N$3*$I6)+(INDEX(_xlfn._xlws.FILTER('Service Duration by unit'!$D$1:$D$400,('Service Duration by unit'!$A$1:$A$400=$J6)*('Service Duration by unit'!$C$1:$C$400=_xlfn.MINIFS('Service Duration by unit'!$C$1:$C$400,'Service Duration by unit'!$A$1:$A$400,$J6,'Service Duration by unit'!$C$1:$C$400,">="&IF($H6=$M$4,N$4,N$3)))),1))*$L6/3600)*(1+$M6)} -> 0 | DB6: {=(IF($H6=$M$4,N$4*$I6,N$3*$I6)+(INDEX(_xlfn._xlws.FILTER('Service Duration by unit'!$D$1:$D$400,('Service Duration by unit'!$A$1:$A$400=$J6)*('Service Duration by unit'!$C$1:$C$400=_xlfn.MINIFS('Service Duration by unit'!$C$1:$C$400,'Service Duration by unit'!$A$1:$A$400,$J6,'Service Duration by unit'!$C$1:$C$400,">="&IF($H6=$M$4,N$4,N$3)))),1))*$L6/3600)*(1+$M6)} -> 0 | DC6: {=(IF($H6=$M$4,N$4*$I6,N$3*$I6)+(INDEX(_xlfn._xlws.FILTER('Service Duration by unit'!$D$1:$D$400,('Service Duration by unit'!$A$1:$A$400=$J6)*('Service Duration by unit'!$C$1:$C$400=_xlfn.MINIFS('Service Duration by unit'!$C$1:$C$400,'Service Duration by unit'!$A$1:$A$400,$J6,'Service Duration by unit'!$C$1:$C$400,">="&IF($H6=$M$4,N$4,N$3)))),1))*$L6/3600)*(1+$M6)} -> 0 | DD6: {=(IF($H6=$M$4,N$4*$I6,N$3*$I6)+(INDEX(_xlfn._xlws.FILTER('Service Duration by unit'!$D$1:$D$400,('Service Duration by unit'!$A$1:$A$400=$J6)*('Service Duration by unit'!$C$1:$C$400=_xlfn.MINIFS('Service Duration by unit'!$C$1:$C$400,'Service Duration by unit'!$A$1:$A$400,$J6,'Service Duration by unit'!$C$1:$C$400,">="&IF($H6=$M$4,N$4,N$3)))),1))*$L6/3600)*(1+$M6)} -> 0 | DE6: {=(IF($H6=$M$4,N$4*$I6,N$3*$I6)+(INDEX(_xlfn._xlws.FILTER('Service Duration by unit'!$D$1:$D$400,('Service Duration by unit'!$A$1:$A$400=$J6)*('Service Duration by unit'!$C$1:$C$400=_xlfn.MINIFS('Service Duration by unit'!$C$1:$C$400,'Service Duration by unit'!$A$1:$A$400,$J6,'Service Duration by unit'!$C$1:$C$400,">="&IF($H6=$M$4,N$4,N$3)))),1))*$L6/3600)*(1+$M6)} -> 0 | DF6: {=(IF($H6=$M$4,N$4*$I6,N$3*$I6)+(INDEX(_xlfn._xlws.FILTER('Service Duration by unit'!$D$1:$D$400,('Service Duration by unit'!$A$1:$A$400=$J6)*('Service Duration by unit'!$C$1:$C$400=_xlfn.MINIFS('Service Duration by unit'!$C$1:$C$400,'Service Duration by unit'!$A$1:$A$400,$J6,'Service Duration by unit'!$C$1:$C$400,">="&IF($H6=$M$4,N$4,N$3)))),1))*$L6/3600)*(1+$M6)} -> 0 | DG6: {=(IF($H6=$M$4,N$4*$I6,N$3*$I6)+(INDEX(_xlfn._xlws.FILTER('Service Duration by unit'!$D$1:$D$400,('Service Duration by unit'!$A$1:$A$400=$J6)*('Service Duration by unit'!$C$1:$C$400=_xlfn.MINIFS('Service Duration by unit'!$C$1:$C$400,'Service Duration by unit'!$A$1:$A$400,$J6,'Service Duration by unit'!$C$1:$C$400,">="&IF($H6=$M$4,N$4,N$3)))),1))*$L6/3600)*(1+$M6)} -> 0 | DH6: {=(IF($H6=$M$4,N$4*$I6,N$3*$I6)+(INDEX(_xlfn._xlws.FILTER('Service Duration by unit'!$D$1:$D$400,('Service Duration by unit'!$A$1:$A$400=$J6)*('Service Duration by unit'!$C$1:$C$400=_xlfn.MINIFS('Service Duration by unit'!$C$1:$C$400,'Service Duration by unit'!$A$1:$A$400,$J6,'Service Duration by unit'!$C$1:$C$400,">="&IF($H6=$M$4,N$4,N$3)))),1))*$L6/3600)*(1+$M6)} -> 0 | DI6: {=(IF($H6=$M$4,N$4*$I6,N$3*$I6)+(INDEX(_xlfn._xlws.FILTER('Service Duration by unit'!$D$1:$D$400,('Service Duration by unit'!$A$1:$A$400=$J6)*('Service Duration by unit'!$C$1:$C$400=_xlfn.MINIFS('Service Duration by unit'!$C$1:$C$400,'Service Duration by unit'!$A$1:$A$400,$J6,'Service Duration by unit'!$C$1:$C$400,">="&IF($H6=$M$4,N$4,N$3)))),1))*$L6/3600)*(1+$M6)} -> 0 | DJ6: {=(IF($H6=$M$4,N$4*$I6,N$3*$I6)+(INDEX(_xlfn._xlws.FILTER('Service Duration by unit'!$D$1:$D$400,('Service Duration by unit'!$A$1:$A$400=$J6)*('Service Duration by unit'!$C$1:$C$400=_xlfn.MINIFS('Service Duration by unit'!$C$1:$C$400,'Service Duration by unit'!$A$1:$A$400,$J6,'Service Duration by unit'!$C$1:$C$400,">="&IF($H6=$M$4,N$4,N$3)))),1))*$L6/3600)*(1+$M6)} -> 0 | DK6: {=(IF($H6=$M$4,N$4*$I6,N$3*$I6)+(INDEX(_xlfn._xlws.FILTER('Service Duration by unit'!$D$1:$D$400,('Service Duration by unit'!$A$1:$A$400=$J6)*('Service Duration by unit'!$C$1:$C$400=_xlfn.MINIFS('Service Duration by unit'!$C$1:$C$400,'Service Duration by unit'!$A$1:$A$400,$J6,'Service Duration by unit'!$C$1:$C$400,">="&IF($H6=$M$4,N$4,N$3)))),1))*$L6/3600)*(1+$M6)} -> 0 | DL6: {=(IF($H6=$M$4,N$4*$I6,N$3*$I6)+(INDEX(_xlfn._xlws.FILTER('Service Duration by unit'!$D$1:$D$400,('Service Duration by unit'!$A$1:$A$400=$J6)*('Service Duration by unit'!$C$1:$C$400=_xlfn.MINIFS('Service Duration by unit'!$C$1:$C$400,'Service Duration by unit'!$A$1:$A$400,$J6,'Service Duration by unit'!$C$1:$C$400,">="&IF($H6=$M$4,N$4,N$3)))),1))*$L6/3600)*(1+$M6)} -> 0 | DM6: {=(IF($H6=$M$4,N$4*$I6,N$3*$I6)+(INDEX(_xlfn._xlws.FILTER('Service Duration by unit'!$D$1:$D$400,('Service Duration by unit'!$A$1:$A$400=$J6)*('Service Duration by unit'!$C$1:$C$400=_xlfn.MINIFS('Service Duration by unit'!$C$1:$C$400,'Service Duration by unit'!$A$1:$A$400,$J6,'Service Duration by unit'!$C$1:$C$400,">="&IF($H6=$M$4,N$4,N$3)))),1))*$L6/3600)*(1+$M6)} -> 0 | DN6: {=(IF($H6=$M$4,N$4*$I6,N$3*$I6)+(INDEX(_xlfn._xlws.FILTER('Service Duration by unit'!$D$1:$D$400,('Service Duration by unit'!$A$1:$A$400=$J6)*('Service Duration by unit'!$C$1:$C$400=_xlfn.MINIFS('Service Duration by unit'!$C$1:$C$400,'Service Duration by unit'!$A$1:$A$400,$J6,'Service Duration by unit'!$C$1:$C$400,">="&IF($H6=$M$4,N$4,N$3)))),1))*$L6/3600)*(1+$M6)} -> 0 | DO6: {=(IF($H6=$M$4,N$4*$I6,N$3*$I6)+(INDEX(_xlfn._xlws.FILTER('Service Duration by unit'!$D$1:$D$400,('Service Duration by unit'!$A$1:$A$400=$J6)*('Service Duration by unit'!$C$1:$C$400=_xlfn.MINIFS('Service Duration by unit'!$C$1:$C$400,'Service Duration by unit'!$A$1:$A$400,$J6,'Service Duration by unit'!$C$1:$C$400,">="&IF($H6=$M$4,N$4,N$3)))),1))*$L6/3600)*(1+$M6)} -> 0 | DP6: {=(IF($H6=$M$4,N$4*$I6,N$3*$I6)+(INDEX(_xlfn._xlws.FILTER('Service Duration by unit'!$D$1:$D$400,('Service Duration by unit'!$A$1:$A$400=$J6)*('Service Duration by unit'!$C$1:$C$400=_xlfn.MINIFS('Service Duration by unit'!$C$1:$C$400,'Service Duration by unit'!$A$1:$A$400,$J6,'Service Duration by unit'!$C$1:$C$400,">="&IF($H6=$M$4,N$4,N$3)))),1))*$L6/3600)*(1+$M6)} -> 0 | DQ6: {=(IF($H6=$M$4,N$4*$I6,N$3*$I6)+(INDEX(_xlfn._xlws.FILTER('Service Duration by unit'!$D$1:$D$400,('Service Duration by unit'!$A$1:$A$400=$J6)*('Service Duration by unit'!$C$1:$C$400=_xlfn.MINIFS('Service Duration by unit'!$C$1:$C$400,'Service Duration by unit'!$A$1:$A$400,$J6,'Service Duration by unit'!$C$1:$C$400,">="&IF($H6=$M$4,N$4,N$3)))),1))*$L6/3600)*(1+$M6)} -> 0 | DR6: {=(IF($H6=$M$4,N$4*$I6,N$3*$I6)+(INDEX(_xlfn._xlws.FILTER('Service Duration by unit'!$D$1:$D$400,('Service Duration by unit'!$A$1:$A$400=$J6)*('Service Duration by unit'!$C$1:$C$400=_xlfn.MINIFS('Service Duration by unit'!$C$1:$C$400,'Service Duration by unit'!$A$1:$A$400,$J6,'Service Duration by unit'!$C$1:$C$400,">="&IF($H6=$M$4,N$4,N$3)))),1))*$L6/3600)*(1+$M6)} -> 0 | DS6: {=(IF($H6=$M$4,N$4*$I6,N$3*$I6)+(INDEX(_xlfn._xlws.FILTER('Service Duration by unit'!$D$1:$D$400,('Service Duration by unit'!$A$1:$A$400=$J6)*('Service Duration by unit'!$C$1:$C$400=_xlfn.MINIFS('Service Duration by unit'!$C$1:$C$400,'Service Duration by unit'!$A$1:$A$400,$J6,'Service Duration by unit'!$C$1:$C$400,">="&IF($H6=$M$4,N$4,N$3)))),1))*$L6/3600)*(1+$M6)} -> 0 | DT6: {=(IF($H6=$M$4,N$4*$I6,N$3*$I6)+(INDEX(_xlfn._xlws.FILTER('Service Duration by unit'!$D$1:$D$400,('Service Duration by unit'!$A$1:$A$400=$J6)*('Service Duration by unit'!$C$1:$C$400=_xlfn.MINIFS('Service Duration by unit'!$C$1:$C$400,'Service Duration by unit'!$A$1:$A$400,$J6,'Service Duration by unit'!$C$1:$C$400,">="&IF($H6=$M$4,N$4,N$3)))),1))*$L6/3600)*(1+$M6)} -> 0 | DU6: {=(IF($H6=$M$4,N$4*$I6,N$3*$I6)+(INDEX(_xlfn._xlws.FILTER('Service Duration by unit'!$D$1:$D$400,('Service Duration by unit'!$A$1:$A$400=$J6)*('Service Duration by unit'!$C$1:$C$400=_xlfn.MINIFS('Service Duration by unit'!$C$1:$C$400,'Service Duration by unit'!$A$1:$A$400,$J6,'Service Duration by unit'!$C$1:$C$400,">="&IF($H6=$M$4,N$4,N$3)))),1))*$L6/3600)*(1+$M6)} -> 0 | DV6: {=(IF($H6=$M$4,N$4*$I6,N$3*$I6)+(INDEX(_xlfn._xlws.FILTER('Service Duration by unit'!$D$1:$D$400,('Service Duration by unit'!$A$1:$A$400=$J6)*('Service Duration by unit'!$C$1:$C$400=_xlfn.MINIFS('Service Duration by unit'!$C$1:$C$400,'Service Duration by unit'!$A$1:$A$400,$J6,'Service Duration by unit'!$C$1:$C$400,">="&IF($H6=$M$4,N$4,N$3)))),1))*$L6/3600)*(1+$M6)} -> 0 | DW6: {=(IF($H6=$M$4,N$4*$I6,N$3*$I6)+(INDEX(_xlfn._xlws.FILTER('Service Duration by unit'!$D$1:$D$400,('Service Duration by unit'!$A$1:$A$400=$J6)*('Service Duration by unit'!$C$1:$C$400=_xlfn.MINIFS('Service Duration by unit'!$C$1:$C$400,'Service Duration by unit'!$A$1:$A$400,$J6,'Service Duration by unit'!$C$1:$C$400,">="&IF($H6=$M$4,N$4,N$3)))),1))*$L6/3600)*(1+$M6)} -> 0 | DX6: {=(IF($H6=$M$4,N$4*$I6,N$3*$I6)+(INDEX(_xlfn._xlws.FILTER('Service Duration by unit'!$D$1:$D$400,('Service Duration by unit'!$A$1:$A$400=$J6)*('Service Duration by unit'!$C$1:$C$400=_xlfn.MINIFS('Service Duration by unit'!$C$1:$C$400,'Service Duration by unit'!$A$1:$A$400,$J6,'Service Duration by unit'!$C$1:$C$400,">="&IF($H6=$M$4,N$4,N$3)))),1))*$L6/3600)*(1+$M6)} -> 0 | DY6: {=(IF($H6=$M$4,N$4*$I6,N$3*$I6)+(INDEX(_xlfn._xlws.FILTER('Service Duration by unit'!$D$1:$D$400,('Service Duration by unit'!$A$1:$A$400=$J6)*('Service Duration by unit'!$C$1:$C$400=_xlfn.MINIFS('Service Duration by unit'!$C$1:$C$400,'Service Duration by unit'!$A$1:$A$400,$J6,'Service Duration by unit'!$C$1:$C$400,">="&IF($H6=$M$4,N$4,N$3)))),1))*$L6/3600)*(1+$M6)} -> 0 | DZ6: {=(IF($H6=$M$4,N$4*$I6,N$3*$I6)+(INDEX(_xlfn._xlws.FILTER('Service Duration by unit'!$D$1:$D$400,('Service Duration by unit'!$A$1:$A$400=$J6)*('Service Duration by unit'!$C$1:$C$400=_xlfn.MINIFS('Service Duration by unit'!$C$1:$C$400,'Service Duration by unit'!$A$1:$A$400,$J6,'Service Duration by unit'!$C$1:$C$400,">="&IF($H6=$M$4,N$4,N$3)))),1))*$L6/3600)*(1+$M6)} -> 0 | EA6: {=(IF($H6=$M$4,N$4*$I6,N$3*$I6)+(INDEX(_xlfn._xlws.FILTER('Service Duration by unit'!$D$1:$D$400,('Service Duration by unit'!$A$1:$A$400=$J6)*('Service Duration by unit'!$C$1:$C$400=_xlfn.MINIFS('Service Duration by unit'!$C$1:$C$400,'Service Duration by unit'!$A$1:$A$400,$J6,'Service Duration by unit'!$C$1:$C$400,">="&IF($H6=$M$4,N$4,N$3)))),1))*$L6/3600)*(1+$M6)} -> 0 | EB6: {=(IF($H6=$M$4,N$4*$I6,N$3*$I6)+(INDEX(_xlfn._xlws.FILTER('Service Duration by unit'!$D$1:$D$400,('Service Duration by unit'!$A$1:$A$400=$J6)*('Service Duration by unit'!$C$1:$C$400=_xlfn.MINIFS('Service Duration by unit'!$C$1:$C$400,'Service Duration by unit'!$A$1:$A$400,$J6,'Service Duration by unit'!$C$1:$C$400,">="&IF($H6=$M$4,N$4,N$3)))),1))*$L6/3600)*(1+$M6)} -> 0 | EC6: {=(IF($H6=$M$4,N$4*$I6,N$3*$I6)+(INDEX(_xlfn._xlws.FILTER('Service Duration by unit'!$D$1:$D$400,('Service Duration by unit'!$A$1:$A$400=$J6)*('Service Duration by unit'!$C$1:$C$400=_xlfn.MINIFS('Service Duration by unit'!$C$1:$C$400,'Service Duration by unit'!$A$1:$A$400,$J6,'Service Duration by unit'!$C$1:$C$400,">="&IF($H6=$M$4,N$4,N$3)))),1))*$L6/3600)*(1+$M6)} -> 0 | ED6: {=(IF($H6=$M$4,N$4*$I6,N$3*$I6)+(INDEX(_xlfn._xlws.FILTER('Service Duration by unit'!$D$1:$D$400,('Service Duration by unit'!$A$1:$A$400=$J6)*('Service Duration by unit'!$C$1:$C$400=_xlfn.MINIFS('Service Duration by unit'!$C$1:$C$400,'Service Duration by unit'!$A$1:$A$400,$J6,'Service Duration by unit'!$C$1:$C$400,">="&IF($H6=$M$4,N$4,N$3)))),1))*$L6/3600)*(1+$M6)} -> 0 | EE6: {=(IF($H6=$M$4,N$4*$I6,N$3*$I6)+(INDEX(_xlfn._xlws.FILTER('Service Duration by unit'!$D$1:$D$400,('Service Duration by unit'!$A$1:$A$400=$J6)*('Service Duration by unit'!$C$1:$C$400=_xlfn.MINIFS('Service Duration by unit'!$C$1:$C$400,'Service Duration by unit'!$A$1:$A$400,$J6,'Service Duration by unit'!$C$1:$C$400,">="&IF($H6=$M$4,N$4,N$3)))),1))*$L6/3600)*(1+$M6)} -> 0 | EF6: {=(IF($H6=$M$4,N$4*$I6,N$3*$I6)+(INDEX(_xlfn._xlws.FILTER('Service Duration by unit'!$D$1:$D$400,('Service Duration by unit'!$A$1:$A$400=$J6)*('Service Duration by unit'!$C$1:$C$400=_xlfn.MINIFS('Service Duration by unit'!$C$1:$C$400,'Service Duration by unit'!$A$1:$A$400,$J6,'Service Duration by unit'!$C$1:$C$400,">="&IF($H6=$M$4,N$4,N$3)))),1))*$L6/3600)*(1+$M6)} -> 0 | EG6: {=(IF($H6=$M$4,N$4*$I6,N$3*$I6)+(INDEX(_xlfn._xlws.FILTER('Service Duration by unit'!$D$1:$D$400,('Service Duration by unit'!$A$1:$A$400=$J6)*('Service Duration by unit'!$C$1:$C$400=_xlfn.MINIFS('Service Duration by unit'!$C$1:$C$400,'Service Duration by unit'!$A$1:$A$400,$J6,'Service Duration by unit'!$C$1:$C$400,">="&IF($H6=$M$4,N$4,N$3)))),1))*$L6/3600)*(1+$M6)} -> 0 | EH6: {=(IF($H6=$M$4,N$4*$I6,N$3*$I6)+(INDEX(_xlfn._xlws.FILTER('Service Duration by unit'!$D$1:$D$400,('Service Duration by unit'!$A$1:$A$400=$J6)*('Service Duration by unit'!$C$1:$C$400=_xlfn.MINIFS('Service Duration by unit'!$C$1:$C$400,'Service Duration by unit'!$A$1:$A$400,$J6,'Service Duration by unit'!$C$1:$C$400,">="&IF($H6=$M$4,N$4,N$3)))),1))*$L6/3600)*(1+$M6)} -> 0 | EI6: {=(IF($H6=$M$4,N$4*$I6,N$3*$I6)+(INDEX(_xlfn._xlws.FILTER('Service Duration by unit'!$D$1:$D$400,('Service Duration by unit'!$A$1:$A$400=$J6)*('Service Duration by unit'!$C$1:$C$400=_xlfn.MINIFS('Service Duration by unit'!$C$1:$C$400,'Service Duration by unit'!$A$1:$A$400,$J6,'Service Duration by unit'!$C$1:$C$400,">="&IF($H6=$M$4,N$4,N$3)))),1))*$L6/3600)*(1+$M6)} -> 0 | EJ6: {=(IF($H6=$M$4,N$4*$I6,N$3*$I6)+(INDEX(_xlfn._xlws.FILTER('Service Duration by unit'!$D$1:$D$400,('Service Duration by unit'!$A$1:$A$400=$J6)*('Service Duration by unit'!$C$1:$C$400=_xlfn.MINIFS('Service Duration by unit'!$C$1:$C$400,'Service Duration by unit'!$A$1:$A$400,$J6,'Service Duration by unit'!$C$1:$C$400,">="&IF($H6=$M$4,N$4,N$3)))),1))*$L6/3600)*(1+$M6)} -> 0 | EK6: {=(IF($H6=$M$4,N$4*$I6,N$3*$I6)+(INDEX(_xlfn._xlws.FILTER('Service Duration by unit'!$D$1:$D$400,('Service Duration by unit'!$A$1:$A$400=$J6)*('Service Duration by unit'!$C$1:$C$400=_xlfn.MINIFS('Service Duration by unit'!$C$1:$C$400,'Service Duration by unit'!$A$1:$A$400,$J6,'Service Duration by unit'!$C$1:$C$400,">="&IF($H6=$M$4,N$4,N$3)))),1))*$L6/3600)*(1+$M6)} -> 0 | EL6: {=(IF($H6=$M$4,N$4*$I6,N$3*$I6)+(INDEX(_xlfn._xlws.FILTER('Service Duration by unit'!$D$1:$D$400,('Service Duration by unit'!$A$1:$A$400=$J6)*('Service Duration by unit'!$C$1:$C$400=_xlfn.MINIFS('Service Duration by unit'!$C$1:$C$400,'Service Duration by unit'!$A$1:$A$400,$J6,'Service Duration by unit'!$C$1:$C$400,">="&IF($H6=$M$4,N$4,N$3)))),1))*$L6/3600)*(1+$M6)} -> 0 | EM6: {=(IF($H6=$M$4,N$4*$I6,N$3*$I6)+(INDEX(_xlfn._xlws.FILTER('Service Duration by unit'!$D$1:$D$400,('Service Duration by unit'!$A$1:$A$400=$J6)*('Service Duration by unit'!$C$1:$C$400=_xlfn.MINIFS('Service Duration by unit'!$C$1:$C$400,'Service Duration by unit'!$A$1:$A$400,$J6,'Service Duration by unit'!$C$1:$C$400,">="&IF($H6=$M$4,N$4,N$3)))),1))*$L6/3600)*(1+$M6)} -> 0 | EN6: {=(IF($H6=$M$4,N$4*$I6,N$3*$I6)+(INDEX(_xlfn._xlws.FILTER('Service Duration by unit'!$D$1:$D$400,('Service Duration by unit'!$A$1:$A$400=$J6)*('Service Duration by unit'!$C$1:$C$400=_xlfn.MINIFS('Service Duration by unit'!$C$1:$C$400,'Service Duration by unit'!$A$1:$A$400,$J6,'Service Duration by unit'!$C$1:$C$400,">="&IF($H6=$M$4,N$4,N$3)))),1))*$L6/3600)*(1+$M6)} -> 0 | EO6: {=(IF($H6=$M$4,N$4*$I6,N$3*$I6)+(INDEX(_xlfn._xlws.FILTER('Service Duration by unit'!$D$1:$D$400,('Service Duration by unit'!$A$1:$A$400=$J6)*('Service Duration by unit'!$C$1:$C$400=_xlfn.MINIFS('Service Duration by unit'!$C$1:$C$400,'Service Duration by unit'!$A$1:$A$400,$J6,'Service Duration by unit'!$C$1:$C$400,">="&IF($H6=$M$4,N$4,N$3)))),1))*$L6/3600)*(1+$M6)} -> 0 | EP6: {=(IF($H6=$M$4,N$4*$I6,N$3*$I6)+(INDEX(_xlfn._xlws.FILTER('Service Duration by unit'!$D$1:$D$400,('Service Duration by unit'!$A$1:$A$400=$J6)*('Service Duration by unit'!$C$1:$C$400=_xlfn.MINIFS('Service Duration by unit'!$C$1:$C$400,'Service Duration by unit'!$A$1:$A$400,$J6,'Service Duration by unit'!$C$1:$C$400,">="&IF($H6=$M$4,N$4,N$3)))),1))*$L6/3600)*(1+$M6)} -> 0 | EQ6: {=(IF($H6=$M$4,N$4*$I6,N$3*$I6)+(INDEX(_xlfn._xlws.FILTER('Service Duration by unit'!$D$1:$D$400,('Service Duration by unit'!$A$1:$A$400=$J6)*('Service Duration by unit'!$C$1:$C$400=_xlfn.MINIFS('Service Duration by unit'!$C$1:$C$400,'Service Duration by unit'!$A$1:$A$400,$J6,'Service Duration by unit'!$C$1:$C$400,">="&IF($H6=$M$4,N$4,N$3)))),1))*$L6/3600)*(1+$M6)} -> 0 | ER6: {=(IF($H6=$M$4,N$4*$I6,N$3*$I6)+(INDEX(_xlfn._xlws.FILTER('Service Duration by unit'!$D$1:$D$400,('Service Duration by unit'!$A$1:$A$400=$J6)*('Service Duration by unit'!$C$1:$C$400=_xlfn.MINIFS('Service Duration by unit'!$C$1:$C$400,'Service Duration by unit'!$A$1:$A$400,$J6,'Service Duration by unit'!$C$1:$C$400,">="&IF($H6=$M$4,N$4,N$3)))),1))*$L6/3600)*(1+$M6)} -> 0 | ES6: {=(IF($H6=$M$4,N$4*$I6,N$3*$I6)+(INDEX(_xlfn._xlws.FILTER('Service Duration by unit'!$D$1:$D$400,('Service Duration by unit'!$A$1:$A$400=$J6)*('Service Duration by unit'!$C$1:$C$400=_xlfn.MINIFS('Service Duration by unit'!$C$1:$C$400,'Service Duration by unit'!$A$1:$A$400,$J6,'Service Duration by unit'!$C$1:$C$400,">="&IF($H6=$M$4,N$4,N$3)))),1))*$L6/3600)*(1+$M6)} -> 0 | ET6: {=(IF($H6=$M$4,N$4*$I6,N$3*$I6)+(INDEX(_xlfn._xlws.FILTER('Service Duration by unit'!$D$1:$D$400,('Service Duration by unit'!$A$1:$A$400=$J6)*('Service Duration by unit'!$C$1:$C$400=_xlfn.MINIFS('Service Duration by unit'!$C$1:$C$400,'Service Duration by unit'!$A$1:$A$400,$J6,'Service Duration by unit'!$C$1:$C$400,">="&IF($H6=$M$4,N$4,N$3)))),1))*$L6/3600)*(1+$M6)} -> 0 | EU6: {=(IF($H6=$M$4,N$4*$I6,N$3*$I6)+(INDEX(_xlfn._xlws.FILTER('Service Duration by unit'!$D$1:$D$400,('Service Duration by unit'!$A$1:$A$400=$J6)*('Service Duration by unit'!$C$1:$C$400=_xlfn.MINIFS('Service Duration by unit'!$C$1:$C$400,'Service Duration by unit'!$A$1:$A$400,$J6,'Service Duration by unit'!$C$1:$C$400,">="&IF($H6=$M$4,N$4,N$3)))),1))*$L6/3600)*(1+$M6)} -> 0 | EV6: {=(IF($H6=$M$4,N$4*$I6,N$3*$I6)+(INDEX(_xlfn._xlws.FILTER('Service Duration by unit'!$D$1:$D$400,('Service Duration by unit'!$A$1:$A$400=$J6)*('Service Duration by unit'!$C$1:$C$400=_xlfn.MINIFS('Service Duration by unit'!$C$1:$C$400,'Service Duration by unit'!$A$1:$A$400,$J6,'Service Duration by unit'!$C$1:$C$400,">="&IF($H6=$M$4,N$4,N$3)))),1))*$L6/3600)*(1+$M6)} -> 0 | EW6: {=(IF($H6=$M$4,N$4*$I6,N$3*$I6)+(INDEX(_xlfn._xlws.FILTER('Service Duration by unit'!$D$1:$D$400,('Service Duration by unit'!$A$1:$A$400=$J6)*('Service Duration by unit'!$C$1:$C$400=_xlfn.MINIFS('Service Duration by unit'!$C$1:$C$400,'Service Duration by unit'!$A$1:$A$400,$J6,'Service Duration by unit'!$C$1:$C$400,">="&IF($H6=$M$4,N$4,N$3)))),1))*$L6/3600)*(1+$M6)} -> 0 | EX6: {=(IF($H6=$M$4,N$4*$I6,N$3*$I6)+(INDEX(_xlfn._xlws.FILTER('Service Duration by unit'!$D$1:$D$400,('Service Duration by unit'!$A$1:$A$400=$J6)*('Service Duration by unit'!$C$1:$C$400=_xlfn.MINIFS('Service Duration by unit'!$C$1:$C$400,'Service Duration by unit'!$A$1:$A$400,$J6,'Service Duration by unit'!$C$1:$C$400,">="&IF($H6=$M$4,N$4,N$3)))),1))*$L6/3600)*(1+$M6)} -> 0 | EY6: {=(IF($H6=$M$4,N$4*$I6,N$3*$I6)+(INDEX(_xlfn._xlws.FILTER('Service Duration by unit'!$D$1:$D$400,('Service Duration by unit'!$A$1:$A$400=$J6)*('Service Duration by unit'!$C$1:$C$400=_xlfn.MINIFS('Service Duration by unit'!$C$1:$C$400,'Service Duration by unit'!$A$1:$A$400,$J6,'Service Duration by unit'!$C$1:$C$400,">="&IF($H6=$M$4,N$4,N$3)))),1))*$L6/3600)*(1+$M6)} -> 0 | EZ6: {=(IF($H6=$M$4,N$4*$I6,N$3*$I6)+(INDEX(_xlfn._xlws.FILTER('Service Duration by unit'!$D$1:$D$400,('Service Duration by unit'!$A$1:$A$400=$J6)*('Service Duration by unit'!$C$1:$C$400=_xlfn.MINIFS('Service Duration by unit'!$C$1:$C$400,'Service Duration by unit'!$A$1:$A$400,$J6,'Service Duration by unit'!$C$1:$C$400,">="&IF($H6=$M$4,N$4,N$3)))),1))*$L6/3600)*(1+$M6)} -> 0 | FA6: {=(IF($H6=$M$4,N$4*$I6,N$3*$I6)+(INDEX(_xlfn._xlws.FILTER('Service Duration by unit'!$D$1:$D$400,('Service Duration by unit'!$A$1:$A$400=$J6)*('Service Duration by unit'!$C$1:$C$400=_xlfn.MINIFS('Service Duration by unit'!$C$1:$C$400,'Service Duration by unit'!$A$1:$A$400,$J6,'Service Duration by unit'!$C$1:$C$400,">="&IF($H6=$M$4,N$4,N$3)))),1))*$L6/3600)*(1+$M6)} -> 0 | FB6: {=(IF($H6=$M$4,N$4*$I6,N$3*$I6)+(INDEX(_xlfn._xlws.FILTER('Service Duration by unit'!$D$1:$D$400,('Service Duration by unit'!$A$1:$A$400=$J6)*('Service Duration by unit'!$C$1:$C$400=_xlfn.MINIFS('Service Duration by unit'!$C$1:$C$400,'Service Duration by unit'!$A$1:$A$400,$J6,'Service Duration by unit'!$C$1:$C$400,">="&IF($H6=$M$4,N$4,N$3)))),1))*$L6/3600)*(1+$M6)} -> 0 | FC6: {=(IF($H6=$M$4,N$4*$I6,N$3*$I6)+(INDEX(_xlfn._xlws.FILTER('Service Duration by unit'!$D$1:$D$400,('Service Duration by unit'!$A$1:$A$400=$J6)*('Service Duration by unit'!$C$1:$C$400=_xlfn.MINIFS('Service Duration by unit'!$C$1:$C$400,'Service Duration by unit'!$A$1:$A$400,$J6,'Service Duration by unit'!$C$1:$C$400,">="&IF($H6=$M$4,N$4,N$3)))),1))*$L6/3600)*(1+$M6)} -> 0 | FD6: {=(IF($H6=$M$4,N$4*$I6,N$3*$I6)+(INDEX(_xlfn._xlws.FILTER('Service Duration by unit'!$D$1:$D$400,('Service Duration by unit'!$A$1:$A$400=$J6)*('Service Duration by unit'!$C$1:$C$400=_xlfn.MINIFS('Service Duration by unit'!$C$1:$C$400,'Service Duration by unit'!$A$1:$A$400,$J6,'Service Duration by unit'!$C$1:$C$400,">="&IF($H6=$M$4,N$4,N$3)))),1))*$L6/3600)*(1+$M6)} -> 0 | FE6: {=(IF($H6=$M$4,N$4*$I6,N$3*$I6)+(INDEX(_xlfn._xlws.FILTER('Service Duration by unit'!$D$1:$D$400,('Service Duration by unit'!$A$1:$A$400=$J6)*('Service Duration by unit'!$C$1:$C$400=_xlfn.MINIFS('Service Duration by unit'!$C$1:$C$400,'Service Duration by unit'!$A$1:$A$400,$J6,'Service Duration by unit'!$C$1:$C$400,">="&IF($H6=$M$4,N$4,N$3)))),1))*$L6/3600)*(1+$M6)} -> 0 | FF6: {=(IF($H6=$M$4,N$4*$I6,N$3*$I6)+(INDEX(_xlfn._xlws.FILTER('Service Duration by unit'!$D$1:$D$400,('Service Duration by unit'!$A$1:$A$400=$J6)*('Service Duration by unit'!$C$1:$C$400=_xlfn.MINIFS('Service Duration by unit'!$C$1:$C$400,'Service Duration by unit'!$A$1:$A$400,$J6,'Service Duration by unit'!$C$1:$C$400,">="&IF($H6=$M$4,N$4,N$3)))),1))*$L6/3600)*(1+$M6)} -> 0
A7: "Altis" Baklijst Eik Fineer 38X25 | B7: 2 | C7: 9897 | D7: 100767 | E7: .D08+D10 | H7: Circumference | I7: 9.29 | J7: Lijst snijden | K7: Lijst snijden | L7: 40 | M7: =('Pricelists by Sequence'!$D$2*(-1)/100) -> 0 | N7: {=(IF($H7=$M$4,N$4*$I7,N$3*$I7)+(INDEX(_xlfn._xlws.FILTER('Service Duration by unit'!$D$1:$D$400,('Service Duration by unit'!$A$1:$A$400=$J7)*('Service Duration by unit'!$C$1:$C$400=_xlfn.MINIFS('Service Duration by unit'!$C$1:$C$400,'Service Duration by unit'!$A$1:$A$400,$J7,'Service Duration by unit'!$C$1:$C$400,">="&IF($H7=$M$4,N$4,N$3)))),1))*$L7/3600)*(1+$M7)} -> 0 | O7: {=(IF($H7=$M$4,N$4*$I7,N$3*$I7)+(INDEX(_xlfn._xlws.FILTER('Service Duration by unit'!$D$1:$D$400,('Service Duration by unit'!$A$1:$A$400=$J7)*('Service Duration by unit'!$C$1:$C$400=_xlfn.MINIFS('Service Duration by unit'!$C$1:$C$400,'Service Duration by unit'!$A$1:$A$400,$J7,'Service Duration by unit'!$C$1:$C$400,">="&IF($H7=$M$4,N$4,N$3)))),1))*$L7/3600)*(1+$M7)} -> 0 | P7: {=(IF($H7=$M$4,N$4*$I7,N$3*$I7)+(INDEX(_xlfn._xlws.FILTER('Service Duration by unit'!$D$1:$D$400,('Service Duration by unit'!$A$1:$A$400=$J7)*('Service Duration by unit'!$C$1:$C$400=_xlfn.MINIFS('Service Duration by unit'!$C$1:$C$400,'Service Duration by unit'!$A$1:$A$400,$J7,'Service Duration by unit'!$C$1:$C$400,">="&IF($H7=$M$4,N$4,N$3)))),1))*$L7/3600)*(1+$M7)} -> 0 | Q7: {=(IF($H7=$M$4,N$4*$I7,N$3*$I7)+(INDEX(_xlfn._xlws.FILTER('Service Duration by unit'!$D$1:$D$400,('Service Duration by unit'!$A$1:$A$400=$J7)*('Service Duration by unit'!$C$1:$C$400=_xlfn.MINIFS('Service Duration by unit'!$C$1:$C$400,'Service Duration by unit'!$A$1:$A$400,$J7,'Service Duration by unit'!$C$1:$C$400,">="&IF($H7=$M$4,N$4,N$3)))),1))*$L7/3600)*(1+$M7)} -> 0 | R7: {=(IF($H7=$M$4,N$4*$I7,N$3*$I7)+(INDEX(_xlfn._xlws.FILTER('Service Duration by unit'!$D$1:$D$400,('Service Duration by unit'!$A$1:$A$400=$J7)*('Service Duration by unit'!$C$1:$C$400=_xlfn.MINIFS('Service Duration by unit'!$C$1:$C$400,'Service Duration by unit'!$A$1:$A$400,$J7,'Service Duration by unit'!$C$1:$C$400,">="&IF($H7=$M$4,N$4,N$3)))),1))*$L7/3600)*(1+$M7)} -> 0 | S7: {=(IF($H7=$M$4,N$4*$I7,N$3*$I7)+(INDEX(_xlfn._xlws.FILTER('Service Duration by unit'!$D$1:$D$400,('Service Duration by unit'!$A$1:$A$400=$J7)*('Service Duration by unit'!$C$1:$C$400=_xlfn.MINIFS('Service Duration by unit'!$C$1:$C$400,'Service Duration by unit'!$A$1:$A$400,$J7,'Service Duration by unit'!$C$1:$C$400,">="&IF($H7=$M$4,N$4,N$3)))),1))*$L7/3600)*(1+$M7)} -> 0 | T7: {=(IF($H7=$M$4,N$4*$I7,N$3*$I7)+(INDEX(_xlfn._xlws.FILTER('Service Duration by unit'!$D$1:$D$400,('Service Duration by unit'!$A$1:$A$400=$J7)*('Service Duration by unit'!$C$1:$C$400=_xlfn.MINIFS('Service Duration by unit'!$C$1:$C$400,'Service Duration by unit'!$A$1:$A$400,$J7,'Service Duration by unit'!$C$1:$C$400,">="&IF($H7=$M$4,N$4,N$3)))),1))*$L7/3600)*(1+$M7)} -> 0 | U7: {=(IF($H7=$M$4,N$4*$I7,N$3*$I7)+(INDEX(_xlfn._xlws.FILTER('Service Duration by unit'!$D$1:$D$400,('Service Duration by unit'!$A$1:$A$400=$J7)*('Service Duration by unit'!$C$1:$C$400=_xlfn.MINIFS('Service Duration by unit'!$C$1:$C$400,'Service Duration by unit'!$A$1:$A$400,$J7,'Service Duration by unit'!$C$1:$C$400,">="&IF($H7=$M$4,N$4,N$3)))),1))*$L7/3600)*(1+$M7)} -> 0 | V7: {=(IF($H7=$M$4,N$4*$I7,N$3*$I7)+(INDEX(_xlfn._xlws.FILTER('Service Duration by unit'!$D$1:$D$400,('Service Duration by unit'!$A$1:$A$400=$J7)*('Service Duration by unit'!$C$1:$C$400=_xlfn.MINIFS('Service Duration by unit'!$C$1:$C$400,'Service Duration by unit'!$A$1:$A$400,$J7,'Service Duration by unit'!$C$1:$C$400,">="&IF($H7=$M$4,N$4,N$3)))),1))*$L7/3600)*(1+$M7)} -> 0 | W7: {=(IF($H7=$M$4,N$4*$I7,N$3*$I7)+(INDEX(_xlfn._xlws.FILTER('Service Duration by unit'!$D$1:$D$400,('Service Duration by unit'!$A$1:$A$400=$J7)*('Service Duration by unit'!$C$1:$C$400=_xlfn.MINIFS('Service Duration by unit'!$C$1:$C$400,'Service Duration by unit'!$A$1:$A$400,$J7,'Service Duration by unit'!$C$1:$C$400,">="&IF($H7=$M$4,N$4,N$3)))),1))*$L7/3600)*(1+$M7)} -> 0 | X7: {=(IF($H7=$M$4,N$4*$I7,N$3*$I7)+(INDEX(_xlfn._xlws.FILTER('Service Duration by unit'!$D$1:$D$400,('Service Duration by unit'!$A$1:$A$400=$J7)*('Service Duration by unit'!$C$1:$C$400=_xlfn.MINIFS('Service Duration by unit'!$C$1:$C$400,'Service Duration by unit'!$A$1:$A$400,$J7,'Service Duration by unit'!$C$1:$C$400,">="&IF($H7=$M$4,N$4,N$3)))),1))*$L7/3600)*(1+$M7)} -> 0 | Y7: {=(IF($H7=$M$4,N$4*$I7,N$3*$I7)+(INDEX(_xlfn._xlws.FILTER('Service Duration by unit'!$D$1:$D$400,('Service Duration by unit'!$A$1:$A$400=$J7)*('Service Duration by unit'!$C$1:$C$400=_xlfn.MINIFS('Service Duration by unit'!$C$1:$C$400,'Service Duration by unit'!$A$1:$A$400,$J7,'Service Duration by unit'!$C$1:$C$400,">="&IF($H7=$M$4,N$4,N$3)))),1))*$L7/3600)*(1+$M7)} -> 0 | Z7: {=(IF($H7=$M$4,N$4*$I7,N$3*$I7)+(INDEX(_xlfn._xlws.FILTER('Service Duration by unit'!$D$1:$D$400,('Service Duration by unit'!$A$1:$A$400=$J7)*('Service Duration by unit'!$C$1:$C$400=_xlfn.MINIFS('Service Duration by unit'!$C$1:$C$400,'Service Duration by unit'!$A$1:$A$400,$J7,'Service Duration by unit'!$C$1:$C$400,">="&IF($H7=$M$4,N$4,N$3)))),1))*$L7/3600)*(1+$M7)} -> 0 | AA7: {=(IF($H7=$M$4,N$4*$I7,N$3*$I7)+(INDEX(_xlfn._xlws.FILTER('Service Duration by unit'!$D$1:$D$400,('Service Duration by unit'!$A$1:$A$400=$J7)*('Service Duration by unit'!$C$1:$C$400=_xlfn.MINIFS('Service Duration by unit'!$C$1:$C$400,'Service Duration by unit'!$A$1:$A$400,$J7,'Service Duration by unit'!$C$1:$C$400,">="&IF($H7=$M$4,N$4,N$3)))),1))*$L7/3600)*(1+$M7)} -> 0 | AB7: {=(IF($H7=$M$4,N$4*$I7,N$3*$I7)+(INDEX(_xlfn._xlws.FILTER('Service Duration by unit'!$D$1:$D$400,('Service Duration by unit'!$A$1:$A$400=$J7)*('Service Duration by unit'!$C$1:$C$400=_xlfn.MINIFS('Service Duration by unit'!$C$1:$C$400,'Service Duration by unit'!$A$1:$A$400,$J7,'Service Duration by unit'!$C$1:$C$400,">="&IF($H7=$M$4,N$4,N$3)))),1))*$L7/3600)*(1+$M7)} -> 0 | AC7: {=(IF($H7=$M$4,N$4*$I7,N$3*$I7)+(INDEX(_xlfn._xlws.FILTER('Service Duration by unit'!$D$1:$D$400,('Service Duration by unit'!$A$1:$A$400=$J7)*('Service Duration by unit'!$C$1:$C$400=_xlfn.MINIFS('Service Duration by unit'!$C$1:$C$400,'Service Duration by unit'!$A$1:$A$400,$J7,'Service Duration by unit'!$C$1:$C$400,">="&IF($H7=$M$4,N$4,N$3)))),1))*$L7/3600)*(1+$M7)} -> 0 | AD7: {=(IF($H7=$M$4,N$4*$I7,N$3*$I7)+(INDEX(_xlfn._xlws.FILTER('Service Duration by unit'!$D$1:$D$400,('Service Duration by unit'!$A$1:$A$400=$J7)*('Service Duration by unit'!$C$1:$C$400=_xlfn.MINIFS('Service Duration by unit'!$C$1:$C$400,'Service Duration by unit'!$A$1:$A$400,$J7,'Service Duration by unit'!$C$1:$C$400,">="&IF($H7=$M$4,N$4,N$3)))),1))*$L7/3600)*(1+$M7)} -> 0 | AE7: {=(IF($H7=$M$4,N$4*$I7,N$3*$I7)+(INDEX(_xlfn._xlws.FILTER('Service Duration by unit'!$D$1:$D$400,('Service Duration by unit'!$A$1:$A$400=$J7)*('Service Duration by unit'!$C$1:$C$400=_xlfn.MINIFS('Service Duration by unit'!$C$1:$C$400,'Service Duration by unit'!$A$1:$A$400,$J7,'Service Duration by unit'!$C$1:$C$400,">="&IF($H7=$M$4,N$4,N$3)))),1))*$L7/3600)*(1+$M7)} -> 0 | AF7: {=(IF($H7=$M$4,N$4*$I7,N$3*$I7)+(INDEX(_xlfn._xlws.FILTER('Service Duration by unit'!$D$1:$D$400,('Service Duration by unit'!$A$1:$A$400=$J7)*('Service Duration by unit'!$C$1:$C$400=_xlfn.MINIFS('Service Duration by unit'!$C$1:$C$400,'Service Duration by unit'!$A$1:$A$400,$J7,'Service Duration by unit'!$C$1:$C$400,">="&IF($H7=$M$4,N$4,N$3)))),1))*$L7/3600)*(1+$M7)} -> 0 | AG7: {=(IF($H7=$M$4,N$4*$I7,N$3*$I7)+(INDEX(_xlfn._xlws.FILTER('Service Duration by unit'!$D$1:$D$400,('Service Duration by unit'!$A$1:$A$400=$J7)*('Service Duration by unit'!$C$1:$C$400=_xlfn.MINIFS('Service Duration by unit'!$C$1:$C$400,'Service Duration by unit'!$A$1:$A$400,$J7,'Service Duration by unit'!$C$1:$C$400,">="&IF($H7=$M$4,N$4,N$3)))),1))*$L7/3600)*(1+$M7)} -> 0 | AH7: {=(IF($H7=$M$4,N$4*$I7,N$3*$I7)+(INDEX(_xlfn._xlws.FILTER('Service Duration by unit'!$D$1:$D$400,('Service Duration by unit'!$A$1:$A$400=$J7)*('Service Duration by unit'!$C$1:$C$400=_xlfn.MINIFS('Service Duration by unit'!$C$1:$C$400,'Service Duration by unit'!$A$1:$A$400,$J7,'Service Duration by unit'!$C$1:$C$400,">="&IF($H7=$M$4,N$4,N$3)))),1))*$L7/3600)*(1+$M7)} -> 0 | AI7: {=(IF($H7=$M$4,N$4*$I7,N$3*$I7)+(INDEX(_xlfn._xlws.FILTER('Service Duration by unit'!$D$1:$D$400,('Service Duration by unit'!$A$1:$A$400=$J7)*('Service Duration by unit'!$C$1:$C$400=_xlfn.MINIFS('Service Duration by unit'!$C$1:$C$400,'Service Duration by unit'!$A$1:$A$400,$J7,'Service Duration by unit'!$C$1:$C$400,">="&IF($H7=$M$4,N$4,N$3)))),1))*$L7/3600)*(1+$M7)} -> 0 | AJ7: {=(IF($H7=$M$4,N$4*$I7,N$3*$I7)+(INDEX(_xlfn._xlws.FILTER('Service Duration by unit'!$D$1:$D$400,('Service Duration by unit'!$A$1:$A$400=$J7)*('Service Duration by unit'!$C$1:$C$400=_xlfn.MINIFS('Service Duration by unit'!$C$1:$C$400,'Service Duration by unit'!$A$1:$A$400,$J7,'Service Duration by unit'!$C$1:$C$400,">="&IF($H7=$M$4,N$4,N$3)))),1))*$L7/3600)*(1+$M7)} -> 0 | AK7: {=(IF($H7=$M$4,N$4*$I7,N$3*$I7)+(INDEX(_xlfn._xlws.FILTER('Service Duration by unit'!$D$1:$D$400,('Service Duration by unit'!$A$1:$A$400=$J7)*('Service Duration by unit'!$C$1:$C$400=_xlfn.MINIFS('Service Duration by unit'!$C$1:$C$400,'Service Duration by unit'!$A$1:$A$400,$J7,'Service Duration by unit'!$C$1:$C$400,">="&IF($H7=$M$4,N$4,N$3)))),1))*$L7/3600)*(1+$M7)} -> 0 | AL7: {=(IF($H7=$M$4,N$4*$I7,N$3*$I7)+(INDEX(_xlfn._xlws.FILTER('Service Duration by unit'!$D$1:$D$400,('Service Duration by unit'!$A$1:$A$400=$J7)*('Service Duration by unit'!$C$1:$C$400=_xlfn.MINIFS('Service Duration by unit'!$C$1:$C$400,'Service Duration by unit'!$A$1:$A$400,$J7,'Service Duration by unit'!$C$1:$C$400,">="&IF($H7=$M$4,N$4,N$3)))),1))*$L7/3600)*(1+$M7)} -> 0 | AM7: {=(IF($H7=$M$4,N$4*$I7,N$3*$I7)+(INDEX(_xlfn._xlws.FILTER('Service Duration by unit'!$D$1:$D$400,('Service Duration by unit'!$A$1:$A$400=$J7)*('Service Duration by unit'!$C$1:$C$400=_xlfn.MINIFS('Service Duration by unit'!$C$1:$C$400,'Service Duration by unit'!$A$1:$A$400,$J7,'Service Duration by unit'!$C$1:$C$400,">="&IF($H7=$M$4,N$4,N$3)))),1))*$L7/3600)*(1+$M7)} -> 0 | AN7: {=(IF($H7=$M$4,N$4*$I7,N$3*$I7)+(INDEX(_xlfn._xlws.FILTER('Service Duration by unit'!$D$1:$D$400,('Service Duration by unit'!$A$1:$A$400=$J7)*('Service Duration by unit'!$C$1:$C$400=_xlfn.MINIFS('Service Duration by unit'!$C$1:$C$400,'Service Duration by unit'!$A$1:$A$400,$J7,'Service Duration by unit'!$C$1:$C$400,">="&IF($H7=$M$4,N$4,N$3)))),1))*$L7/3600)*(1+$M7)} -> 0 | AO7: {=(IF($H7=$M$4,N$4*$I7,N$3*$I7)+(INDEX(_xlfn._xlws.FILTER('Service Duration by unit'!$D$1:$D$400,('Service Duration by unit'!$A$1:$A$400=$J7)*('Service Duration by unit'!$C$1:$C$400=_xlfn.MINIFS('Service Duration by unit'!$C$1:$C$400,'Service Duration by unit'!$A$1:$A$400,$J7,'Service Duration by unit'!$C$1:$C$400,">="&IF($H7=$M$4,N$4,N$3)))),1))*$L7/3600)*(1+$M7)} -> 0 | AP7: {=(IF($H7=$M$4,N$4*$I7,N$3*$I7)+(INDEX(_xlfn._xlws.FILTER('Service Duration by unit'!$D$1:$D$400,('Service Duration by unit'!$A$1:$A$400=$J7)*('Service Duration by unit'!$C$1:$C$400=_xlfn.MINIFS('Service Duration by unit'!$C$1:$C$400,'Service Duration by unit'!$A$1:$A$400,$J7,'Service Duration by unit'!$C$1:$C$400,">="&IF($H7=$M$4,N$4,N$3)))),1))*$L7/3600)*(1+$M7)} -> 0 | AQ7: {=(IF($H7=$M$4,N$4*$I7,N$3*$I7)+(INDEX(_xlfn._xlws.FILTER('Service Duration by unit'!$D$1:$D$400,('Service Duration by unit'!$A$1:$A$400=$J7)*('Service Duration by unit'!$C$1:$C$400=_xlfn.MINIFS('Service Duration by unit'!$C$1:$C$400,'Service Duration by unit'!$A$1:$A$400,$J7,'Service Duration by unit'!$C$1:$C$400,">="&IF($H7=$M$4,N$4,N$3)))),1))*$L7/3600)*(1+$M7)} -> 0 | AR7: {=(IF($H7=$M$4,N$4*$I7,N$3*$I7)+(INDEX(_xlfn._xlws.FILTER('Service Duration by unit'!$D$1:$D$400,('Service Duration by unit'!$A$1:$A$400=$J7)*('Service Duration by unit'!$C$1:$C$400=_xlfn.MINIFS('Service Duration by unit'!$C$1:$C$400,'Service Duration by unit'!$A$1:$A$400,$J7,'Service Duration by unit'!$C$1:$C$400,">="&IF($H7=$M$4,N$4,N$3)))),1))*$L7/3600)*(1+$M7)} -> 0 | AS7: {=(IF($H7=$M$4,N$4*$I7,N$3*$I7)+(INDEX(_xlfn._xlws.FILTER('Service Duration by unit'!$D$1:$D$400,('Service Duration by unit'!$A$1:$A$400=$J7)*('Service Duration by unit'!$C$1:$C$400=_xlfn.MINIFS('Service Duration by unit'!$C$1:$C$400,'Service Duration by unit'!$A$1:$A$400,$J7,'Service Duration by unit'!$C$1:$C$400,">="&IF($H7=$M$4,N$4,N$3)))),1))*$L7/3600)*(1+$M7)} -> 0 | AT7: {=(IF($H7=$M$4,N$4*$I7,N$3*$I7)+(INDEX(_xlfn._xlws.FILTER('Service Duration by unit'!$D$1:$D$400,('Service Duration by unit'!$A$1:$A$400=$J7)*('Service Duration by unit'!$C$1:$C$400=_xlfn.MINIFS('Service Duration by unit'!$C$1:$C$400,'Service Duration by unit'!$A$1:$A$400,$J7,'Service Duration by unit'!$C$1:$C$400,">="&IF($H7=$M$4,N$4,N$3)))),1))*$L7/3600)*(1+$M7)} -> 0 | AU7: {=(IF($H7=$M$4,N$4*$I7,N$3*$I7)+(INDEX(_xlfn._xlws.FILTER('Service Duration by unit'!$D$1:$D$400,('Service Duration by unit'!$A$1:$A$400=$J7)*('Service Duration by unit'!$C$1:$C$400=_xlfn.MINIFS('Service Duration by unit'!$C$1:$C$400,'Service Duration by unit'!$A$1:$A$400,$J7,'Service Duration by unit'!$C$1:$C$400,">="&IF($H7=$M$4,N$4,N$3)))),1))*$L7/3600)*(1+$M7)} -> 0 | AV7: {=(IF($H7=$M$4,N$4*$I7,N$3*$I7)+(INDEX(_xlfn._xlws.FILTER('Service Duration by unit'!$D$1:$D$400,('Service Duration by unit'!$A$1:$A$400=$J7)*('Service Duration by unit'!$C$1:$C$400=_xlfn.MINIFS('Service Duration by unit'!$C$1:$C$400,'Service Duration by unit'!$A$1:$A$400,$J7,'Service Duration by unit'!$C$1:$C$400,">="&IF($H7=$M$4,N$4,N$3)))),1))*$L7/3600)*(1+$M7)} -> 0 | AW7: {=(IF($H7=$M$4,N$4*$I7,N$3*$I7)+(INDEX(_xlfn._xlws.FILTER('Service Duration by unit'!$D$1:$D$400,('Service Duration by unit'!$A$1:$A$400=$J7)*('Service Duration by unit'!$C$1:$C$400=_xlfn.MINIFS('Service Duration by unit'!$C$1:$C$400,'Service Duration by unit'!$A$1:$A$400,$J7,'Service Duration by unit'!$C$1:$C$400,">="&IF($H7=$M$4,N$4,N$3)))),1))*$L7/3600)*(1+$M7)} -> 0 | AX7: {=(IF($H7=$M$4,N$4*$I7,N$3*$I7)+(INDEX(_xlfn._xlws.FILTER('Service Duration by unit'!$D$1:$D$400,('Service Duration by unit'!$A$1:$A$400=$J7)*('Service Duration by unit'!$C$1:$C$400=_xlfn.MINIFS('Service Duration by unit'!$C$1:$C$400,'Service Duration by unit'!$A$1:$A$400,$J7,'Service Duration by unit'!$C$1:$C$400,">="&IF($H7=$M$4,N$4,N$3)))),1))*$L7/3600)*(1+$M7)} -> 0 | AY7: {=(IF($H7=$M$4,N$4*$I7,N$3*$I7)+(INDEX(_xlfn._xlws.FILTER('Service Duration by unit'!$D$1:$D$400,('Service Duration by unit'!$A$1:$A$400=$J7)*('Service Duration by unit'!$C$1:$C$400=_xlfn.MINIFS('Service Duration by unit'!$C$1:$C$400,'Service Duration by unit'!$A$1:$A$400,$J7,'Service Duration by unit'!$C$1:$C$400,">="&IF($H7=$M$4,N$4,N$3)))),1))*$L7/3600)*(1+$M7)} -> 0 | AZ7: {=(IF($H7=$M$4,N$4*$I7,N$3*$I7)+(INDEX(_xlfn._xlws.FILTER('Service Duration by unit'!$D$1:$D$400,('Service Duration by unit'!$A$1:$A$400=$J7)*('Service Duration by unit'!$C$1:$C$400=_xlfn.MINIFS('Service Duration by unit'!$C$1:$C$400,'Service Duration by unit'!$A$1:$A$400,$J7,'Service Duration by unit'!$C$1:$C$400,">="&IF($H7=$M$4,N$4,N$3)))),1))*$L7/3600)*(1+$M7)} -> 0 | BA7: {=(IF($H7=$M$4,N$4*$I7,N$3*$I7)+(INDEX(_xlfn._xlws.FILTER('Service Duration by unit'!$D$1:$D$400,('Service Duration by unit'!$A$1:$A$400=$J7)*('Service Duration by unit'!$C$1:$C$400=_xlfn.MINIFS('Service Duration by unit'!$C$1:$C$400,'Service Duration by unit'!$A$1:$A$400,$J7,'Service Duration by unit'!$C$1:$C$400,">="&IF($H7=$M$4,N$4,N$3)))),1))*$L7/3600)*(1+$M7)} -> 0 | BB7: {=(IF($H7=$M$4,N$4*$I7,N$3*$I7)+(INDEX(_xlfn._xlws.FILTER('Service Duration by unit'!$D$1:$D$400,('Service Duration by unit'!$A$1:$A$400=$J7)*('Service Duration by unit'!$C$1:$C$400=_xlfn.MINIFS('Service Duration by unit'!$C$1:$C$400,'Service Duration by unit'!$A$1:$A$400,$J7,'Service Duration by unit'!$C$1:$C$400,">="&IF($H7=$M$4,N$4,N$3)))),1))*$L7/3600)*(1+$M7)} -> 0 | BC7: {=(IF($H7=$M$4,N$4*$I7,N$3*$I7)+(INDEX(_xlfn._xlws.FILTER('Service Duration by unit'!$D$1:$D$400,('Service Duration by unit'!$A$1:$A$400=$J7)*('Service Duration by unit'!$C$1:$C$400=_xlfn.MINIFS('Service Duration by unit'!$C$1:$C$400,'Service Duration by unit'!$A$1:$A$400,$J7,'Service Duration by unit'!$C$1:$C$400,">="&IF($H7=$M$4,N$4,N$3)))),1))*$L7/3600)*(1+$M7)} -> 0 | BD7: {=(IF($H7=$M$4,N$4*$I7,N$3*$I7)+(INDEX(_xlfn._xlws.FILTER('Service Duration by unit'!$D$1:$D$400,('Service Duration by unit'!$A$1:$A$400=$J7)*('Service Duration by unit'!$C$1:$C$400=_xlfn.MINIFS('Service Duration by unit'!$C$1:$C$400,'Service Duration by unit'!$A$1:$A$400,$J7,'Service Duration by unit'!$C$1:$C$400,">="&IF($H7=$M$4,N$4,N$3)))),1))*$L7/3600)*(1+$M7)} -> 0 | BE7: {=(IF($H7=$M$4,N$4*$I7,N$3*$I7)+(INDEX(_xlfn._xlws.FILTER('Service Duration by unit'!$D$1:$D$400,('Service Duration by unit'!$A$1:$A$400=$J7)*('Service Duration by unit'!$C$1:$C$400=_xlfn.MINIFS('Service Duration by unit'!$C$1:$C$400,'Service Duration by unit'!$A$1:$A$400,$J7,'Service Duration by unit'!$C$1:$C$400,">="&IF($H7=$M$4,N$4,N$3)))),1))*$L7/3600)*(1+$M7)} -> 0 | BF7: {=(IF($H7=$M$4,N$4*$I7,N$3*$I7)+(INDEX(_xlfn._xlws.FILTER('Service Duration by unit'!$D$1:$D$400,('Service Duration by unit'!$A$1:$A$400=$J7)*('Service Duration by unit'!$C$1:$C$400=_xlfn.MINIFS('Service Duration by unit'!$C$1:$C$400,'Service Duration by unit'!$A$1:$A$400,$J7,'Service Duration by unit'!$C$1:$C$400,">="&IF($H7=$M$4,N$4,N$3)))),1))*$L7/3600)*(1+$M7)} -> 0 | BG7: {=(IF($H7=$M$4,N$4*$I7,N$3*$I7)+(INDEX(_xlfn._xlws.FILTER('Service Duration by unit'!$D$1:$D$400,('Service Duration by unit'!$A$1:$A$400=$J7)*('Service Duration by unit'!$C$1:$C$400=_xlfn.MINIFS('Service Duration by unit'!$C$1:$C$400,'Service Duration by unit'!$A$1:$A$400,$J7,'Service Duration by unit'!$C$1:$C$400,">="&IF($H7=$M$4,N$4,N$3)))),1))*$L7/3600)*(1+$M7)} -> 0 | BH7: {=(IF($H7=$M$4,N$4*$I7,N$3*$I7)+(INDEX(_xlfn._xlws.FILTER('Service Duration by unit'!$D$1:$D$400,('Service Duration by unit'!$A$1:$A$400=$J7)*('Service Duration by unit'!$C$1:$C$400=_xlfn.MINIFS('Service Duration by unit'!$C$1:$C$400,'Service Duration by unit'!$A$1:$A$400,$J7,'Service Duration by unit'!$C$1:$C$400,">="&IF($H7=$M$4,N$4,N$3)))),1))*$L7/3600)*(1+$M7)} -> 0 | BI7: {=(IF($H7=$M$4,N$4*$I7,N$3*$I7)+(INDEX(_xlfn._xlws.FILTER('Service Duration by unit'!$D$1:$D$400,('Service Duration by unit'!$A$1:$A$400=$J7)*('Service Duration by unit'!$C$1:$C$400=_xlfn.MINIFS('Service Duration by unit'!$C$1:$C$400,'Service Duration by unit'!$A$1:$A$400,$J7,'Service Duration by unit'!$C$1:$C$400,">="&IF($H7=$M$4,N$4,N$3)))),1))*$L7/3600)*(1+$M7)} -> 0 | BJ7: {=(IF($H7=$M$4,N$4*$I7,N$3*$I7)+(INDEX(_xlfn._xlws.FILTER('Service Duration by unit'!$D$1:$D$400,('Service Duration by unit'!$A$1:$A$400=$J7)*('Service Duration by unit'!$C$1:$C$400=_xlfn.MINIFS('Service Duration by unit'!$C$1:$C$400,'Service Duration by unit'!$A$1:$A$400,$J7,'Service Duration by unit'!$C$1:$C$400,">="&IF($H7=$M$4,N$4,N$3)))),1))*$L7/3600)*(1+$M7)} -> 0 | BK7: {=(IF($H7=$M$4,N$4*$I7,N$3*$I7)+(INDEX(_xlfn._xlws.FILTER('Service Duration by unit'!$D$1:$D$400,('Service Duration by unit'!$A$1:$A$400=$J7)*('Service Duration by unit'!$C$1:$C$400=_xlfn.MINIFS('Service Duration by unit'!$C$1:$C$400,'Service Duration by unit'!$A$1:$A$400,$J7,'Service Duration by unit'!$C$1:$C$400,">="&IF($H7=$M$4,N$4,N$3)))),1))*$L7/3600)*(1+$M7)} -> 0 | BL7: {=(IF($H7=$M$4,N$4*$I7,N$3*$I7)+(INDEX(_xlfn._xlws.FILTER('Service Duration by unit'!$D$1:$D$400,('Service Duration by unit'!$A$1:$A$400=$J7)*('Service Duration by unit'!$C$1:$C$400=_xlfn.MINIFS('Service Duration by unit'!$C$1:$C$400,'Service Duration by unit'!$A$1:$A$400,$J7,'Service Duration by unit'!$C$1:$C$400,">="&IF($H7=$M$4,N$4,N$3)))),1))*$L7/3600)*(1+$M7)} -> 0 | BM7: {=(IF($H7=$M$4,N$4*$I7,N$3*$I7)+(INDEX(_xlfn._xlws.FILTER('Service Duration by unit'!$D$1:$D$400,('Service Duration by unit'!$A$1:$A$400=$J7)*('Service Duration by unit'!$C$1:$C$400=_xlfn.MINIFS('Service Duration by unit'!$C$1:$C$400,'Service Duration by unit'!$A$1:$A$400,$J7,'Service Duration by unit'!$C$1:$C$400,">="&IF($H7=$M$4,N$4,N$3)))),1))*$L7/3600)*(1+$M7)} -> 0 | BN7: {=(IF($H7=$M$4,N$4*$I7,N$3*$I7)+(INDEX(_xlfn._xlws.FILTER('Service Duration by unit'!$D$1:$D$400,('Service Duration by unit'!$A$1:$A$400=$J7)*('Service Duration by unit'!$C$1:$C$400=_xlfn.MINIFS('Service Duration by unit'!$C$1:$C$400,'Service Duration by unit'!$A$1:$A$400,$J7,'Service Duration by unit'!$C$1:$C$400,">="&IF($H7=$M$4,N$4,N$3)))),1))*$L7/3600)*(1+$M7)} -> 0 | BO7: {=(IF($H7=$M$4,N$4*$I7,N$3*$I7)+(INDEX(_xlfn._xlws.FILTER('Service Duration by unit'!$D$1:$D$400,('Service Duration by unit'!$A$1:$A$400=$J7)*('Service Duration by unit'!$C$1:$C$400=_xlfn.MINIFS('Service Duration by unit'!$C$1:$C$400,'Service Duration by unit'!$A$1:$A$400,$J7,'Service Duration by unit'!$C$1:$C$400,">="&IF($H7=$M$4,N$4,N$3)))),1))*$L7/3600)*(1+$M7)} -> 0 | BP7: {=(IF($H7=$M$4,N$4*$I7,N$3*$I7)+(INDEX(_xlfn._xlws.FILTER('Service Duration by unit'!$D$1:$D$400,('Service Duration by unit'!$A$1:$A$400=$J7)*('Service Duration by unit'!$C$1:$C$400=_xlfn.MINIFS('Service Duration by unit'!$C$1:$C$400,'Service Duration by unit'!$A$1:$A$400,$J7,'Service Duration by unit'!$C$1:$C$400,">="&IF($H7=$M$4,N$4,N$3)))),1))*$L7/3600)*(1+$M7)} -> 0 | BQ7: {=(IF($H7=$M$4,N$4*$I7,N$3*$I7)+(INDEX(_xlfn._xlws.FILTER('Service Duration by unit'!$D$1:$D$400,('Service Duration by unit'!$A$1:$A$400=$J7)*('Service Duration by unit'!$C$1:$C$400=_xlfn.MINIFS('Service Duration by unit'!$C$1:$C$400,'Service Duration by unit'!$A$1:$A$400,$J7,'Service Duration by unit'!$C$1:$C$400,">="&IF($H7=$M$4,N$4,N$3)))),1))*$L7/3600)*(1+$M7)} -> 0 | BR7: {=(IF($H7=$M$4,N$4*$I7,N$3*$I7)+(INDEX(_xlfn._xlws.FILTER('Service Duration by unit'!$D$1:$D$400,('Service Duration by unit'!$A$1:$A$400=$J7)*('Service Duration by unit'!$C$1:$C$400=_xlfn.MINIFS('Service Duration by unit'!$C$1:$C$400,'Service Duration by unit'!$A$1:$A$400,$J7,'Service Duration by unit'!$C$1:$C$400,">="&IF($H7=$M$4,N$4,N$3)))),1))*$L7/3600)*(1+$M7)} -> 0 | BS7: {=(IF($H7=$M$4,N$4*$I7,N$3*$I7)+(INDEX(_xlfn._xlws.FILTER('Service Duration by unit'!$D$1:$D$400,('Service Duration by unit'!$A$1:$A$400=$J7)*('Service Duration by unit'!$C$1:$C$400=_xlfn.MINIFS('Service Duration by unit'!$C$1:$C$400,'Service Duration by unit'!$A$1:$A$400,$J7,'Service Duration by unit'!$C$1:$C$400,">="&IF($H7=$M$4,N$4,N$3)))),1))*$L7/3600)*(1+$M7)} -> 0 | BT7: {=(IF($H7=$M$4,N$4*$I7,N$3*$I7)+(INDEX(_xlfn._xlws.FILTER('Service Duration by unit'!$D$1:$D$400,('Service Duration by unit'!$A$1:$A$400=$J7)*('Service Duration by unit'!$C$1:$C$400=_xlfn.MINIFS('Service Duration by unit'!$C$1:$C$400,'Service Duration by unit'!$A$1:$A$400,$J7,'Service Duration by unit'!$C$1:$C$400,">="&IF($H7=$M$4,N$4,N$3)))),1))*$L7/3600)*(1+$M7)} -> 0 | BU7: {=(IF($H7=$M$4,N$4*$I7,N$3*$I7)+(INDEX(_xlfn._xlws.FILTER('Service Duration by unit'!$D$1:$D$400,('Service Duration by unit'!$A$1:$A$400=$J7)*('Service Duration by unit'!$C$1:$C$400=_xlfn.MINIFS('Service Duration by unit'!$C$1:$C$400,'Service Duration by unit'!$A$1:$A$400,$J7,'Service Duration by unit'!$C$1:$C$400,">="&IF($H7=$M$4,N$4,N$3)))),1))*$L7/3600)*(1+$M7)} -> 0 | BV7: {=(IF($H7=$M$4,N$4*$I7,N$3*$I7)+(INDEX(_xlfn._xlws.FILTER('Service Duration by unit'!$D$1:$D$400,('Service Duration by unit'!$A$1:$A$400=$J7)*('Service Duration by unit'!$C$1:$C$400=_xlfn.MINIFS('Service Duration by unit'!$C$1:$C$400,'Service Duration by unit'!$A$1:$A$400,$J7,'Service Duration by unit'!$C$1:$C$400,">="&IF($H7=$M$4,N$4,N$3)))),1))*$L7/3600)*(1+$M7)} -> 0 | BW7: {=(IF($H7=$M$4,N$4*$I7,N$3*$I7)+(INDEX(_xlfn._xlws.FILTER('Service Duration by unit'!$D$1:$D$400,('Service Duration by unit'!$A$1:$A$400=$J7)*('Service Duration by unit'!$C$1:$C$400=_xlfn.MINIFS('Service Duration by unit'!$C$1:$C$400,'Service Duration by unit'!$A$1:$A$400,$J7,'Service Duration by unit'!$C$1:$C$400,">="&IF($H7=$M$4,N$4,N$3)))),1))*$L7/3600)*(1+$M7)} -> 0 | BX7: {=(IF($H7=$M$4,N$4*$I7,N$3*$I7)+(INDEX(_xlfn._xlws.FILTER('Service Duration by unit'!$D$1:$D$400,('Service Duration by unit'!$A$1:$A$400=$J7)*('Service Duration by unit'!$C$1:$C$400=_xlfn.MINIFS('Service Duration by unit'!$C$1:$C$400,'Service Duration by unit'!$A$1:$A$400,$J7,'Service Duration by unit'!$C$1:$C$400,">="&IF($H7=$M$4,N$4,N$3)))),1))*$L7/3600)*(1+$M7)} -> 0 | BY7: {=(IF($H7=$M$4,N$4*$I7,N$3*$I7)+(INDEX(_xlfn._xlws.FILTER('Service Duration by unit'!$D$1:$D$400,('Service Duration by unit'!$A$1:$A$400=$J7)*('Service Duration by unit'!$C$1:$C$400=_xlfn.MINIFS('Service Duration by unit'!$C$1:$C$400,'Service Duration by unit'!$A$1:$A$400,$J7,'Service Duration by unit'!$C$1:$C$400,">="&IF($H7=$M$4,N$4,N$3)))),1))*$L7/3600)*(1+$M7)} -> 0 | BZ7: {=(IF($H7=$M$4,N$4*$I7,N$3*$I7)+(INDEX(_xlfn._xlws.FILTER('Service Duration by unit'!$D$1:$D$400,('Service Duration by unit'!$A$1:$A$400=$J7)*('Service Duration by unit'!$C$1:$C$400=_xlfn.MINIFS('Service Duration by unit'!$C$1:$C$400,'Service Duration by unit'!$A$1:$A$400,$J7,'Service Duration by unit'!$C$1:$C$400,">="&IF($H7=$M$4,N$4,N$3)))),1))*$L7/3600)*(1+$M7)} -> 0 | CA7: {=(IF($H7=$M$4,N$4*$I7,N$3*$I7)+(INDEX(_xlfn._xlws.FILTER('Service Duration by unit'!$D$1:$D$400,('Service Duration by unit'!$A$1:$A$400=$J7)*('Service Duration by unit'!$C$1:$C$400=_xlfn.MINIFS('Service Duration by unit'!$C$1:$C$400,'Service Duration by unit'!$A$1:$A$400,$J7,'Service Duration by unit'!$C$1:$C$400,">="&IF($H7=$M$4,N$4,N$3)))),1))*$L7/3600)*(1+$M7)} -> 0 | CB7: {=(IF($H7=$M$4,N$4*$I7,N$3*$I7)+(INDEX(_xlfn._xlws.FILTER('Service Duration by unit'!$D$1:$D$400,('Service Duration by unit'!$A$1:$A$400=$J7)*('Service Duration by unit'!$C$1:$C$400=_xlfn.MINIFS('Service Duration by unit'!$C$1:$C$400,'Service Duration by unit'!$A$1:$A$400,$J7,'Service Duration by unit'!$C$1:$C$400,">="&IF($H7=$M$4,N$4,N$3)))),1))*$L7/3600)*(1+$M7)} -> 0 | CC7: {=(IF($H7=$M$4,N$4*$I7,N$3*$I7)+(INDEX(_xlfn._xlws.FILTER('Service Duration by unit'!$D$1:$D$400,('Service Duration by unit'!$A$1:$A$400=$J7)*('Service Duration by unit'!$C$1:$C$400=_xlfn.MINIFS('Service Duration by unit'!$C$1:$C$400,'Service Duration by unit'!$A$1:$A$400,$J7,'Service Duration by unit'!$C$1:$C$400,">="&IF($H7=$M$4,N$4,N$3)))),1))*$L7/3600)*(1+$M7)} -> 0 | CD7: {=(IF($H7=$M$4,N$4*$I7,N$3*$I7)+(INDEX(_xlfn._xlws.FILTER('Service Duration by unit'!$D$1:$D$400,('Service Duration by unit'!$A$1:$A$400=$J7)*('Service Duration by unit'!$C$1:$C$400=_xlfn.MINIFS('Service Duration by unit'!$C$1:$C$400,'Service Duration by unit'!$A$1:$A$400,$J7,'Service Duration by unit'!$C$1:$C$400,">="&IF($H7=$M$4,N$4,N$3)))),1))*$L7/3600)*(1+$M7)} -> 0 | CE7: {=(IF($H7=$M$4,N$4*$I7,N$3*$I7)+(INDEX(_xlfn._xlws.FILTER('Service Duration by unit'!$D$1:$D$400,('Service Duration by unit'!$A$1:$A$400=$J7)*('Service Duration by unit'!$C$1:$C$400=_xlfn.MINIFS('Service Duration by unit'!$C$1:$C$400,'Service Duration by unit'!$A$1:$A$400,$J7,'Service Duration by unit'!$C$1:$C$400,">="&IF($H7=$M$4,N$4,N$3)))),1))*$L7/3600)*(1+$M7)} -> 0 | CF7: {=(IF($H7=$M$4,N$4*$I7,N$3*$I7)+(INDEX(_xlfn._xlws.FILTER('Service Duration by unit'!$D$1:$D$400,('Service Duration by unit'!$A$1:$A$400=$J7)*('Service Duration by unit'!$C$1:$C$400=_xlfn.MINIFS('Service Duration by unit'!$C$1:$C$400,'Service Duration by unit'!$A$1:$A$400,$J7,'Service Duration by unit'!$C$1:$C$400,">="&IF($H7=$M$4,N$4,N$3)))),1))*$L7/3600)*(1+$M7)} -> 0 | CG7: {=(IF($H7=$M$4,N$4*$I7,N$3*$I7)+(INDEX(_xlfn._xlws.FILTER('Service Duration by unit'!$D$1:$D$400,('Service Duration by unit'!$A$1:$A$400=$J7)*('Service Duration by unit'!$C$1:$C$400=_xlfn.MINIFS('Service Duration by unit'!$C$1:$C$400,'Service Duration by unit'!$A$1:$A$400,$J7,'Service Duration by unit'!$C$1:$C$400,">="&IF($H7=$M$4,N$4,N$3)))),1))*$L7/3600)*(1+$M7)} -> 0 | CH7: {=(IF($H7=$M$4,N$4*$I7,N$3*$I7)+(INDEX(_xlfn._xlws.FILTER('Service Duration by unit'!$D$1:$D$400,('Service Duration by unit'!$A$1:$A$400=$J7)*('Service Duration by unit'!$C$1:$C$400=_xlfn.MINIFS('Service Duration by unit'!$C$1:$C$400,'Service Duration by unit'!$A$1:$A$400,$J7,'Service Duration by unit'!$C$1:$C$400,">="&IF($H7=$M$4,N$4,N$3)))),1))*$L7/3600)*(1+$M7)} -> 0 | CI7: {=(IF($H7=$M$4,N$4*$I7,N$3*$I7)+(INDEX(_xlfn._xlws.FILTER('Service Duration by unit'!$D$1:$D$400,('Service Duration by unit'!$A$1:$A$400=$J7)*('Service Duration by unit'!$C$1:$C$400=_xlfn.MINIFS('Service Duration by unit'!$C$1:$C$400,'Service Duration by unit'!$A$1:$A$400,$J7,'Service Duration by unit'!$C$1:$C$400,">="&IF($H7=$M$4,N$4,N$3)))),1))*$L7/3600)*(1+$M7)} -> 0 | CJ7: {=(IF($H7=$M$4,N$4*$I7,N$3*$I7)+(INDEX(_xlfn._xlws.FILTER('Service Duration by unit'!$D$1:$D$400,('Service Duration by unit'!$A$1:$A$400=$J7)*('Service Duration by unit'!$C$1:$C$400=_xlfn.MINIFS('Service Duration by unit'!$C$1:$C$400,'Service Duration by unit'!$A$1:$A$400,$J7,'Service Duration by unit'!$C$1:$C$400,">="&IF($H7=$M$4,N$4,N$3)))),1))*$L7/3600)*(1+$M7)} -> 0 | CK7: {=(IF($H7=$M$4,N$4*$I7,N$3*$I7)+(INDEX(_xlfn._xlws.FILTER('Service Duration by unit'!$D$1:$D$400,('Service Duration by unit'!$A$1:$A$400=$J7)*('Service Duration by unit'!$C$1:$C$400=_xlfn.MINIFS('Service Duration by unit'!$C$1:$C$400,'Service Duration by unit'!$A$1:$A$400,$J7,'Service Duration by unit'!$C$1:$C$400,">="&IF($H7=$M$4,N$4,N$3)))),1))*$L7/3600)*(1+$M7)} -> 0 | CL7: {=(IF($H7=$M$4,N$4*$I7,N$3*$I7)+(INDEX(_xlfn._xlws.FILTER('Service Duration by unit'!$D$1:$D$400,('Service Duration by unit'!$A$1:$A$400=$J7)*('Service Duration by unit'!$C$1:$C$400=_xlfn.MINIFS('Service Duration by unit'!$C$1:$C$400,'Service Duration by unit'!$A$1:$A$400,$J7,'Service Duration by unit'!$C$1:$C$400,">="&IF($H7=$M$4,N$4,N$3)))),1))*$L7/3600)*(1+$M7)} -> 0 | CM7: {=(IF($H7=$M$4,N$4*$I7,N$3*$I7)+(INDEX(_xlfn._xlws.FILTER('Service Duration by unit'!$D$1:$D$400,('Service Duration by unit'!$A$1:$A$400=$J7)*('Service Duration by unit'!$C$1:$C$400=_xlfn.MINIFS('Service Duration by unit'!$C$1:$C$400,'Service Duration by unit'!$A$1:$A$400,$J7,'Service Duration by unit'!$C$1:$C$400,">="&IF($H7=$M$4,N$4,N$3)))),1))*$L7/3600)*(1+$M7)} -> 0 | CN7: {=(IF($H7=$M$4,N$4*$I7,N$3*$I7)+(INDEX(_xlfn._xlws.FILTER('Service Duration by unit'!$D$1:$D$400,('Service Duration by unit'!$A$1:$A$400=$J7)*('Service Duration by unit'!$C$1:$C$400=_xlfn.MINIFS('Service Duration by unit'!$C$1:$C$400,'Service Duration by unit'!$A$1:$A$400,$J7,'Service Duration by unit'!$C$1:$C$400,">="&IF($H7=$M$4,N$4,N$3)))),1))*$L7/3600)*(1+$M7)} -> 0 | CO7: {=(IF($H7=$M$4,N$4*$I7,N$3*$I7)+(INDEX(_xlfn._xlws.FILTER('Service Duration by unit'!$D$1:$D$400,('Service Duration by unit'!$A$1:$A$400=$J7)*('Service Duration by unit'!$C$1:$C$400=_xlfn.MINIFS('Service Duration by unit'!$C$1:$C$400,'Service Duration by unit'!$A$1:$A$400,$J7,'Service Duration by unit'!$C$1:$C$400,">="&IF($H7=$M$4,N$4,N$3)))),1))*$L7/3600)*(1+$M7)} -> 0 | CP7: {=(IF($H7=$M$4,N$4*$I7,N$3*$I7)+(INDEX(_xlfn._xlws.FILTER('Service Duration by unit'!$D$1:$D$400,('Service Duration by unit'!$A$1:$A$400=$J7)*('Service Duration by unit'!$C$1:$C$400=_xlfn.MINIFS('Service Duration by unit'!$C$1:$C$400,'Service Duration by unit'!$A$1:$A$400,$J7,'Service Duration by unit'!$C$1:$C$400,">="&IF($H7=$M$4,N$4,N$3)))),1))*$L7/3600)*(1+$M7)} -> 0 | CQ7: {=(IF($H7=$M$4,N$4*$I7,N$3*$I7)+(INDEX(_xlfn._xlws.FILTER('Service Duration by unit'!$D$1:$D$400,('Service Duration by unit'!$A$1:$A$400=$J7)*('Service Duration by unit'!$C$1:$C$400=_xlfn.MINIFS('Service Duration by unit'!$C$1:$C$400,'Service Duration by unit'!$A$1:$A$400,$J7,'Service Duration by unit'!$C$1:$C$400,">="&IF($H7=$M$4,N$4,N$3)))),1))*$L7/3600)*(1+$M7)} -> 0 | CR7: {=(IF($H7=$M$4,N$4*$I7,N$3*$I7)+(INDEX(_xlfn._xlws.FILTER('Service Duration by unit'!$D$1:$D$400,('Service Duration by unit'!$A$1:$A$400=$J7)*('Service Duration by unit'!$C$1:$C$400=_xlfn.MINIFS('Service Duration by unit'!$C$1:$C$400,'Service Duration by unit'!$A$1:$A$400,$J7,'Service Duration by unit'!$C$1:$C$400,">="&IF($H7=$M$4,N$4,N$3)))),1))*$L7/3600)*(1+$M7)} -> 0 | CS7: {=(IF($H7=$M$4,N$4*$I7,N$3*$I7)+(INDEX(_xlfn._xlws.FILTER('Service Duration by unit'!$D$1:$D$400,('Service Duration by unit'!$A$1:$A$400=$J7)*('Service Duration by unit'!$C$1:$C$400=_xlfn.MINIFS('Service Duration by unit'!$C$1:$C$400,'Service Duration by unit'!$A$1:$A$400,$J7,'Service Duration by unit'!$C$1:$C$400,">="&IF($H7=$M$4,N$4,N$3)))),1))*$L7/3600)*(1+$M7)} -> 0 | CT7: {=(IF($H7=$M$4,N$4*$I7,N$3*$I7)+(INDEX(_xlfn._xlws.FILTER('Service Duration by unit'!$D$1:$D$400,('Service Duration by unit'!$A$1:$A$400=$J7)*('Service Duration by unit'!$C$1:$C$400=_xlfn.MINIFS('Service Duration by unit'!$C$1:$C$400,'Service Duration by unit'!$A$1:$A$400,$J7,'Service Duration by unit'!$C$1:$C$400,">="&IF($H7=$M$4,N$4,N$3)))),1))*$L7/3600)*(1+$M7)} -> 0 | CU7: {=(IF($H7=$M$4,N$4*$I7,N$3*$I7)+(INDEX(_xlfn._xlws.FILTER('Service Duration by unit'!$D$1:$D$400,('Service Duration by unit'!$A$1:$A$400=$J7)*('Service Duration by unit'!$C$1:$C$400=_xlfn.MINIFS('Service Duration by unit'!$C$1:$C$400,'Service Duration by unit'!$A$1:$A$400,$J7,'Service Duration by unit'!$C$1:$C$400,">="&IF($H7=$M$4,N$4,N$3)))),1))*$L7/3600)*(1+$M7)} -> 0 | CV7: {=(IF($H7=$M$4,N$4*$I7,N$3*$I7)+(INDEX(_xlfn._xlws.FILTER('Service Duration by unit'!$D$1:$D$400,('Service Duration by unit'!$A$1:$A$400=$J7)*('Service Duration by unit'!$C$1:$C$400=_xlfn.MINIFS('Service Duration by unit'!$C$1:$C$400,'Service Duration by unit'!$A$1:$A$400,$J7,'Service Duration by unit'!$C$1:$C$400,">="&IF($H7=$M$4,N$4,N$3)))),1))*$L7/3600)*(1+$M7)} -> 0 | CW7: {=(IF($H7=$M$4,N$4*$I7,N$3*$I7)+(INDEX(_xlfn._xlws.FILTER('Service Duration by unit'!$D$1:$D$400,('Service Duration by unit'!$A$1:$A$400=$J7)*('Service Duration by unit'!$C$1:$C$400=_xlfn.MINIFS('Service Duration by unit'!$C$1:$C$400,'Service Duration by unit'!$A$1:$A$400,$J7,'Service Duration by unit'!$C$1:$C$400,">="&IF($H7=$M$4,N$4,N$3)))),1))*$L7/3600)*(1+$M7)} -> 0 | CX7: {=(IF($H7=$M$4,N$4*$I7,N$3*$I7)+(INDEX(_xlfn._xlws.FILTER('Service Duration by unit'!$D$1:$D$400,('Service Duration by unit'!$A$1:$A$400=$J7)*('Service Duration by unit'!$C$1:$C$400=_xlfn.MINIFS('Service Duration by unit'!$C$1:$C$400,'Service Duration by unit'!$A$1:$A$400,$J7,'Service Duration by unit'!$C$1:$C$400,">="&IF($H7=$M$4,N$4,N$3)))),1))*$L7/3600)*(1+$M7)} -> 0 | CY7: {=(IF($H7=$M$4,N$4*$I7,N$3*$I7)+(INDEX(_xlfn._xlws.FILTER('Service Duration by unit'!$D$1:$D$400,('Service Duration by unit'!$A$1:$A$400=$J7)*('Service Duration by unit'!$C$1:$C$400=_xlfn.MINIFS('Service Duration by unit'!$C$1:$C$400,'Service Duration by unit'!$A$1:$A$400,$J7,'Service Duration by unit'!$C$1:$C$400,">="&IF($H7=$M$4,N$4,N$3)))),1))*$L7/3600)*(1+$M7)} -> 0 | CZ7: {=(IF($H7=$M$4,N$4*$I7,N$3*$I7)+(INDEX(_xlfn._xlws.FILTER('Service Duration by unit'!$D$1:$D$400,('Service Duration by unit'!$A$1:$A$400=$J7)*('Service Duration by unit'!$C$1:$C$400=_xlfn.MINIFS('Service Duration by unit'!$C$1:$C$400,'Service Duration by unit'!$A$1:$A$400,$J7,'Service Duration by unit'!$C$1:$C$400,">="&IF($H7=$M$4,N$4,N$3)))),1))*$L7/3600)*(1+$M7)} -> 0 | DA7: {=(IF($H7=$M$4,N$4*$I7,N$3*$I7)+(INDEX(_xlfn._xlws.FILTER('Service Duration by unit'!$D$1:$D$400,('Service Duration by unit'!$A$1:$A$400=$J7)*('Service Duration by unit'!$C$1:$C$400=_xlfn.MINIFS('Service Duration by unit'!$C$1:$C$400,'Service Duration by unit'!$A$1:$A$400,$J7,'Service Duration by unit'!$C$1:$C$400,">="&IF($H7=$M$4,N$4,N$3)))),1))*$L7/3600)*(1+$M7)} -> 0 | DB7: {=(IF($H7=$M$4,N$4*$I7,N$3*$I7)+(INDEX(_xlfn._xlws.FILTER('Service Duration by unit'!$D$1:$D$400,('Service Duration by unit'!$A$1:$A$400=$J7)*('Service Duration by unit'!$C$1:$C$400=_xlfn.MINIFS('Service Duration by unit'!$C$1:$C$400,'Service Duration by unit'!$A$1:$A$400,$J7,'Service Duration by unit'!$C$1:$C$400,">="&IF($H7=$M$4,N$4,N$3)))),1))*$L7/3600)*(1+$M7)} -> 0 | DC7: {=(IF($H7=$M$4,N$4*$I7,N$3*$I7)+(INDEX(_xlfn._xlws.FILTER('Service Duration by unit'!$D$1:$D$400,('Service Duration by unit'!$A$1:$A$400=$J7)*('Service Duration by unit'!$C$1:$C$400=_xlfn.MINIFS('Service Duration by unit'!$C$1:$C$400,'Service Duration by unit'!$A$1:$A$400,$J7,'Service Duration by unit'!$C$1:$C$400,">="&IF($H7=$M$4,N$4,N$3)))),1))*$L7/3600)*(1+$M7)} -> 0 | DD7: {=(IF($H7=$M$4,N$4*$I7,N$3*$I7)+(INDEX(_xlfn._xlws.FILTER('Service Duration by unit'!$D$1:$D$400,('Service Duration by unit'!$A$1:$A$400=$J7)*('Service Duration by unit'!$C$1:$C$400=_xlfn.MINIFS('Service Duration by unit'!$C$1:$C$400,'Service Duration by unit'!$A$1:$A$400,$J7,'Service Duration by unit'!$C$1:$C$400,">="&IF($H7=$M$4,N$4,N$3)))),1))*$L7/3600)*(1+$M7)} -> 0 | DE7: {=(IF($H7=$M$4,N$4*$I7,N$3*$I7)+(INDEX(_xlfn._xlws.FILTER('Service Duration by unit'!$D$1:$D$400,('Service Duration by unit'!$A$1:$A$400=$J7)*('Service Duration by unit'!$C$1:$C$400=_xlfn.MINIFS('Service Duration by unit'!$C$1:$C$400,'Service Duration by unit'!$A$1:$A$400,$J7,'Service Duration by unit'!$C$1:$C$400,">="&IF($H7=$M$4,N$4,N$3)))),1))*$L7/3600)*(1+$M7)} -> 0 | DF7: {=(IF($H7=$M$4,N$4*$I7,N$3*$I7)+(INDEX(_xlfn._xlws.FILTER('Service Duration by unit'!$D$1:$D$400,('Service Duration by unit'!$A$1:$A$400=$J7)*('Service Duration by unit'!$C$1:$C$400=_xlfn.MINIFS('Service Duration by unit'!$C$1:$C$400,'Service Duration by unit'!$A$1:$A$400,$J7,'Service Duration by unit'!$C$1:$C$400,">="&IF($H7=$M$4,N$4,N$3)))),1))*$L7/3600)*(1+$M7)} -> 0 | DG7: {=(IF($H7=$M$4,N$4*$I7,N$3*$I7)+(INDEX(_xlfn._xlws.FILTER('Service Duration by unit'!$D$1:$D$400,('Service Duration by unit'!$A$1:$A$400=$J7)*('Service Duration by unit'!$C$1:$C$400=_xlfn.MINIFS('Service Duration by unit'!$C$1:$C$400,'Service Duration by unit'!$A$1:$A$400,$J7,'Service Duration by unit'!$C$1:$C$400,">="&IF($H7=$M$4,N$4,N$3)))),1))*$L7/3600)*(1+$M7)} -> 0 | DH7: {=(IF($H7=$M$4,N$4*$I7,N$3*$I7)+(INDEX(_xlfn._xlws.FILTER('Service Duration by unit'!$D$1:$D$400,('Service Duration by unit'!$A$1:$A$400=$J7)*('Service Duration by unit'!$C$1:$C$400=_xlfn.MINIFS('Service Duration by unit'!$C$1:$C$400,'Service Duration by unit'!$A$1:$A$400,$J7,'Service Duration by unit'!$C$1:$C$400,">="&IF($H7=$M$4,N$4,N$3)))),1))*$L7/3600)*(1+$M7)} -> 0 | DI7: {=(IF($H7=$M$4,N$4*$I7,N$3*$I7)+(INDEX(_xlfn._xlws.FILTER('Service Duration by unit'!$D$1:$D$400,('Service Duration by unit'!$A$1:$A$400=$J7)*('Service Duration by unit'!$C$1:$C$400=_xlfn.MINIFS('Service Duration by unit'!$C$1:$C$400,'Service Duration by unit'!$A$1:$A$400,$J7,'Service Duration by unit'!$C$1:$C$400,">="&IF($H7=$M$4,N$4,N$3)))),1))*$L7/3600)*(1+$M7)} -> 0 | DJ7: {=(IF($H7=$M$4,N$4*$I7,N$3*$I7)+(INDEX(_xlfn._xlws.FILTER('Service Duration by unit'!$D$1:$D$400,('Service Duration by unit'!$A$1:$A$400=$J7)*('Service Duration by unit'!$C$1:$C$400=_xlfn.MINIFS('Service Duration by unit'!$C$1:$C$400,'Service Duration by unit'!$A$1:$A$400,$J7,'Service Duration by unit'!$C$1:$C$400,">="&IF($H7=$M$4,N$4,N$3)))),1))*$L7/3600)*(1+$M7)} -> 0 | DK7: {=(IF($H7=$M$4,N$4*$I7,N$3*$I7)+(INDEX(_xlfn._xlws.FILTER('Service Duration by unit'!$D$1:$D$400,('Service Duration by unit'!$A$1:$A$400=$J7)*('Service Duration by unit'!$C$1:$C$400=_xlfn.MINIFS('Service Duration by unit'!$C$1:$C$400,'Service Duration by unit'!$A$1:$A$400,$J7,'Service Duration by unit'!$C$1:$C$400,">="&IF($H7=$M$4,N$4,N$3)))),1))*$L7/3600)*(1+$M7)} -> 0 | DL7: {=(IF($H7=$M$4,N$4*$I7,N$3*$I7)+(INDEX(_xlfn._xlws.FILTER('Service Duration by unit'!$D$1:$D$400,('Service Duration by unit'!$A$1:$A$400=$J7)*('Service Duration by unit'!$C$1:$C$400=_xlfn.MINIFS('Service Duration by unit'!$C$1:$C$400,'Service Duration by unit'!$A$1:$A$400,$J7,'Service Duration by unit'!$C$1:$C$400,">="&IF($H7=$M$4,N$4,N$3)))),1))*$L7/3600)*(1+$M7)} -> 0 | DM7: {=(IF($H7=$M$4,N$4*$I7,N$3*$I7)+(INDEX(_xlfn._xlws.FILTER('Service Duration by unit'!$D$1:$D$400,('Service Duration by unit'!$A$1:$A$400=$J7)*('Service Duration by unit'!$C$1:$C$400=_xlfn.MINIFS('Service Duration by unit'!$C$1:$C$400,'Service Duration by unit'!$A$1:$A$400,$J7,'Service Duration by unit'!$C$1:$C$400,">="&IF($H7=$M$4,N$4,N$3)))),1))*$L7/3600)*(1+$M7)} -> 0 | DN7: {=(IF($H7=$M$4,N$4*$I7,N$3*$I7)+(INDEX(_xlfn._xlws.FILTER('Service Duration by unit'!$D$1:$D$400,('Service Duration by unit'!$A$1:$A$400=$J7)*('Service Duration by unit'!$C$1:$C$400=_xlfn.MINIFS('Service Duration by unit'!$C$1:$C$400,'Service Duration by unit'!$A$1:$A$400,$J7,'Service Duration by unit'!$C$1:$C$400,">="&IF($H7=$M$4,N$4,N$3)))),1))*$L7/3600)*(1+$M7)} -> 0 | DO7: {=(IF($H7=$M$4,N$4*$I7,N$3*$I7)+(INDEX(_xlfn._xlws.FILTER('Service Duration by unit'!$D$1:$D$400,('Service Duration by unit'!$A$1:$A$400=$J7)*('Service Duration by unit'!$C$1:$C$400=_xlfn.MINIFS('Service Duration by unit'!$C$1:$C$400,'Service Duration by unit'!$A$1:$A$400,$J7,'Service Duration by unit'!$C$1:$C$400,">="&IF($H7=$M$4,N$4,N$3)))),1))*$L7/3600)*(1+$M7)} -> 0 | DP7: {=(IF($H7=$M$4,N$4*$I7,N$3*$I7)+(INDEX(_xlfn._xlws.FILTER('Service Duration by unit'!$D$1:$D$400,('Service Duration by unit'!$A$1:$A$400=$J7)*('Service Duration by unit'!$C$1:$C$400=_xlfn.MINIFS('Service Duration by unit'!$C$1:$C$400,'Service Duration by unit'!$A$1:$A$400,$J7,'Service Duration by unit'!$C$1:$C$400,">="&IF($H7=$M$4,N$4,N$3)))),1))*$L7/3600)*(1+$M7)} -> 0 | DQ7: {=(IF($H7=$M$4,N$4*$I7,N$3*$I7)+(INDEX(_xlfn._xlws.FILTER('Service Duration by unit'!$D$1:$D$400,('Service Duration by unit'!$A$1:$A$400=$J7)*('Service Duration by unit'!$C$1:$C$400=_xlfn.MINIFS('Service Duration by unit'!$C$1:$C$400,'Service Duration by unit'!$A$1:$A$400,$J7,'Service Duration by unit'!$C$1:$C$400,">="&IF($H7=$M$4,N$4,N$3)))),1))*$L7/3600)*(1+$M7)} -> 0 | DR7: {=(IF($H7=$M$4,N$4*$I7,N$3*$I7)+(INDEX(_xlfn._xlws.FILTER('Service Duration by unit'!$D$1:$D$400,('Service Duration by unit'!$A$1:$A$400=$J7)*('Service Duration by unit'!$C$1:$C$400=_xlfn.MINIFS('Service Duration by unit'!$C$1:$C$400,'Service Duration by unit'!$A$1:$A$400,$J7,'Service Duration by unit'!$C$1:$C$400,">="&IF($H7=$M$4,N$4,N$3)))),1))*$L7/3600)*(1+$M7)} -> 0 | DS7: {=(IF($H7=$M$4,N$4*$I7,N$3*$I7)+(INDEX(_xlfn._xlws.FILTER('Service Duration by unit'!$D$1:$D$400,('Service Duration by unit'!$A$1:$A$400=$J7)*('Service Duration by unit'!$C$1:$C$400=_xlfn.MINIFS('Service Duration by unit'!$C$1:$C$400,'Service Duration by unit'!$A$1:$A$400,$J7,'Service Duration by unit'!$C$1:$C$400,">="&IF($H7=$M$4,N$4,N$3)))),1))*$L7/3600)*(1+$M7)} -> 0 | DT7: {=(IF($H7=$M$4,N$4*$I7,N$3*$I7)+(INDEX(_xlfn._xlws.FILTER('Service Duration by unit'!$D$1:$D$400,('Service Duration by unit'!$A$1:$A$400=$J7)*('Service Duration by unit'!$C$1:$C$400=_xlfn.MINIFS('Service Duration by unit'!$C$1:$C$400,'Service Duration by unit'!$A$1:$A$400,$J7,'Service Duration by unit'!$C$1:$C$400,">="&IF($H7=$M$4,N$4,N$3)))),1))*$L7/3600)*(1+$M7)} -> 0 | DU7: {=(IF($H7=$M$4,N$4*$I7,N$3*$I7)+(INDEX(_xlfn._xlws.FILTER('Service Duration by unit'!$D$1:$D$400,('Service Duration by unit'!$A$1:$A$400=$J7)*('Service Duration by unit'!$C$1:$C$400=_xlfn.MINIFS('Service Duration by unit'!$C$1:$C$400,'Service Duration by unit'!$A$1:$A$400,$J7,'Service Duration by unit'!$C$1:$C$400,">="&IF($H7=$M$4,N$4,N$3)))),1))*$L7/3600)*(1+$M7)} -> 0 | DV7: {=(IF($H7=$M$4,N$4*$I7,N$3*$I7)+(INDEX(_xlfn._xlws.FILTER('Service Duration by unit'!$D$1:$D$400,('Service Duration by unit'!$A$1:$A$400=$J7)*('Service Duration by unit'!$C$1:$C$400=_xlfn.MINIFS('Service Duration by unit'!$C$1:$C$400,'Service Duration by unit'!$A$1:$A$400,$J7,'Service Duration by unit'!$C$1:$C$400,">="&IF($H7=$M$4,N$4,N$3)))),1))*$L7/3600)*(1+$M7)} -> 0 | DW7: {=(IF($H7=$M$4,N$4*$I7,N$3*$I7)+(INDEX(_xlfn._xlws.FILTER('Service Duration by unit'!$D$1:$D$400,('Service Duration by unit'!$A$1:$A$400=$J7)*('Service Duration by unit'!$C$1:$C$400=_xlfn.MINIFS('Service Duration by unit'!$C$1:$C$400,'Service Duration by unit'!$A$1:$A$400,$J7,'Service Duration by unit'!$C$1:$C$400,">="&IF($H7=$M$4,N$4,N$3)))),1))*$L7/3600)*(1+$M7)} -> 0 | DX7: {=(IF($H7=$M$4,N$4*$I7,N$3*$I7)+(INDEX(_xlfn._xlws.FILTER('Service Duration by unit'!$D$1:$D$400,('Service Duration by unit'!$A$1:$A$400=$J7)*('Service Duration by unit'!$C$1:$C$400=_xlfn.MINIFS('Service Duration by unit'!$C$1:$C$400,'Service Duration by unit'!$A$1:$A$400,$J7,'Service Duration by unit'!$C$1:$C$400,">="&IF($H7=$M$4,N$4,N$3)))),1))*$L7/3600)*(1+$M7)} -> 0 | DY7: {=(IF($H7=$M$4,N$4*$I7,N$3*$I7)+(INDEX(_xlfn._xlws.FILTER('Service Duration by unit'!$D$1:$D$400,('Service Duration by unit'!$A$1:$A$400=$J7)*('Service Duration by unit'!$C$1:$C$400=_xlfn.MINIFS('Service Duration by unit'!$C$1:$C$400,'Service Duration by unit'!$A$1:$A$400,$J7,'Service Duration by unit'!$C$1:$C$400,">="&IF($H7=$M$4,N$4,N$3)))),1))*$L7/3600)*(1+$M7)} -> 0 | DZ7: {=(IF($H7=$M$4,N$4*$I7,N$3*$I7)+(INDEX(_xlfn._xlws.FILTER('Service Duration by unit'!$D$1:$D$400,('Service Duration by unit'!$A$1:$A$400=$J7)*('Service Duration by unit'!$C$1:$C$400=_xlfn.MINIFS('Service Duration by unit'!$C$1:$C$400,'Service Duration by unit'!$A$1:$A$400,$J7,'Service Duration by unit'!$C$1:$C$400,">="&IF($H7=$M$4,N$4,N$3)))),1))*$L7/3600)*(1+$M7)} -> 0 | EA7: {=(IF($H7=$M$4,N$4*$I7,N$3*$I7)+(INDEX(_xlfn._xlws.FILTER('Service Duration by unit'!$D$1:$D$400,('Service Duration by unit'!$A$1:$A$400=$J7)*('Service Duration by unit'!$C$1:$C$400=_xlfn.MINIFS('Service Duration by unit'!$C$1:$C$400,'Service Duration by unit'!$A$1:$A$400,$J7,'Service Duration by unit'!$C$1:$C$400,">="&IF($H7=$M$4,N$4,N$3)))),1))*$L7/3600)*(1+$M7)} -> 0 | EB7: {=(IF($H7=$M$4,N$4*$I7,N$3*$I7)+(INDEX(_xlfn._xlws.FILTER('Service Duration by unit'!$D$1:$D$400,('Service Duration by unit'!$A$1:$A$400=$J7)*('Service Duration by unit'!$C$1:$C$400=_xlfn.MINIFS('Service Duration by unit'!$C$1:$C$400,'Service Duration by unit'!$A$1:$A$400,$J7,'Service Duration by unit'!$C$1:$C$400,">="&IF($H7=$M$4,N$4,N$3)))),1))*$L7/3600)*(1+$M7)} -> 0 | EC7: {=(IF($H7=$M$4,N$4*$I7,N$3*$I7)+(INDEX(_xlfn._xlws.FILTER('Service Duration by unit'!$D$1:$D$400,('Service Duration by unit'!$A$1:$A$400=$J7)*('Service Duration by unit'!$C$1:$C$400=_xlfn.MINIFS('Service Duration by unit'!$C$1:$C$400,'Service Duration by unit'!$A$1:$A$400,$J7,'Service Duration by unit'!$C$1:$C$400,">="&IF($H7=$M$4,N$4,N$3)))),1))*$L7/3600)*(1+$M7)} -> 0 | ED7: {=(IF($H7=$M$4,N$4*$I7,N$3*$I7)+(INDEX(_xlfn._xlws.FILTER('Service Duration by unit'!$D$1:$D$400,('Service Duration by unit'!$A$1:$A$400=$J7)*('Service Duration by unit'!$C$1:$C$400=_xlfn.MINIFS('Service Duration by unit'!$C$1:$C$400,'Service Duration by unit'!$A$1:$A$400,$J7,'Service Duration by unit'!$C$1:$C$400,">="&IF($H7=$M$4,N$4,N$3)))),1))*$L7/3600)*(1+$M7)} -> 0 | EE7: {=(IF($H7=$M$4,N$4*$I7,N$3*$I7)+(INDEX(_xlfn._xlws.FILTER('Service Duration by unit'!$D$1:$D$400,('Service Duration by unit'!$A$1:$A$400=$J7)*('Service Duration by unit'!$C$1:$C$400=_xlfn.MINIFS('Service Duration by unit'!$C$1:$C$400,'Service Duration by unit'!$A$1:$A$400,$J7,'Service Duration by unit'!$C$1:$C$400,">="&IF($H7=$M$4,N$4,N$3)))),1))*$L7/3600)*(1+$M7)} -> 0 | EF7: {=(IF($H7=$M$4,N$4*$I7,N$3*$I7)+(INDEX(_xlfn._xlws.FILTER('Service Duration by unit'!$D$1:$D$400,('Service Duration by unit'!$A$1:$A$400=$J7)*('Service Duration by unit'!$C$1:$C$400=_xlfn.MINIFS('Service Duration by unit'!$C$1:$C$400,'Service Duration by unit'!$A$1:$A$400,$J7,'Service Duration by unit'!$C$1:$C$400,">="&IF($H7=$M$4,N$4,N$3)))),1))*$L7/3600)*(1+$M7)} -> 0 | EG7: {=(IF($H7=$M$4,N$4*$I7,N$3*$I7)+(INDEX(_xlfn._xlws.FILTER('Service Duration by unit'!$D$1:$D$400,('Service Duration by unit'!$A$1:$A$400=$J7)*('Service Duration by unit'!$C$1:$C$400=_xlfn.MINIFS('Service Duration by unit'!$C$1:$C$400,'Service Duration by unit'!$A$1:$A$400,$J7,'Service Duration by unit'!$C$1:$C$400,">="&IF($H7=$M$4,N$4,N$3)))),1))*$L7/3600)*(1+$M7)} -> 0 | EH7: {=(IF($H7=$M$4,N$4*$I7,N$3*$I7)+(INDEX(_xlfn._xlws.FILTER('Service Duration by unit'!$D$1:$D$400,('Service Duration by unit'!$A$1:$A$400=$J7)*('Service Duration by unit'!$C$1:$C$400=_xlfn.MINIFS('Service Duration by unit'!$C$1:$C$400,'Service Duration by unit'!$A$1:$A$400,$J7,'Service Duration by unit'!$C$1:$C$400,">="&IF($H7=$M$4,N$4,N$3)))),1))*$L7/3600)*(1+$M7)} -> 0 | EI7: {=(IF($H7=$M$4,N$4*$I7,N$3*$I7)+(INDEX(_xlfn._xlws.FILTER('Service Duration by unit'!$D$1:$D$400,('Service Duration by unit'!$A$1:$A$400=$J7)*('Service Duration by unit'!$C$1:$C$400=_xlfn.MINIFS('Service Duration by unit'!$C$1:$C$400,'Service Duration by unit'!$A$1:$A$400,$J7,'Service Duration by unit'!$C$1:$C$400,">="&IF($H7=$M$4,N$4,N$3)))),1))*$L7/3600)*(1+$M7)} -> 0 | EJ7: {=(IF($H7=$M$4,N$4*$I7,N$3*$I7)+(INDEX(_xlfn._xlws.FILTER('Service Duration by unit'!$D$1:$D$400,('Service Duration by unit'!$A$1:$A$400=$J7)*('Service Duration by unit'!$C$1:$C$400=_xlfn.MINIFS('Service Duration by unit'!$C$1:$C$400,'Service Duration by unit'!$A$1:$A$400,$J7,'Service Duration by unit'!$C$1:$C$400,">="&IF($H7=$M$4,N$4,N$3)))),1))*$L7/3600)*(1+$M7)} -> 0 | EK7: {=(IF($H7=$M$4,N$4*$I7,N$3*$I7)+(INDEX(_xlfn._xlws.FILTER('Service Duration by unit'!$D$1:$D$400,('Service Duration by unit'!$A$1:$A$400=$J7)*('Service Duration by unit'!$C$1:$C$400=_xlfn.MINIFS('Service Duration by unit'!$C$1:$C$400,'Service Duration by unit'!$A$1:$A$400,$J7,'Service Duration by unit'!$C$1:$C$400,">="&IF($H7=$M$4,N$4,N$3)))),1))*$L7/3600)*(1+$M7)} -> 0 | EL7: {=(IF($H7=$M$4,N$4*$I7,N$3*$I7)+(INDEX(_xlfn._xlws.FILTER('Service Duration by unit'!$D$1:$D$400,('Service Duration by unit'!$A$1:$A$400=$J7)*('Service Duration by unit'!$C$1:$C$400=_xlfn.MINIFS('Service Duration by unit'!$C$1:$C$400,'Service Duration by unit'!$A$1:$A$400,$J7,'Service Duration by unit'!$C$1:$C$400,">="&IF($H7=$M$4,N$4,N$3)))),1))*$L7/3600)*(1+$M7)} -> 0 | EM7: {=(IF($H7=$M$4,N$4*$I7,N$3*$I7)+(INDEX(_xlfn._xlws.FILTER('Service Duration by unit'!$D$1:$D$400,('Service Duration by unit'!$A$1:$A$400=$J7)*('Service Duration by unit'!$C$1:$C$400=_xlfn.MINIFS('Service Duration by unit'!$C$1:$C$400,'Service Duration by unit'!$A$1:$A$400,$J7,'Service Duration by unit'!$C$1:$C$400,">="&IF($H7=$M$4,N$4,N$3)))),1))*$L7/3600)*(1+$M7)} -> 0 | EN7: {=(IF($H7=$M$4,N$4*$I7,N$3*$I7)+(INDEX(_xlfn._xlws.FILTER('Service Duration by unit'!$D$1:$D$400,('Service Duration by unit'!$A$1:$A$400=$J7)*('Service Duration by unit'!$C$1:$C$400=_xlfn.MINIFS('Service Duration by unit'!$C$1:$C$400,'Service Duration by unit'!$A$1:$A$400,$J7,'Service Duration by unit'!$C$1:$C$400,">="&IF($H7=$M$4,N$4,N$3)))),1))*$L7/3600)*(1+$M7)} -> 0 | EO7: {=(IF($H7=$M$4,N$4*$I7,N$3*$I7)+(INDEX(_xlfn._xlws.FILTER('Service Duration by unit'!$D$1:$D$400,('Service Duration by unit'!$A$1:$A$400=$J7)*('Service Duration by unit'!$C$1:$C$400=_xlfn.MINIFS('Service Duration by unit'!$C$1:$C$400,'Service Duration by unit'!$A$1:$A$400,$J7,'Service Duration by unit'!$C$1:$C$400,">="&IF($H7=$M$4,N$4,N$3)))),1))*$L7/3600)*(1+$M7)} -> 0 | EP7: {=(IF($H7=$M$4,N$4*$I7,N$3*$I7)+(INDEX(_xlfn._xlws.FILTER('Service Duration by unit'!$D$1:$D$400,('Service Duration by unit'!$A$1:$A$400=$J7)*('Service Duration by unit'!$C$1:$C$400=_xlfn.MINIFS('Service Duration by unit'!$C$1:$C$400,'Service Duration by unit'!$A$1:$A$400,$J7,'Service Duration by unit'!$C$1:$C$400,">="&IF($H7=$M$4,N$4,N$3)))),1))*$L7/3600)*(1+$M7)} -> 0 | EQ7: {=(IF($H7=$M$4,N$4*$I7,N$3*$I7)+(INDEX(_xlfn._xlws.FILTER('Service Duration by unit'!$D$1:$D$400,('Service Duration by unit'!$A$1:$A$400=$J7)*('Service Duration by unit'!$C$1:$C$400=_xlfn.MINIFS('Service Duration by unit'!$C$1:$C$400,'Service Duration by unit'!$A$1:$A$400,$J7,'Service Duration by unit'!$C$1:$C$400,">="&IF($H7=$M$4,N$4,N$3)))),1))*$L7/3600)*(1+$M7)} -> 0 | ER7: {=(IF($H7=$M$4,N$4*$I7,N$3*$I7)+(INDEX(_xlfn._xlws.FILTER('Service Duration by unit'!$D$1:$D$400,('Service Duration by unit'!$A$1:$A$400=$J7)*('Service Duration by unit'!$C$1:$C$400=_xlfn.MINIFS('Service Duration by unit'!$C$1:$C$400,'Service Duration by unit'!$A$1:$A$400,$J7,'Service Duration by unit'!$C$1:$C$400,">="&IF($H7=$M$4,N$4,N$3)))),1))*$L7/3600)*(1+$M7)} -> 0 | ES7: {=(IF($H7=$M$4,N$4*$I7,N$3*$I7)+(INDEX(_xlfn._xlws.FILTER('Service Duration by unit'!$D$1:$D$400,('Service Duration by unit'!$A$1:$A$400=$J7)*('Service Duration by unit'!$C$1:$C$400=_xlfn.MINIFS('Service Duration by unit'!$C$1:$C$400,'Service Duration by unit'!$A$1:$A$400,$J7,'Service Duration by unit'!$C$1:$C$400,">="&IF($H7=$M$4,N$4,N$3)))),1))*$L7/3600)*(1+$M7)} -> 0 | ET7: {=(IF($H7=$M$4,N$4*$I7,N$3*$I7)+(INDEX(_xlfn._xlws.FILTER('Service Duration by unit'!$D$1:$D$400,('Service Duration by unit'!$A$1:$A$400=$J7)*('Service Duration by unit'!$C$1:$C$400=_xlfn.MINIFS('Service Duration by unit'!$C$1:$C$400,'Service Duration by unit'!$A$1:$A$400,$J7,'Service Duration by unit'!$C$1:$C$400,">="&IF($H7=$M$4,N$4,N$3)))),1))*$L7/3600)*(1+$M7)} -> 0 | EU7: {=(IF($H7=$M$4,N$4*$I7,N$3*$I7)+(INDEX(_xlfn._xlws.FILTER('Service Duration by unit'!$D$1:$D$400,('Service Duration by unit'!$A$1:$A$400=$J7)*('Service Duration by unit'!$C$1:$C$400=_xlfn.MINIFS('Service Duration by unit'!$C$1:$C$400,'Service Duration by unit'!$A$1:$A$400,$J7,'Service Duration by unit'!$C$1:$C$400,">="&IF($H7=$M$4,N$4,N$3)))),1))*$L7/3600)*(1+$M7)} -> 0 | EV7: {=(IF($H7=$M$4,N$4*$I7,N$3*$I7)+(INDEX(_xlfn._xlws.FILTER('Service Duration by unit'!$D$1:$D$400,('Service Duration by unit'!$A$1:$A$400=$J7)*('Service Duration by unit'!$C$1:$C$400=_xlfn.MINIFS('Service Duration by unit'!$C$1:$C$400,'Service Duration by unit'!$A$1:$A$400,$J7,'Service Duration by unit'!$C$1:$C$400,">="&IF($H7=$M$4,N$4,N$3)))),1))*$L7/3600)*(1+$M7)} -> 0 | EW7: {=(IF($H7=$M$4,N$4*$I7,N$3*$I7)+(INDEX(_xlfn._xlws.FILTER('Service Duration by unit'!$D$1:$D$400,('Service Duration by unit'!$A$1:$A$400=$J7)*('Service Duration by unit'!$C$1:$C$400=_xlfn.MINIFS('Service Duration by unit'!$C$1:$C$400,'Service Duration by unit'!$A$1:$A$400,$J7,'Service Duration by unit'!$C$1:$C$400,">="&IF($H7=$M$4,N$4,N$3)))),1))*$L7/3600)*(1+$M7)} -> 0 | EX7: {=(IF($H7=$M$4,N$4*$I7,N$3*$I7)+(INDEX(_xlfn._xlws.FILTER('Service Duration by unit'!$D$1:$D$400,('Service Duration by unit'!$A$1:$A$400=$J7)*('Service Duration by unit'!$C$1:$C$400=_xlfn.MINIFS('Service Duration by unit'!$C$1:$C$400,'Service Duration by unit'!$A$1:$A$400,$J7,'Service Duration by unit'!$C$1:$C$400,">="&IF($H7=$M$4,N$4,N$3)))),1))*$L7/3600)*(1+$M7)} -> 0 | EY7: {=(IF($H7=$M$4,N$4*$I7,N$3*$I7)+(INDEX(_xlfn._xlws.FILTER('Service Duration by unit'!$D$1:$D$400,('Service Duration by unit'!$A$1:$A$400=$J7)*('Service Duration by unit'!$C$1:$C$400=_xlfn.MINIFS('Service Duration by unit'!$C$1:$C$400,'Service Duration by unit'!$A$1:$A$400,$J7,'Service Duration by unit'!$C$1:$C$400,">="&IF($H7=$M$4,N$4,N$3)))),1))*$L7/3600)*(1+$M7)} -> 0 | EZ7: {=(IF($H7=$M$4,N$4*$I7,N$3*$I7)+(INDEX(_xlfn._xlws.FILTER('Service Duration by unit'!$D$1:$D$400,('Service Duration by unit'!$A$1:$A$400=$J7)*('Service Duration by unit'!$C$1:$C$400=_xlfn.MINIFS('Service Duration by unit'!$C$1:$C$400,'Service Duration by unit'!$A$1:$A$400,$J7,'Service Duration by unit'!$C$1:$C$400,">="&IF($H7=$M$4,N$4,N$3)))),1))*$L7/3600)*(1+$M7)} -> 0 | FA7: {=(IF($H7=$M$4,N$4*$I7,N$3*$I7)+(INDEX(_xlfn._xlws.FILTER('Service Duration by unit'!$D$1:$D$400,('Service Duration by unit'!$A$1:$A$400=$J7)*('Service Duration by unit'!$C$1:$C$400=_xlfn.MINIFS('Service Duration by unit'!$C$1:$C$400,'Service Duration by unit'!$A$1:$A$400,$J7,'Service Duration by unit'!$C$1:$C$400,">="&IF($H7=$M$4,N$4,N$3)))),1))*$L7/3600)*(1+$M7)} -> 0 | FB7: {=(IF($H7=$M$4,N$4*$I7,N$3*$I7)+(INDEX(_xlfn._xlws.FILTER('Service Duration by unit'!$D$1:$D$400,('Service Duration by unit'!$A$1:$A$400=$J7)*('Service Duration by unit'!$C$1:$C$400=_xlfn.MINIFS('Service Duration by unit'!$C$1:$C$400,'Service Duration by unit'!$A$1:$A$400,$J7,'Service Duration by unit'!$C$1:$C$400,">="&IF($H7=$M$4,N$4,N$3)))),1))*$L7/3600)*(1+$M7)} -> 0 | FC7: {=(IF($H7=$M$4,N$4*$I7,N$3*$I7)+(INDEX(_xlfn._xlws.FILTER('Service Duration by unit'!$D$1:$D$400,('Service Duration by unit'!$A$1:$A$400=$J7)*('Service Duration by unit'!$C$1:$C$400=_xlfn.MINIFS('Service Duration by unit'!$C$1:$C$400,'Service Duration by unit'!$A$1:$A$400,$J7,'Service Duration by unit'!$C$1:$C$400,">="&IF($H7=$M$4,N$4,N$3)))),1))*$L7/3600)*(1+$M7)} -> 0 | FD7: {=(IF($H7=$M$4,N$4*$I7,N$3*$I7)+(INDEX(_xlfn._xlws.FILTER('Service Duration by unit'!$D$1:$D$400,('Service Duration by unit'!$A$1:$A$400=$J7)*('Service Duration by unit'!$C$1:$C$400=_xlfn.MINIFS('Service Duration by unit'!$C$1:$C$400,'Service Duration by unit'!$A$1:$A$400,$J7,'Service Duration by unit'!$C$1:$C$400,">="&IF($H7=$M$4,N$4,N$3)))),1))*$L7/3600)*(1+$M7)} -> 0 | FE7: {=(IF($H7=$M$4,N$4*$I7,N$3*$I7)+(INDEX(_xlfn._xlws.FILTER('Service Duration by unit'!$D$1:$D$400,('Service Duration by unit'!$A$1:$A$400=$J7)*('Service Duration by unit'!$C$1:$C$400=_xlfn.MINIFS('Service Duration by unit'!$C$1:$C$400,'Service Duration by unit'!$A$1:$A$400,$J7,'Service Duration by unit'!$C$1:$C$400,">="&IF($H7=$M$4,N$4,N$3)))),1))*$L7/3600)*(1+$M7)} -> 0 | FF7: {=(IF($H7=$M$4,N$4*$I7,N$3*$I7)+(INDEX(_xlfn._xlws.FILTER('Service Duration by unit'!$D$1:$D$400,('Service Duration by unit'!$A$1:$A$400=$J7)*('Service Duration by unit'!$C$1:$C$400=_xlfn.MINIFS('Service Duration by unit'!$C$1:$C$400,'Service Duration by unit'!$A$1:$A$400,$J7,'Service Duration by unit'!$C$1:$C$400,">="&IF($H7=$M$4,N$4,N$3)))),1))*$L7/3600)*(1+$M7)} -> 0
A8: "Anilin" Ramin Donkerblauw 14/13 | B8: 3 | C8: 9898 | D8: 70721 | E8: .E01 | H8: Circumference | I8: 2.84 | J8: Lijst snijden | K8: Lijst snijden | L8: 40 | M8: =('Pricelists by Sequence'!$D$2*(-1)/100) -> 0 | N8: {=(IF($H8=$M$4,N$4*$I8,N$3*$I8)+(INDEX(_xlfn._xlws.FILTER('Service Duration by unit'!$D$1:$D$400,('Service Duration by unit'!$A$1:$A$400=$J8)*('Service Duration by unit'!$C$1:$C$400=_xlfn.MINIFS('Service Duration by unit'!$C$1:$C$400,'Service Duration by unit'!$A$1:$A$400,$J8,'Service Duration by unit'!$C$1:$C$400,">="&IF($H8=$M$4,N$4,N$3)))),1))*$L8/3600)*(1+$M8)} -> 0 | O8: {=(IF($H8=$M$4,N$4*$I8,N$3*$I8)+(INDEX(_xlfn._xlws.FILTER('Service Duration by unit'!$D$1:$D$400,('Service Duration by unit'!$A$1:$A$400=$J8)*('Service Duration by unit'!$C$1:$C$400=_xlfn.MINIFS('Service Duration by unit'!$C$1:$C$400,'Service Duration by unit'!$A$1:$A$400,$J8,'Service Duration by unit'!$C$1:$C$400,">="&IF($H8=$M$4,N$4,N$3)))),1))*$L8/3600)*(1+$M8)} -> 0 | P8: {=(IF($H8=$M$4,N$4*$I8,N$3*$I8)+(INDEX(_xlfn._xlws.FILTER('Service Duration by unit'!$D$1:$D$400,('Service Duration by unit'!$A$1:$A$400=$J8)*('Service Duration by unit'!$C$1:$C$400=_xlfn.MINIFS('Service Duration by unit'!$C$1:$C$400,'Service Duration by unit'!$A$1:$A$400,$J8,'Service Duration by unit'!$C$1:$C$400,">="&IF($H8=$M$4,N$4,N$3)))),1))*$L8/3600)*(1+$M8)} -> 0 | Q8: {=(IF($H8=$M$4,N$4*$I8,N$3*$I8)+(INDEX(_xlfn._xlws.FILTER('Service Duration by unit'!$D$1:$D$400,('Service Duration by unit'!$A$1:$A$400=$J8)*('Service Duration by unit'!$C$1:$C$400=_xlfn.MINIFS('Service Duration by unit'!$C$1:$C$400,'Service Duration by unit'!$A$1:$A$400,$J8,'Service Duration by unit'!$C$1:$C$400,">="&IF($H8=$M$4,N$4,N$3)))),1))*$L8/3600)*(1+$M8)} -> 0 | R8: {=(IF($H8=$M$4,N$4*$I8,N$3*$I8)+(INDEX(_xlfn._xlws.FILTER('Service Duration by unit'!$D$1:$D$400,('Service Duration by unit'!$A$1:$A$400=$J8)*('Service Duration by unit'!$C$1:$C$400=_xlfn.MINIFS('Service Duration by unit'!$C$1:$C$400,'Service Duration by unit'!$A$1:$A$400,$J8,'Service Duration by unit'!$C$1:$C$400,">="&IF($H8=$M$4,N$4,N$3)))),1))*$L8/3600)*(1+$M8)} -> 0 | S8: {=(IF($H8=$M$4,N$4*$I8,N$3*$I8)+(INDEX(_xlfn._xlws.FILTER('Service Duration by unit'!$D$1:$D$400,('Service Duration by unit'!$A$1:$A$400=$J8)*('Service Duration by unit'!$C$1:$C$400=_xlfn.MINIFS('Service Duration by unit'!$C$1:$C$400,'Service Duration by unit'!$A$1:$A$400,$J8,'Service Duration by unit'!$C$1:$C$400,">="&IF($H8=$M$4,N$4,N$3)))),1))*$L8/3600)*(1+$M8)} -> 0 | T8: {=(IF($H8=$M$4,N$4*$I8,N$3*$I8)+(INDEX(_xlfn._xlws.FILTER('Service Duration by unit'!$D$1:$D$400,('Service Duration by unit'!$A$1:$A$400=$J8)*('Service Duration by unit'!$C$1:$C$400=_xlfn.MINIFS('Service Duration by unit'!$C$1:$C$400,'Service Duration by unit'!$A$1:$A$400,$J8,'Service Duration by unit'!$C$1:$C$400,">="&IF($H8=$M$4,N$4,N$3)))),1))*$L8/3600)*(1+$M8)} -> 0 | U8: {=(IF($H8=$M$4,N$4*$I8,N$3*$I8)+(INDEX(_xlfn._xlws.FILTER('Service Duration by unit'!$D$1:$D$400,('Service Duration by unit'!$A$1:$A$400=$J8)*('Service Duration by unit'!$C$1:$C$400=_xlfn.MINIFS('Service Duration by unit'!$C$1:$C$400,'Service Duration by unit'!$A$1:$A$400,$J8,'Service Duration by unit'!$C$1:$C$400,">="&IF($H8=$M$4,N$4,N$3)))),1))*$L8/3600)*(1+$M8)} -> 0 | V8: {=(IF($H8=$M$4,N$4*$I8,N$3*$I8)+(INDEX(_xlfn._xlws.FILTER('Service Duration by unit'!$D$1:$D$400,('Service Duration by unit'!$A$1:$A$400=$J8)*('Service Duration by unit'!$C$1:$C$400=_xlfn.MINIFS('Service Duration by unit'!$C$1:$C$400,'Service Duration by unit'!$A$1:$A$400,$J8,'Service Duration by unit'!$C$1:$C$400,">="&IF($H8=$M$4,N$4,N$3)))),1))*$L8/3600)*(1+$M8)} -> 0 | W8: {=(IF($H8=$M$4,N$4*$I8,N$3*$I8)+(INDEX(_xlfn._xlws.FILTER('Service Duration by unit'!$D$1:$D$400,('Service Duration by unit'!$A$1:$A$400=$J8)*('Service Duration by unit'!$C$1:$C$400=_xlfn.MINIFS('Service Duration by unit'!$C$1:$C$400,'Service Duration by unit'!$A$1:$A$400,$J8,'Service Duration by unit'!$C$1:$C$400,">="&IF($H8=$M$4,N$4,N$3)))),1))*$L8/3600)*(1+$M8)} -> 0 | X8: {=(IF($H8=$M$4,N$4*$I8,N$3*$I8)+(INDEX(_xlfn._xlws.FILTER('Service Duration by unit'!$D$1:$D$400,('Service Duration by unit'!$A$1:$A$400=$J8)*('Service Duration by unit'!$C$1:$C$400=_xlfn.MINIFS('Service Duration by unit'!$C$1:$C$400,'Service Duration by unit'!$A$1:$A$400,$J8,'Service Duration by unit'!$C$1:$C$400,">="&IF($H8=$M$4,N$4,N$3)))),1))*$L8/3600)*(1+$M8)} -> 0 | Y8: {=(IF($H8=$M$4,N$4*$I8,N$3*$I8)+(INDEX(_xlfn._xlws.FILTER('Service Duration by unit'!$D$1:$D$400,('Service Duration by unit'!$A$1:$A$400=$J8)*('Service Duration by unit'!$C$1:$C$400=_xlfn.MINIFS('Service Duration by unit'!$C$1:$C$400,'Service Duration by unit'!$A$1:$A$400,$J8,'Service Duration by unit'!$C$1:$C$400,">="&IF($H8=$M$4,N$4,N$3)))),1))*$L8/3600)*(1+$M8)} -> 0 | Z8: {=(IF($H8=$M$4,N$4*$I8,N$3*$I8)+(INDEX(_xlfn._xlws.FILTER('Service Duration by unit'!$D$1:$D$400,('Service Duration by unit'!$A$1:$A$400=$J8)*('Service Duration by unit'!$C$1:$C$400=_xlfn.MINIFS('Service Duration by unit'!$C$1:$C$400,'Service Duration by unit'!$A$1:$A$400,$J8,'Service Duration by unit'!$C$1:$C$400,">="&IF($H8=$M$4,N$4,N$3)))),1))*$L8/3600)*(1+$M8)} -> 0 | AA8: {=(IF($H8=$M$4,N$4*$I8,N$3*$I8)+(INDEX(_xlfn._xlws.FILTER('Service Duration by unit'!$D$1:$D$400,('Service Duration by unit'!$A$1:$A$400=$J8)*('Service Duration by unit'!$C$1:$C$400=_xlfn.MINIFS('Service Duration by unit'!$C$1:$C$400,'Service Duration by unit'!$A$1:$A$400,$J8,'Service Duration by unit'!$C$1:$C$400,">="&IF($H8=$M$4,N$4,N$3)))),1))*$L8/3600)*(1+$M8)} -> 0 | AB8: {=(IF($H8=$M$4,N$4*$I8,N$3*$I8)+(INDEX(_xlfn._xlws.FILTER('Service Duration by unit'!$D$1:$D$400,('Service Duration by unit'!$A$1:$A$400=$J8)*('Service Duration by unit'!$C$1:$C$400=_xlfn.MINIFS('Service Duration by unit'!$C$1:$C$400,'Service Duration by unit'!$A$1:$A$400,$J8,'Service Duration by unit'!$C$1:$C$400,">="&IF($H8=$M$4,N$4,N$3)))),1))*$L8/3600)*(1+$M8)} -> 0 | AC8: {=(IF($H8=$M$4,N$4*$I8,N$3*$I8)+(INDEX(_xlfn._xlws.FILTER('Service Duration by unit'!$D$1:$D$400,('Service Duration by unit'!$A$1:$A$400=$J8)*('Service Duration by unit'!$C$1:$C$400=_xlfn.MINIFS('Service Duration by unit'!$C$1:$C$400,'Service Duration by unit'!$A$1:$A$400,$J8,'Service Duration by unit'!$C$1:$C$400,">="&IF($H8=$M$4,N$4,N$3)))),1))*$L8/3600)*(1+$M8)} -> 0 | AD8: {=(IF($H8=$M$4,N$4*$I8,N$3*$I8)+(INDEX(_xlfn._xlws.FILTER('Service Duration by unit'!$D$1:$D$400,('Service Duration by unit'!$A$1:$A$400=$J8)*('Service Duration by unit'!$C$1:$C$400=_xlfn.MINIFS('Service Duration by unit'!$C$1:$C$400,'Service Duration by unit'!$A$1:$A$400,$J8,'Service Duration by unit'!$C$1:$C$400,">="&IF($H8=$M$4,N$4,N$3)))),1))*$L8/3600)*(1+$M8)} -> 0 | AE8: {=(IF($H8=$M$4,N$4*$I8,N$3*$I8)+(INDEX(_xlfn._xlws.FILTER('Service Duration by unit'!$D$1:$D$400,('Service Duration by unit'!$A$1:$A$400=$J8)*('Service Duration by unit'!$C$1:$C$400=_xlfn.MINIFS('Service Duration by unit'!$C$1:$C$400,'Service Duration by unit'!$A$1:$A$400,$J8,'Service Duration by unit'!$C$1:$C$400,">="&IF($H8=$M$4,N$4,N$3)))),1))*$L8/3600)*(1+$M8)} -> 0 | AF8: {=(IF($H8=$M$4,N$4*$I8,N$3*$I8)+(INDEX(_xlfn._xlws.FILTER('Service Duration by unit'!$D$1:$D$400,('Service Duration by unit'!$A$1:$A$400=$J8)*('Service Duration by unit'!$C$1:$C$400=_xlfn.MINIFS('Service Duration by unit'!$C$1:$C$400,'Service Duration by unit'!$A$1:$A$400,$J8,'Service Duration by unit'!$C$1:$C$400,">="&IF($H8=$M$4,N$4,N$3)))),1))*$L8/3600)*(1+$M8)} -> 0 | AG8: {=(IF($H8=$M$4,N$4*$I8,N$3*$I8)+(INDEX(_xlfn._xlws.FILTER('Service Duration by unit'!$D$1:$D$400,('Service Duration by unit'!$A$1:$A$400=$J8)*('Service Duration by unit'!$C$1:$C$400=_xlfn.MINIFS('Service Duration by unit'!$C$1:$C$400,'Service Duration by unit'!$A$1:$A$400,$J8,'Service Duration by unit'!$C$1:$C$400,">="&IF($H8=$M$4,N$4,N$3)))),1))*$L8/3600)*(1+$M8)} -> 0 | AH8: {=(IF($H8=$M$4,N$4*$I8,N$3*$I8)+(INDEX(_xlfn._xlws.FILTER('Service Duration by unit'!$D$1:$D$400,('Service Duration by unit'!$A$1:$A$400=$J8)*('Service Duration by unit'!$C$1:$C$400=_xlfn.MINIFS('Service Duration by unit'!$C$1:$C$400,'Service Duration by unit'!$A$1:$A$400,$J8,'Service Duration by unit'!$C$1:$C$400,">="&IF($H8=$M$4,N$4,N$3)))),1))*$L8/3600)*(1+$M8)} -> 0 | AI8: {=(IF($H8=$M$4,N$4*$I8,N$3*$I8)+(INDEX(_xlfn._xlws.FILTER('Service Duration by unit'!$D$1:$D$400,('Service Duration by unit'!$A$1:$A$400=$J8)*('Service Duration by unit'!$C$1:$C$400=_xlfn.MINIFS('Service Duration by unit'!$C$1:$C$400,'Service Duration by unit'!$A$1:$A$400,$J8,'Service Duration by unit'!$C$1:$C$400,">="&IF($H8=$M$4,N$4,N$3)))),1))*$L8/3600)*(1+$M8)} -> 0 | AJ8: {=(IF($H8=$M$4,N$4*$I8,N$3*$I8)+(INDEX(_xlfn._xlws.FILTER('Service Duration by unit'!$D$1:$D$400,('Service Duration by unit'!$A$1:$A$400=$J8)*('Service Duration by unit'!$C$1:$C$400=_xlfn.MINIFS('Service Duration by unit'!$C$1:$C$400,'Service Duration by unit'!$A$1:$A$400,$J8,'Service Duration by unit'!$C$1:$C$400,">="&IF($H8=$M$4,N$4,N$3)))),1))*$L8/3600)*(1+$M8)} -> 0 | AK8: {=(IF($H8=$M$4,N$4*$I8,N$3*$I8)+(INDEX(_xlfn._xlws.FILTER('Service Duration by unit'!$D$1:$D$400,('Service Duration by unit'!$A$1:$A$400=$J8)*('Service Duration by unit'!$C$1:$C$400=_xlfn.MINIFS('Service Duration by unit'!$C$1:$C$400,'Service Duration by unit'!$A$1:$A$400,$J8,'Service Duration by unit'!$C$1:$C$400,">="&IF($H8=$M$4,N$4,N$3)))),1))*$L8/3600)*(1+$M8)} -> 0 | AL8: {=(IF($H8=$M$4,N$4*$I8,N$3*$I8)+(INDEX(_xlfn._xlws.FILTER('Service Duration by unit'!$D$1:$D$400,('Service Duration by unit'!$A$1:$A$400=$J8)*('Service Duration by unit'!$C$1:$C$400=_xlfn.MINIFS('Service Duration by unit'!$C$1:$C$400,'Service Duration by unit'!$A$1:$A$400,$J8,'Service Duration by unit'!$C$1:$C$400,">="&IF($H8=$M$4,N$4,N$3)))),1))*$L8/3600)*(1+$M8)} -> 0 | AM8: {=(IF($H8=$M$4,N$4*$I8,N$3*$I8)+(INDEX(_xlfn._xlws.FILTER('Service Duration by unit'!$D$1:$D$400,('Service Duration by unit'!$A$1:$A$400=$J8)*('Service Duration by unit'!$C$1:$C$400=_xlfn.MINIFS('Service Duration by unit'!$C$1:$C$400,'Service Duration by unit'!$A$1:$A$400,$J8,'Service Duration by unit'!$C$1:$C$400,">="&IF($H8=$M$4,N$4,N$3)))),1))*$L8/3600)*(1+$M8)} -> 0 | AN8: {=(IF($H8=$M$4,N$4*$I8,N$3*$I8)+(INDEX(_xlfn._xlws.FILTER('Service Duration by unit'!$D$1:$D$400,('Service Duration by unit'!$A$1:$A$400=$J8)*('Service Duration by unit'!$C$1:$C$400=_xlfn.MINIFS('Service Duration by unit'!$C$1:$C$400,'Service Duration by unit'!$A$1:$A$400,$J8,'Service Duration by unit'!$C$1:$C$400,">="&IF($H8=$M$4,N$4,N$3)))),1))*$L8/3600)*(1+$M8)} -> 0 | AO8: {=(IF($H8=$M$4,N$4*$I8,N$3*$I8)+(INDEX(_xlfn._xlws.FILTER('Service Duration by unit'!$D$1:$D$400,('Service Duration by unit'!$A$1:$A$400=$J8)*('Service Duration by unit'!$C$1:$C$400=_xlfn.MINIFS('Service Duration by unit'!$C$1:$C$400,'Service Duration by unit'!$A$1:$A$400,$J8,'Service Duration by unit'!$C$1:$C$400,">="&IF($H8=$M$4,N$4,N$3)))),1))*$L8/3600)*(1+$M8)} -> 0 | AP8: {=(IF($H8=$M$4,N$4*$I8,N$3*$I8)+(INDEX(_xlfn._xlws.FILTER('Service Duration by unit'!$D$1:$D$400,('Service Duration by unit'!$A$1:$A$400=$J8)*('Service Duration by unit'!$C$1:$C$400=_xlfn.MINIFS('Service Duration by unit'!$C$1:$C$400,'Service Duration by unit'!$A$1:$A$400,$J8,'Service Duration by unit'!$C$1:$C$400,">="&IF($H8=$M$4,N$4,N$3)))),1))*$L8/3600)*(1+$M8)} -> 0 | AQ8: {=(IF($H8=$M$4,N$4*$I8,N$3*$I8)+(INDEX(_xlfn._xlws.FILTER('Service Duration by unit'!$D$1:$D$400,('Service Duration by unit'!$A$1:$A$400=$J8)*('Service Duration by unit'!$C$1:$C$400=_xlfn.MINIFS('Service Duration by unit'!$C$1:$C$400,'Service Duration by unit'!$A$1:$A$400,$J8,'Service Duration by unit'!$C$1:$C$400,">="&IF($H8=$M$4,N$4,N$3)))),1))*$L8/3600)*(1+$M8)} -> 0 | AR8: {=(IF($H8=$M$4,N$4*$I8,N$3*$I8)+(INDEX(_xlfn._xlws.FILTER('Service Duration by unit'!$D$1:$D$400,('Service Duration by unit'!$A$1:$A$400=$J8)*('Service Duration by unit'!$C$1:$C$400=_xlfn.MINIFS('Service Duration by unit'!$C$1:$C$400,'Service Duration by unit'!$A$1:$A$400,$J8,'Service Duration by unit'!$C$1:$C$400,">="&IF($H8=$M$4,N$4,N$3)))),1))*$L8/3600)*(1+$M8)} -> 0 | AS8: {=(IF($H8=$M$4,N$4*$I8,N$3*$I8)+(INDEX(_xlfn._xlws.FILTER('Service Duration by unit'!$D$1:$D$400,('Service Duration by unit'!$A$1:$A$400=$J8)*('Service Duration by unit'!$C$1:$C$400=_xlfn.MINIFS('Service Duration by unit'!$C$1:$C$400,'Service Duration by unit'!$A$1:$A$400,$J8,'Service Duration by unit'!$C$1:$C$400,">="&IF($H8=$M$4,N$4,N$3)))),1))*$L8/3600)*(1+$M8)} -> 0 | AT8: {=(IF($H8=$M$4,N$4*$I8,N$3*$I8)+(INDEX(_xlfn._xlws.FILTER('Service Duration by unit'!$D$1:$D$400,('Service Duration by unit'!$A$1:$A$400=$J8)*('Service Duration by unit'!$C$1:$C$400=_xlfn.MINIFS('Service Duration by unit'!$C$1:$C$400,'Service Duration by unit'!$A$1:$A$400,$J8,'Service Duration by unit'!$C$1:$C$400,">="&IF($H8=$M$4,N$4,N$3)))),1))*$L8/3600)*(1+$M8)} -> 0 | AU8: {=(IF($H8=$M$4,N$4*$I8,N$3*$I8)+(INDEX(_xlfn._xlws.FILTER('Service Duration by unit'!$D$1:$D$400,('Service Duration by unit'!$A$1:$A$400=$J8)*('Service Duration by unit'!$C$1:$C$400=_xlfn.MINIFS('Service Duration by unit'!$C$1:$C$400,'Service Duration by unit'!$A$1:$A$400,$J8,'Service Duration by unit'!$C$1:$C$400,">="&IF($H8=$M$4,N$4,N$3)))),1))*$L8/3600)*(1+$M8)} -> 0 | AV8: {=(IF($H8=$M$4,N$4*$I8,N$3*$I8)+(INDEX(_xlfn._xlws.FILTER('Service Duration by unit'!$D$1:$D$400,('Service Duration by unit'!$A$1:$A$400=$J8)*('Service Duration by unit'!$C$1:$C$400=_xlfn.MINIFS('Service Duration by unit'!$C$1:$C$400,'Service Duration by unit'!$A$1:$A$400,$J8,'Service Duration by unit'!$C$1:$C$400,">="&IF($H8=$M$4,N$4,N$3)))),1))*$L8/3600)*(1+$M8)} -> 0 | AW8: {=(IF($H8=$M$4,N$4*$I8,N$3*$I8)+(INDEX(_xlfn._xlws.FILTER('Service Duration by unit'!$D$1:$D$400,('Service Duration by unit'!$A$1:$A$400=$J8)*('Service Duration by unit'!$C$1:$C$400=_xlfn.MINIFS('Service Duration by unit'!$C$1:$C$400,'Service Duration by unit'!$A$1:$A$400,$J8,'Service Duration by unit'!$C$1:$C$400,">="&IF($H8=$M$4,N$4,N$3)))),1))*$L8/3600)*(1+$M8)} -> 0 | AX8: {=(IF($H8=$M$4,N$4*$I8,N$3*$I8)+(INDEX(_xlfn._xlws.FILTER('Service Duration by unit'!$D$1:$D$400,('Service Duration by unit'!$A$1:$A$400=$J8)*('Service Duration by unit'!$C$1:$C$400=_xlfn.MINIFS('Service Duration by unit'!$C$1:$C$400,'Service Duration by unit'!$A$1:$A$400,$J8,'Service Duration by unit'!$C$1:$C$400,">="&IF($H8=$M$4,N$4,N$3)))),1))*$L8/3600)*(1+$M8)} -> 0 | AY8: {=(IF($H8=$M$4,N$4*$I8,N$3*$I8)+(INDEX(_xlfn._xlws.FILTER('Service Duration by unit'!$D$1:$D$400,('Service Duration by unit'!$A$1:$A$400=$J8)*('Service Duration by unit'!$C$1:$C$400=_xlfn.MINIFS('Service Duration by unit'!$C$1:$C$400,'Service Duration by unit'!$A$1:$A$400,$J8,'Service Duration by unit'!$C$1:$C$400,">="&IF($H8=$M$4,N$4,N$3)))),1))*$L8/3600)*(1+$M8)} -> 0 | AZ8: {=(IF($H8=$M$4,N$4*$I8,N$3*$I8)+(INDEX(_xlfn._xlws.FILTER('Service Duration by unit'!$D$1:$D$400,('Service Duration by unit'!$A$1:$A$400=$J8)*('Service Duration by unit'!$C$1:$C$400=_xlfn.MINIFS('Service Duration by unit'!$C$1:$C$400,'Service Duration by unit'!$A$1:$A$400,$J8,'Service Duration by unit'!$C$1:$C$400,">="&IF($H8=$M$4,N$4,N$3)))),1))*$L8/3600)*(1+$M8)} -> 0 | BA8: {=(IF($H8=$M$4,N$4*$I8,N$3*$I8)+(INDEX(_xlfn._xlws.FILTER('Service Duration by unit'!$D$1:$D$400,('Service Duration by unit'!$A$1:$A$400=$J8)*('Service Duration by unit'!$C$1:$C$400=_xlfn.MINIFS('Service Duration by unit'!$C$1:$C$400,'Service Duration by unit'!$A$1:$A$400,$J8,'Service Duration by unit'!$C$1:$C$400,">="&IF($H8=$M$4,N$4,N$3)))),1))*$L8/3600)*(1+$M8)} -> 0 | BB8: {=(IF($H8=$M$4,N$4*$I8,N$3*$I8)+(INDEX(_xlfn._xlws.FILTER('Service Duration by unit'!$D$1:$D$400,('Service Duration by unit'!$A$1:$A$400=$J8)*('Service Duration by unit'!$C$1:$C$400=_xlfn.MINIFS('Service Duration by unit'!$C$1:$C$400,'Service Duration by unit'!$A$1:$A$400,$J8,'Service Duration by unit'!$C$1:$C$400,">="&IF($H8=$M$4,N$4,N$3)))),1))*$L8/3600)*(1+$M8)} -> 0 | BC8: {=(IF($H8=$M$4,N$4*$I8,N$3*$I8)+(INDEX(_xlfn._xlws.FILTER('Service Duration by unit'!$D$1:$D$400,('Service Duration by unit'!$A$1:$A$400=$J8)*('Service Duration by unit'!$C$1:$C$400=_xlfn.MINIFS('Service Duration by unit'!$C$1:$C$400,'Service Duration by unit'!$A$1:$A$400,$J8,'Service Duration by unit'!$C$1:$C$400,">="&IF($H8=$M$4,N$4,N$3)))),1))*$L8/3600)*(1+$M8)} -> 0 | BD8: {=(IF($H8=$M$4,N$4*$I8,N$3*$I8)+(INDEX(_xlfn._xlws.FILTER('Service Duration by unit'!$D$1:$D$400,('Service Duration by unit'!$A$1:$A$400=$J8)*('Service Duration by unit'!$C$1:$C$400=_xlfn.MINIFS('Service Duration by unit'!$C$1:$C$400,'Service Duration by unit'!$A$1:$A$400,$J8,'Service Duration by unit'!$C$1:$C$400,">="&IF($H8=$M$4,N$4,N$3)))),1))*$L8/3600)*(1+$M8)} -> 0 | BE8: {=(IF($H8=$M$4,N$4*$I8,N$3*$I8)+(INDEX(_xlfn._xlws.FILTER('Service Duration by unit'!$D$1:$D$400,('Service Duration by unit'!$A$1:$A$400=$J8)*('Service Duration by unit'!$C$1:$C$400=_xlfn.MINIFS('Service Duration by unit'!$C$1:$C$400,'Service Duration by unit'!$A$1:$A$400,$J8,'Service Duration by unit'!$C$1:$C$400,">="&IF($H8=$M$4,N$4,N$3)))),1))*$L8/3600)*(1+$M8)} -> 0 | BF8: {=(IF($H8=$M$4,N$4*$I8,N$3*$I8)+(INDEX(_xlfn._xlws.FILTER('Service Duration by unit'!$D$1:$D$400,('Service Duration by unit'!$A$1:$A$400=$J8)*('Service Duration by unit'!$C$1:$C$400=_xlfn.MINIFS('Service Duration by unit'!$C$1:$C$400,'Service Duration by unit'!$A$1:$A$400,$J8,'Service Duration by unit'!$C$1:$C$400,">="&IF($H8=$M$4,N$4,N$3)))),1))*$L8/3600)*(1+$M8)} -> 0 | BG8: {=(IF($H8=$M$4,N$4*$I8,N$3*$I8)+(INDEX(_xlfn._xlws.FILTER('Service Duration by unit'!$D$1:$D$400,('Service Duration by unit'!$A$1:$A$400=$J8)*('Service Duration by unit'!$C$1:$C$400=_xlfn.MINIFS('Service Duration by unit'!$C$1:$C$400,'Service Duration by unit'!$A$1:$A$400,$J8,'Service Duration by unit'!$C$1:$C$400,">="&IF($H8=$M$4,N$4,N$3)))),1))*$L8/3600)*(1+$M8)} -> 0 | BH8: {=(IF($H8=$M$4,N$4*$I8,N$3*$I8)+(INDEX(_xlfn._xlws.FILTER('Service Duration by unit'!$D$1:$D$400,('Service Duration by unit'!$A$1:$A$400=$J8)*('Service Duration by unit'!$C$1:$C$400=_xlfn.MINIFS('Service Duration by unit'!$C$1:$C$400,'Service Duration by unit'!$A$1:$A$400,$J8,'Service Duration by unit'!$C$1:$C$400,">="&IF($H8=$M$4,N$4,N$3)))),1))*$L8/3600)*(1+$M8)} -> 0 | BI8: {=(IF($H8=$M$4,N$4*$I8,N$3*$I8)+(INDEX(_xlfn._xlws.FILTER('Service Duration by unit'!$D$1:$D$400,('Service Duration by unit'!$A$1:$A$400=$J8)*('Service Duration by unit'!$C$1:$C$400=_xlfn.MINIFS('Service Duration by unit'!$C$1:$C$400,'Service Duration by unit'!$A$1:$A$400,$J8,'Service Duration by unit'!$C$1:$C$400,">="&IF($H8=$M$4,N$4,N$3)))),1))*$L8/3600)*(1+$M8)} -> 0 | BJ8: {=(IF($H8=$M$4,N$4*$I8,N$3*$I8)+(INDEX(_xlfn._xlws.FILTER('Service Duration by unit'!$D$1:$D$400,('Service Duration by unit'!$A$1:$A$400=$J8)*('Service Duration by unit'!$C$1:$C$400=_xlfn.MINIFS('Service Duration by unit'!$C$1:$C$400,'Service Duration by unit'!$A$1:$A$400,$J8,'Service Duration by unit'!$C$1:$C$400,">="&IF($H8=$M$4,N$4,N$3)))),1))*$L8/3600)*(1+$M8)} -> 0 | BK8: {=(IF($H8=$M$4,N$4*$I8,N$3*$I8)+(INDEX(_xlfn._xlws.FILTER('Service Duration by unit'!$D$1:$D$400,('Service Duration by unit'!$A$1:$A$400=$J8)*('Service Duration by unit'!$C$1:$C$400=_xlfn.MINIFS('Service Duration by unit'!$C$1:$C$400,'Service Duration by unit'!$A$1:$A$400,$J8,'Service Duration by unit'!$C$1:$C$400,">="&IF($H8=$M$4,N$4,N$3)))),1))*$L8/3600)*(1+$M8)} -> 0 | BL8: {=(IF($H8=$M$4,N$4*$I8,N$3*$I8)+(INDEX(_xlfn._xlws.FILTER('Service Duration by unit'!$D$1:$D$400,('Service Duration by unit'!$A$1:$A$400=$J8)*('Service Duration by unit'!$C$1:$C$400=_xlfn.MINIFS('Service Duration by unit'!$C$1:$C$400,'Service Duration by unit'!$A$1:$A$400,$J8,'Service Duration by unit'!$C$1:$C$400,">="&IF($H8=$M$4,N$4,N$3)))),1))*$L8/3600)*(1+$M8)} -> 0 | BM8: {=(IF($H8=$M$4,N$4*$I8,N$3*$I8)+(INDEX(_xlfn._xlws.FILTER('Service Duration by unit'!$D$1:$D$400,('Service Duration by unit'!$A$1:$A$400=$J8)*('Service Duration by unit'!$C$1:$C$400=_xlfn.MINIFS('Service Duration by unit'!$C$1:$C$400,'Service Duration by unit'!$A$1:$A$400,$J8,'Service Duration by unit'!$C$1:$C$400,">="&IF($H8=$M$4,N$4,N$3)))),1))*$L8/3600)*(1+$M8)} -> 0 | BN8: {=(IF($H8=$M$4,N$4*$I8,N$3*$I8)+(INDEX(_xlfn._xlws.FILTER('Service Duration by unit'!$D$1:$D$400,('Service Duration by unit'!$A$1:$A$400=$J8)*('Service Duration by unit'!$C$1:$C$400=_xlfn.MINIFS('Service Duration by unit'!$C$1:$C$400,'Service Duration by unit'!$A$1:$A$400,$J8,'Service Duration by unit'!$C$1:$C$400,">="&IF($H8=$M$4,N$4,N$3)))),1))*$L8/3600)*(1+$M8)} -> 0 | BO8: {=(IF($H8=$M$4,N$4*$I8,N$3*$I8)+(INDEX(_xlfn._xlws.FILTER('Service Duration by unit'!$D$1:$D$400,('Service Duration by unit'!$A$1:$A$400=$J8)*('Service Duration by unit'!$C$1:$C$400=_xlfn.MINIFS('Service Duration by unit'!$C$1:$C$400,'Service Duration by unit'!$A$1:$A$400,$J8,'Service Duration by unit'!$C$1:$C$400,">="&IF($H8=$M$4,N$4,N$3)))),1))*$L8/3600)*(1+$M8)} -> 0 | BP8: {=(IF($H8=$M$4,N$4*$I8,N$3*$I8)+(INDEX(_xlfn._xlws.FILTER('Service Duration by unit'!$D$1:$D$400,('Service Duration by unit'!$A$1:$A$400=$J8)*('Service Duration by unit'!$C$1:$C$400=_xlfn.MINIFS('Service Duration by unit'!$C$1:$C$400,'Service Duration by unit'!$A$1:$A$400,$J8,'Service Duration by unit'!$C$1:$C$400,">="&IF($H8=$M$4,N$4,N$3)))),1))*$L8/3600)*(1+$M8)} -> 0 | BQ8: {=(IF($H8=$M$4,N$4*$I8,N$3*$I8)+(INDEX(_xlfn._xlws.FILTER('Service Duration by unit'!$D$1:$D$400,('Service Duration by unit'!$A$1:$A$400=$J8)*('Service Duration by unit'!$C$1:$C$400=_xlfn.MINIFS('Service Duration by unit'!$C$1:$C$400,'Service Duration by unit'!$A$1:$A$400,$J8,'Service Duration by unit'!$C$1:$C$400,">="&IF($H8=$M$4,N$4,N$3)))),1))*$L8/3600)*(1+$M8)} -> 0 | BR8: {=(IF($H8=$M$4,N$4*$I8,N$3*$I8)+(INDEX(_xlfn._xlws.FILTER('Service Duration by unit'!$D$1:$D$400,('Service Duration by unit'!$A$1:$A$400=$J8)*('Service Duration by unit'!$C$1:$C$400=_xlfn.MINIFS('Service Duration by unit'!$C$1:$C$400,'Service Duration by unit'!$A$1:$A$400,$J8,'Service Duration by unit'!$C$1:$C$400,">="&IF($H8=$M$4,N$4,N$3)))),1))*$L8/3600)*(1+$M8)} -> 0 | BS8: {=(IF($H8=$M$4,N$4*$I8,N$3*$I8)+(INDEX(_xlfn._xlws.FILTER('Service Duration by unit'!$D$1:$D$400,('Service Duration by unit'!$A$1:$A$400=$J8)*('Service Duration by unit'!$C$1:$C$400=_xlfn.MINIFS('Service Duration by unit'!$C$1:$C$400,'Service Duration by unit'!$A$1:$A$400,$J8,'Service Duration by unit'!$C$1:$C$400,">="&IF($H8=$M$4,N$4,N$3)))),1))*$L8/3600)*(1+$M8)} -> 0 | BT8: {=(IF($H8=$M$4,N$4*$I8,N$3*$I8)+(INDEX(_xlfn._xlws.FILTER('Service Duration by unit'!$D$1:$D$400,('Service Duration by unit'!$A$1:$A$400=$J8)*('Service Duration by unit'!$C$1:$C$400=_xlfn.MINIFS('Service Duration by unit'!$C$1:$C$400,'Service Duration by unit'!$A$1:$A$400,$J8,'Service Duration by unit'!$C$1:$C$400,">="&IF($H8=$M$4,N$4,N$3)))),1))*$L8/3600)*(1+$M8)} -> 0 | BU8: {=(IF($H8=$M$4,N$4*$I8,N$3*$I8)+(INDEX(_xlfn._xlws.FILTER('Service Duration by unit'!$D$1:$D$400,('Service Duration by unit'!$A$1:$A$400=$J8)*('Service Duration by unit'!$C$1:$C$400=_xlfn.MINIFS('Service Duration by unit'!$C$1:$C$400,'Service Duration by unit'!$A$1:$A$400,$J8,'Service Duration by unit'!$C$1:$C$400,">="&IF($H8=$M$4,N$4,N$3)))),1))*$L8/3600)*(1+$M8)} -> 0 | BV8: {=(IF($H8=$M$4,N$4*$I8,N$3*$I8)+(INDEX(_xlfn._xlws.FILTER('Service Duration by unit'!$D$1:$D$400,('Service Duration by unit'!$A$1:$A$400=$J8)*('Service Duration by unit'!$C$1:$C$400=_xlfn.MINIFS('Service Duration by unit'!$C$1:$C$400,'Service Duration by unit'!$A$1:$A$400,$J8,'Service Duration by unit'!$C$1:$C$400,">="&IF($H8=$M$4,N$4,N$3)))),1))*$L8/3600)*(1+$M8)} -> 0 | BW8: {=(IF($H8=$M$4,N$4*$I8,N$3*$I8)+(INDEX(_xlfn._xlws.FILTER('Service Duration by unit'!$D$1:$D$400,('Service Duration by unit'!$A$1:$A$400=$J8)*('Service Duration by unit'!$C$1:$C$400=_xlfn.MINIFS('Service Duration by unit'!$C$1:$C$400,'Service Duration by unit'!$A$1:$A$400,$J8,'Service Duration by unit'!$C$1:$C$400,">="&IF($H8=$M$4,N$4,N$3)))),1))*$L8/3600)*(1+$M8)} -> 0 | BX8: {=(IF($H8=$M$4,N$4*$I8,N$3*$I8)+(INDEX(_xlfn._xlws.FILTER('Service Duration by unit'!$D$1:$D$400,('Service Duration by unit'!$A$1:$A$400=$J8)*('Service Duration by unit'!$C$1:$C$400=_xlfn.MINIFS('Service Duration by unit'!$C$1:$C$400,'Service Duration by unit'!$A$1:$A$400,$J8,'Service Duration by unit'!$C$1:$C$400,">="&IF($H8=$M$4,N$4,N$3)))),1))*$L8/3600)*(1+$M8)} -> 0 | BY8: {=(IF($H8=$M$4,N$4*$I8,N$3*$I8)+(INDEX(_xlfn._xlws.FILTER('Service Duration by unit'!$D$1:$D$400,('Service Duration by unit'!$A$1:$A$400=$J8)*('Service Duration by unit'!$C$1:$C$400=_xlfn.MINIFS('Service Duration by unit'!$C$1:$C$400,'Service Duration by unit'!$A$1:$A$400,$J8,'Service Duration by unit'!$C$1:$C$400,">="&IF($H8=$M$4,N$4,N$3)))),1))*$L8/3600)*(1+$M8)} -> 0 | BZ8: {=(IF($H8=$M$4,N$4*$I8,N$3*$I8)+(INDEX(_xlfn._xlws.FILTER('Service Duration by unit'!$D$1:$D$400,('Service Duration by unit'!$A$1:$A$400=$J8)*('Service Duration by unit'!$C$1:$C$400=_xlfn.MINIFS('Service Duration by unit'!$C$1:$C$400,'Service Duration by unit'!$A$1:$A$400,$J8,'Service Duration by unit'!$C$1:$C$400,">="&IF($H8=$M$4,N$4,N$3)))),1))*$L8/3600)*(1+$M8)} -> 0 | CA8: {=(IF($H8=$M$4,N$4*$I8,N$3*$I8)+(INDEX(_xlfn._xlws.FILTER('Service Duration by unit'!$D$1:$D$400,('Service Duration by unit'!$A$1:$A$400=$J8)*('Service Duration by unit'!$C$1:$C$400=_xlfn.MINIFS('Service Duration by unit'!$C$1:$C$400,'Service Duration by unit'!$A$1:$A$400,$J8,'Service Duration by unit'!$C$1:$C$400,">="&IF($H8=$M$4,N$4,N$3)))),1))*$L8/3600)*(1+$M8)} -> 0 | CB8: {=(IF($H8=$M$4,N$4*$I8,N$3*$I8)+(INDEX(_xlfn._xlws.FILTER('Service Duration by unit'!$D$1:$D$400,('Service Duration by unit'!$A$1:$A$400=$J8)*('Service Duration by unit'!$C$1:$C$400=_xlfn.MINIFS('Service Duration by unit'!$C$1:$C$400,'Service Duration by unit'!$A$1:$A$400,$J8,'Service Duration by unit'!$C$1:$C$400,">="&IF($H8=$M$4,N$4,N$3)))),1))*$L8/3600)*(1+$M8)} -> 0 | CC8: {=(IF($H8=$M$4,N$4*$I8,N$3*$I8)+(INDEX(_xlfn._xlws.FILTER('Service Duration by unit'!$D$1:$D$400,('Service Duration by unit'!$A$1:$A$400=$J8)*('Service Duration by unit'!$C$1:$C$400=_xlfn.MINIFS('Service Duration by unit'!$C$1:$C$400,'Service Duration by unit'!$A$1:$A$400,$J8,'Service Duration by unit'!$C$1:$C$400,">="&IF($H8=$M$4,N$4,N$3)))),1))*$L8/3600)*(1+$M8)} -> 0 | CD8: {=(IF($H8=$M$4,N$4*$I8,N$3*$I8)+(INDEX(_xlfn._xlws.FILTER('Service Duration by unit'!$D$1:$D$400,('Service Duration by unit'!$A$1:$A$400=$J8)*('Service Duration by unit'!$C$1:$C$400=_xlfn.MINIFS('Service Duration by unit'!$C$1:$C$400,'Service Duration by unit'!$A$1:$A$400,$J8,'Service Duration by unit'!$C$1:$C$400,">="&IF($H8=$M$4,N$4,N$3)))),1))*$L8/3600)*(1+$M8)} -> 0 | CE8: {=(IF($H8=$M$4,N$4*$I8,N$3*$I8)+(INDEX(_xlfn._xlws.FILTER('Service Duration by unit'!$D$1:$D$400,('Service Duration by unit'!$A$1:$A$400=$J8)*('Service Duration by unit'!$C$1:$C$400=_xlfn.MINIFS('Service Duration by unit'!$C$1:$C$400,'Service Duration by unit'!$A$1:$A$400,$J8,'Service Duration by unit'!$C$1:$C$400,">="&IF($H8=$M$4,N$4,N$3)))),1))*$L8/3600)*(1+$M8)} -> 0 | CF8: {=(IF($H8=$M$4,N$4*$I8,N$3*$I8)+(INDEX(_xlfn._xlws.FILTER('Service Duration by unit'!$D$1:$D$400,('Service Duration by unit'!$A$1:$A$400=$J8)*('Service Duration by unit'!$C$1:$C$400=_xlfn.MINIFS('Service Duration by unit'!$C$1:$C$400,'Service Duration by unit'!$A$1:$A$400,$J8,'Service Duration by unit'!$C$1:$C$400,">="&IF($H8=$M$4,N$4,N$3)))),1))*$L8/3600)*(1+$M8)} -> 0 | CG8: {=(IF($H8=$M$4,N$4*$I8,N$3*$I8)+(INDEX(_xlfn._xlws.FILTER('Service Duration by unit'!$D$1:$D$400,('Service Duration by unit'!$A$1:$A$400=$J8)*('Service Duration by unit'!$C$1:$C$400=_xlfn.MINIFS('Service Duration by unit'!$C$1:$C$400,'Service Duration by unit'!$A$1:$A$400,$J8,'Service Duration by unit'!$C$1:$C$400,">="&IF($H8=$M$4,N$4,N$3)))),1))*$L8/3600)*(1+$M8)} -> 0 | CH8: {=(IF($H8=$M$4,N$4*$I8,N$3*$I8)+(INDEX(_xlfn._xlws.FILTER('Service Duration by unit'!$D$1:$D$400,('Service Duration by unit'!$A$1:$A$400=$J8)*('Service Duration by unit'!$C$1:$C$400=_xlfn.MINIFS('Service Duration by unit'!$C$1:$C$400,'Service Duration by unit'!$A$1:$A$400,$J8,'Service Duration by unit'!$C$1:$C$400,">="&IF($H8=$M$4,N$4,N$3)))),1))*$L8/3600)*(1+$M8)} -> 0 | CI8: {=(IF($H8=$M$4,N$4*$I8,N$3*$I8)+(INDEX(_xlfn._xlws.FILTER('Service Duration by unit'!$D$1:$D$400,('Service Duration by unit'!$A$1:$A$400=$J8)*('Service Duration by unit'!$C$1:$C$400=_xlfn.MINIFS('Service Duration by unit'!$C$1:$C$400,'Service Duration by unit'!$A$1:$A$400,$J8,'Service Duration by unit'!$C$1:$C$400,">="&IF($H8=$M$4,N$4,N$3)))),1))*$L8/3600)*(1+$M8)} -> 0 | CJ8: {=(IF($H8=$M$4,N$4*$I8,N$3*$I8)+(INDEX(_xlfn._xlws.FILTER('Service Duration by unit'!$D$1:$D$400,('Service Duration by unit'!$A$1:$A$400=$J8)*('Service Duration by unit'!$C$1:$C$400=_xlfn.MINIFS('Service Duration by unit'!$C$1:$C$400,'Service Duration by unit'!$A$1:$A$400,$J8,'Service Duration by unit'!$C$1:$C$400,">="&IF($H8=$M$4,N$4,N$3)))),1))*$L8/3600)*(1+$M8)} -> 0 | CK8: {=(IF($H8=$M$4,N$4*$I8,N$3*$I8)+(INDEX(_xlfn._xlws.FILTER('Service Duration by unit'!$D$1:$D$400,('Service Duration by unit'!$A$1:$A$400=$J8)*('Service Duration by unit'!$C$1:$C$400=_xlfn.MINIFS('Service Duration by unit'!$C$1:$C$400,'Service Duration by unit'!$A$1:$A$400,$J8,'Service Duration by unit'!$C$1:$C$400,">="&IF($H8=$M$4,N$4,N$3)))),1))*$L8/3600)*(1+$M8)} -> 0 | CL8: {=(IF($H8=$M$4,N$4*$I8,N$3*$I8)+(INDEX(_xlfn._xlws.FILTER('Service Duration by unit'!$D$1:$D$400,('Service Duration by unit'!$A$1:$A$400=$J8)*('Service Duration by unit'!$C$1:$C$400=_xlfn.MINIFS('Service Duration by unit'!$C$1:$C$400,'Service Duration by unit'!$A$1:$A$400,$J8,'Service Duration by unit'!$C$1:$C$400,">="&IF($H8=$M$4,N$4,N$3)))),1))*$L8/3600)*(1+$M8)} -> 0 | CM8: {=(IF($H8=$M$4,N$4*$I8,N$3*$I8)+(INDEX(_xlfn._xlws.FILTER('Service Duration by unit'!$D$1:$D$400,('Service Duration by unit'!$A$1:$A$400=$J8)*('Service Duration by unit'!$C$1:$C$400=_xlfn.MINIFS('Service Duration by unit'!$C$1:$C$400,'Service Duration by unit'!$A$1:$A$400,$J8,'Service Duration by unit'!$C$1:$C$400,">="&IF($H8=$M$4,N$4,N$3)))),1))*$L8/3600)*(1+$M8)} -> 0 | CN8: {=(IF($H8=$M$4,N$4*$I8,N$3*$I8)+(INDEX(_xlfn._xlws.FILTER('Service Duration by unit'!$D$1:$D$400,('Service Duration by unit'!$A$1:$A$400=$J8)*('Service Duration by unit'!$C$1:$C$400=_xlfn.MINIFS('Service Duration by unit'!$C$1:$C$400,'Service Duration by unit'!$A$1:$A$400,$J8,'Service Duration by unit'!$C$1:$C$400,">="&IF($H8=$M$4,N$4,N$3)))),1))*$L8/3600)*(1+$M8)} -> 0 | CO8: {=(IF($H8=$M$4,N$4*$I8,N$3*$I8)+(INDEX(_xlfn._xlws.FILTER('Service Duration by unit'!$D$1:$D$400,('Service Duration by unit'!$A$1:$A$400=$J8)*('Service Duration by unit'!$C$1:$C$400=_xlfn.MINIFS('Service Duration by unit'!$C$1:$C$400,'Service Duration by unit'!$A$1:$A$400,$J8,'Service Duration by unit'!$C$1:$C$400,">="&IF($H8=$M$4,N$4,N$3)))),1))*$L8/3600)*(1+$M8)} -> 0 | CP8: {=(IF($H8=$M$4,N$4*$I8,N$3*$I8)+(INDEX(_xlfn._xlws.FILTER('Service Duration by unit'!$D$1:$D$400,('Service Duration by unit'!$A$1:$A$400=$J8)*('Service Duration by unit'!$C$1:$C$400=_xlfn.MINIFS('Service Duration by unit'!$C$1:$C$400,'Service Duration by unit'!$A$1:$A$400,$J8,'Service Duration by unit'!$C$1:$C$400,">="&IF($H8=$M$4,N$4,N$3)))),1))*$L8/3600)*(1+$M8)} -> 0 | CQ8: {=(IF($H8=$M$4,N$4*$I8,N$3*$I8)+(INDEX(_xlfn._xlws.FILTER('Service Duration by unit'!$D$1:$D$400,('Service Duration by unit'!$A$1:$A$400=$J8)*('Service Duration by unit'!$C$1:$C$400=_xlfn.MINIFS('Service Duration by unit'!$C$1:$C$400,'Service Duration by unit'!$A$1:$A$400,$J8,'Service Duration by unit'!$C$1:$C$400,">="&IF($H8=$M$4,N$4,N$3)))),1))*$L8/3600)*(1+$M8)} -> 0 | CR8: {=(IF($H8=$M$4,N$4*$I8,N$3*$I8)+(INDEX(_xlfn._xlws.FILTER('Service Duration by unit'!$D$1:$D$400,('Service Duration by unit'!$A$1:$A$400=$J8)*('Service Duration by unit'!$C$1:$C$400=_xlfn.MINIFS('Service Duration by unit'!$C$1:$C$400,'Service Duration by unit'!$A$1:$A$400,$J8,'Service Duration by unit'!$C$1:$C$400,">="&IF($H8=$M$4,N$4,N$3)))),1))*$L8/3600)*(1+$M8)} -> 0 | CS8: {=(IF($H8=$M$4,N$4*$I8,N$3*$I8)+(INDEX(_xlfn._xlws.FILTER('Service Duration by unit'!$D$1:$D$400,('Service Duration by unit'!$A$1:$A$400=$J8)*('Service Duration by unit'!$C$1:$C$400=_xlfn.MINIFS('Service Duration by unit'!$C$1:$C$400,'Service Duration by unit'!$A$1:$A$400,$J8,'Service Duration by unit'!$C$1:$C$400,">="&IF($H8=$M$4,N$4,N$3)))),1))*$L8/3600)*(1+$M8)} -> 0 | CT8: {=(IF($H8=$M$4,N$4*$I8,N$3*$I8)+(INDEX(_xlfn._xlws.FILTER('Service Duration by unit'!$D$1:$D$400,('Service Duration by unit'!$A$1:$A$400=$J8)*('Service Duration by unit'!$C$1:$C$400=_xlfn.MINIFS('Service Duration by unit'!$C$1:$C$400,'Service Duration by unit'!$A$1:$A$400,$J8,'Service Duration by unit'!$C$1:$C$400,">="&IF($H8=$M$4,N$4,N$3)))),1))*$L8/3600)*(1+$M8)} -> 0 | CU8: {=(IF($H8=$M$4,N$4*$I8,N$3*$I8)+(INDEX(_xlfn._xlws.FILTER('Service Duration by unit'!$D$1:$D$400,('Service Duration by unit'!$A$1:$A$400=$J8)*('Service Duration by unit'!$C$1:$C$400=_xlfn.MINIFS('Service Duration by unit'!$C$1:$C$400,'Service Duration by unit'!$A$1:$A$400,$J8,'Service Duration by unit'!$C$1:$C$400,">="&IF($H8=$M$4,N$4,N$3)))),1))*$L8/3600)*(1+$M8)} -> 0 | CV8: {=(IF($H8=$M$4,N$4*$I8,N$3*$I8)+(INDEX(_xlfn._xlws.FILTER('Service Duration by unit'!$D$1:$D$400,('Service Duration by unit'!$A$1:$A$400=$J8)*('Service Duration by unit'!$C$1:$C$400=_xlfn.MINIFS('Service Duration by unit'!$C$1:$C$400,'Service Duration by unit'!$A$1:$A$400,$J8,'Service Duration by unit'!$C$1:$C$400,">="&IF($H8=$M$4,N$4,N$3)))),1))*$L8/3600)*(1+$M8)} -> 0 | CW8: {=(IF($H8=$M$4,N$4*$I8,N$3*$I8)+(INDEX(_xlfn._xlws.FILTER('Service Duration by unit'!$D$1:$D$400,('Service Duration by unit'!$A$1:$A$400=$J8)*('Service Duration by unit'!$C$1:$C$400=_xlfn.MINIFS('Service Duration by unit'!$C$1:$C$400,'Service Duration by unit'!$A$1:$A$400,$J8,'Service Duration by unit'!$C$1:$C$400,">="&IF($H8=$M$4,N$4,N$3)))),1))*$L8/3600)*(1+$M8)} -> 0 | CX8: {=(IF($H8=$M$4,N$4*$I8,N$3*$I8)+(INDEX(_xlfn._xlws.FILTER('Service Duration by unit'!$D$1:$D$400,('Service Duration by unit'!$A$1:$A$400=$J8)*('Service Duration by unit'!$C$1:$C$400=_xlfn.MINIFS('Service Duration by unit'!$C$1:$C$400,'Service Duration by unit'!$A$1:$A$400,$J8,'Service Duration by unit'!$C$1:$C$400,">="&IF($H8=$M$4,N$4,N$3)))),1))*$L8/3600)*(1+$M8)} -> 0 | CY8: {=(IF($H8=$M$4,N$4*$I8,N$3*$I8)+(INDEX(_xlfn._xlws.FILTER('Service Duration by unit'!$D$1:$D$400,('Service Duration by unit'!$A$1:$A$400=$J8)*('Service Duration by unit'!$C$1:$C$400=_xlfn.MINIFS('Service Duration by unit'!$C$1:$C$400,'Service Duration by unit'!$A$1:$A$400,$J8,'Service Duration by unit'!$C$1:$C$400,">="&IF($H8=$M$4,N$4,N$3)))),1))*$L8/3600)*(1+$M8)} -> 0 | CZ8: {=(IF($H8=$M$4,N$4*$I8,N$3*$I8)+(INDEX(_xlfn._xlws.FILTER('Service Duration by unit'!$D$1:$D$400,('Service Duration by unit'!$A$1:$A$400=$J8)*('Service Duration by unit'!$C$1:$C$400=_xlfn.MINIFS('Service Duration by unit'!$C$1:$C$400,'Service Duration by unit'!$A$1:$A$400,$J8,'Service Duration by unit'!$C$1:$C$400,">="&IF($H8=$M$4,N$4,N$3)))),1))*$L8/3600)*(1+$M8)} -> 0 | DA8: {=(IF($H8=$M$4,N$4*$I8,N$3*$I8)+(INDEX(_xlfn._xlws.FILTER('Service Duration by unit'!$D$1:$D$400,('Service Duration by unit'!$A$1:$A$400=$J8)*('Service Duration by unit'!$C$1:$C$400=_xlfn.MINIFS('Service Duration by unit'!$C$1:$C$400,'Service Duration by unit'!$A$1:$A$400,$J8,'Service Duration by unit'!$C$1:$C$400,">="&IF($H8=$M$4,N$4,N$3)))),1))*$L8/3600)*(1+$M8)} -> 0 | DB8: {=(IF($H8=$M$4,N$4*$I8,N$3*$I8)+(INDEX(_xlfn._xlws.FILTER('Service Duration by unit'!$D$1:$D$400,('Service Duration by unit'!$A$1:$A$400=$J8)*('Service Duration by unit'!$C$1:$C$400=_xlfn.MINIFS('Service Duration by unit'!$C$1:$C$400,'Service Duration by unit'!$A$1:$A$400,$J8,'Service Duration by unit'!$C$1:$C$400,">="&IF($H8=$M$4,N$4,N$3)))),1))*$L8/3600)*(1+$M8)} -> 0 | DC8: {=(IF($H8=$M$4,N$4*$I8,N$3*$I8)+(INDEX(_xlfn._xlws.FILTER('Service Duration by unit'!$D$1:$D$400,('Service Duration by unit'!$A$1:$A$400=$J8)*('Service Duration by unit'!$C$1:$C$400=_xlfn.MINIFS('Service Duration by unit'!$C$1:$C$400,'Service Duration by unit'!$A$1:$A$400,$J8,'Service Duration by unit'!$C$1:$C$400,">="&IF($H8=$M$4,N$4,N$3)))),1))*$L8/3600)*(1+$M8)} -> 0 | DD8: {=(IF($H8=$M$4,N$4*$I8,N$3*$I8)+(INDEX(_xlfn._xlws.FILTER('Service Duration by unit'!$D$1:$D$400,('Service Duration by unit'!$A$1:$A$400=$J8)*('Service Duration by unit'!$C$1:$C$400=_xlfn.MINIFS('Service Duration by unit'!$C$1:$C$400,'Service Duration by unit'!$A$1:$A$400,$J8,'Service Duration by unit'!$C$1:$C$400,">="&IF($H8=$M$4,N$4,N$3)))),1))*$L8/3600)*(1+$M8)} -> 0 | DE8: {=(IF($H8=$M$4,N$4*$I8,N$3*$I8)+(INDEX(_xlfn._xlws.FILTER('Service Duration by unit'!$D$1:$D$400,('Service Duration by unit'!$A$1:$A$400=$J8)*('Service Duration by unit'!$C$1:$C$400=_xlfn.MINIFS('Service Duration by unit'!$C$1:$C$400,'Service Duration by unit'!$A$1:$A$400,$J8,'Service Duration by unit'!$C$1:$C$400,">="&IF($H8=$M$4,N$4,N$3)))),1))*$L8/3600)*(1+$M8)} -> 0 | DF8: {=(IF($H8=$M$4,N$4*$I8,N$3*$I8)+(INDEX(_xlfn._xlws.FILTER('Service Duration by unit'!$D$1:$D$400,('Service Duration by unit'!$A$1:$A$400=$J8)*('Service Duration by unit'!$C$1:$C$400=_xlfn.MINIFS('Service Duration by unit'!$C$1:$C$400,'Service Duration by unit'!$A$1:$A$400,$J8,'Service Duration by unit'!$C$1:$C$400,">="&IF($H8=$M$4,N$4,N$3)))),1))*$L8/3600)*(1+$M8)} -> 0 | DG8: {=(IF($H8=$M$4,N$4*$I8,N$3*$I8)+(INDEX(_xlfn._xlws.FILTER('Service Duration by unit'!$D$1:$D$400,('Service Duration by unit'!$A$1:$A$400=$J8)*('Service Duration by unit'!$C$1:$C$400=_xlfn.MINIFS('Service Duration by unit'!$C$1:$C$400,'Service Duration by unit'!$A$1:$A$400,$J8,'Service Duration by unit'!$C$1:$C$400,">="&IF($H8=$M$4,N$4,N$3)))),1))*$L8/3600)*(1+$M8)} -> 0 | DH8: {=(IF($H8=$M$4,N$4*$I8,N$3*$I8)+(INDEX(_xlfn._xlws.FILTER('Service Duration by unit'!$D$1:$D$400,('Service Duration by unit'!$A$1:$A$400=$J8)*('Service Duration by unit'!$C$1:$C$400=_xlfn.MINIFS('Service Duration by unit'!$C$1:$C$400,'Service Duration by unit'!$A$1:$A$400,$J8,'Service Duration by unit'!$C$1:$C$400,">="&IF($H8=$M$4,N$4,N$3)))),1))*$L8/3600)*(1+$M8)} -> 0 | DI8: {=(IF($H8=$M$4,N$4*$I8,N$3*$I8)+(INDEX(_xlfn._xlws.FILTER('Service Duration by unit'!$D$1:$D$400,('Service Duration by unit'!$A$1:$A$400=$J8)*('Service Duration by unit'!$C$1:$C$400=_xlfn.MINIFS('Service Duration by unit'!$C$1:$C$400,'Service Duration by unit'!$A$1:$A$400,$J8,'Service Duration by unit'!$C$1:$C$400,">="&IF($H8=$M$4,N$4,N$3)))),1))*$L8/3600)*(1+$M8)} -> 0 | DJ8: {=(IF($H8=$M$4,N$4*$I8,N$3*$I8)+(INDEX(_xlfn._xlws.FILTER('Service Duration by unit'!$D$1:$D$400,('Service Duration by unit'!$A$1:$A$400=$J8)*('Service Duration by unit'!$C$1:$C$400=_xlfn.MINIFS('Service Duration by unit'!$C$1:$C$400,'Service Duration by unit'!$A$1:$A$400,$J8,'Service Duration by unit'!$C$1:$C$400,">="&IF($H8=$M$4,N$4,N$3)))),1))*$L8/3600)*(1+$M8)} -> 0 | DK8: {=(IF($H8=$M$4,N$4*$I8,N$3*$I8)+(INDEX(_xlfn._xlws.FILTER('Service Duration by unit'!$D$1:$D$400,('Service Duration by unit'!$A$1:$A$400=$J8)*('Service Duration by unit'!$C$1:$C$400=_xlfn.MINIFS('Service Duration by unit'!$C$1:$C$400,'Service Duration by unit'!$A$1:$A$400,$J8,'Service Duration by unit'!$C$1:$C$400,">="&IF($H8=$M$4,N$4,N$3)))),1))*$L8/3600)*(1+$M8)} -> 0 | DL8: {=(IF($H8=$M$4,N$4*$I8,N$3*$I8)+(INDEX(_xlfn._xlws.FILTER('Service Duration by unit'!$D$1:$D$400,('Service Duration by unit'!$A$1:$A$400=$J8)*('Service Duration by unit'!$C$1:$C$400=_xlfn.MINIFS('Service Duration by unit'!$C$1:$C$400,'Service Duration by unit'!$A$1:$A$400,$J8,'Service Duration by unit'!$C$1:$C$400,">="&IF($H8=$M$4,N$4,N$3)))),1))*$L8/3600)*(1+$M8)} -> 0 | DM8: {=(IF($H8=$M$4,N$4*$I8,N$3*$I8)+(INDEX(_xlfn._xlws.FILTER('Service Duration by unit'!$D$1:$D$400,('Service Duration by unit'!$A$1:$A$400=$J8)*('Service Duration by unit'!$C$1:$C$400=_xlfn.MINIFS('Service Duration by unit'!$C$1:$C$400,'Service Duration by unit'!$A$1:$A$400,$J8,'Service Duration by unit'!$C$1:$C$400,">="&IF($H8=$M$4,N$4,N$3)))),1))*$L8/3600)*(1+$M8)} -> 0 | DN8: {=(IF($H8=$M$4,N$4*$I8,N$3*$I8)+(INDEX(_xlfn._xlws.FILTER('Service Duration by unit'!$D$1:$D$400,('Service Duration by unit'!$A$1:$A$400=$J8)*('Service Duration by unit'!$C$1:$C$400=_xlfn.MINIFS('Service Duration by unit'!$C$1:$C$400,'Service Duration by unit'!$A$1:$A$400,$J8,'Service Duration by unit'!$C$1:$C$400,">="&IF($H8=$M$4,N$4,N$3)))),1))*$L8/3600)*(1+$M8)} -> 0 | DO8: {=(IF($H8=$M$4,N$4*$I8,N$3*$I8)+(INDEX(_xlfn._xlws.FILTER('Service Duration by unit'!$D$1:$D$400,('Service Duration by unit'!$A$1:$A$400=$J8)*('Service Duration by unit'!$C$1:$C$400=_xlfn.MINIFS('Service Duration by unit'!$C$1:$C$400,'Service Duration by unit'!$A$1:$A$400,$J8,'Service Duration by unit'!$C$1:$C$400,">="&IF($H8=$M$4,N$4,N$3)))),1))*$L8/3600)*(1+$M8)} -> 0 | DP8: {=(IF($H8=$M$4,N$4*$I8,N$3*$I8)+(INDEX(_xlfn._xlws.FILTER('Service Duration by unit'!$D$1:$D$400,('Service Duration by unit'!$A$1:$A$400=$J8)*('Service Duration by unit'!$C$1:$C$400=_xlfn.MINIFS('Service Duration by unit'!$C$1:$C$400,'Service Duration by unit'!$A$1:$A$400,$J8,'Service Duration by unit'!$C$1:$C$400,">="&IF($H8=$M$4,N$4,N$3)))),1))*$L8/3600)*(1+$M8)} -> 0 | DQ8: {=(IF($H8=$M$4,N$4*$I8,N$3*$I8)+(INDEX(_xlfn._xlws.FILTER('Service Duration by unit'!$D$1:$D$400,('Service Duration by unit'!$A$1:$A$400=$J8)*('Service Duration by unit'!$C$1:$C$400=_xlfn.MINIFS('Service Duration by unit'!$C$1:$C$400,'Service Duration by unit'!$A$1:$A$400,$J8,'Service Duration by unit'!$C$1:$C$400,">="&IF($H8=$M$4,N$4,N$3)))),1))*$L8/3600)*(1+$M8)} -> 0 | DR8: {=(IF($H8=$M$4,N$4*$I8,N$3*$I8)+(INDEX(_xlfn._xlws.FILTER('Service Duration by unit'!$D$1:$D$400,('Service Duration by unit'!$A$1:$A$400=$J8)*('Service Duration by unit'!$C$1:$C$400=_xlfn.MINIFS('Service Duration by unit'!$C$1:$C$400,'Service Duration by unit'!$A$1:$A$400,$J8,'Service Duration by unit'!$C$1:$C$400,">="&IF($H8=$M$4,N$4,N$3)))),1))*$L8/3600)*(1+$M8)} -> 0 | DS8: {=(IF($H8=$M$4,N$4*$I8,N$3*$I8)+(INDEX(_xlfn._xlws.FILTER('Service Duration by unit'!$D$1:$D$400,('Service Duration by unit'!$A$1:$A$400=$J8)*('Service Duration by unit'!$C$1:$C$400=_xlfn.MINIFS('Service Duration by unit'!$C$1:$C$400,'Service Duration by unit'!$A$1:$A$400,$J8,'Service Duration by unit'!$C$1:$C$400,">="&IF($H8=$M$4,N$4,N$3)))),1))*$L8/3600)*(1+$M8)} -> 0 | DT8: {=(IF($H8=$M$4,N$4*$I8,N$3*$I8)+(INDEX(_xlfn._xlws.FILTER('Service Duration by unit'!$D$1:$D$400,('Service Duration by unit'!$A$1:$A$400=$J8)*('Service Duration by unit'!$C$1:$C$400=_xlfn.MINIFS('Service Duration by unit'!$C$1:$C$400,'Service Duration by unit'!$A$1:$A$400,$J8,'Service Duration by unit'!$C$1:$C$400,">="&IF($H8=$M$4,N$4,N$3)))),1))*$L8/3600)*(1+$M8)} -> 0 | DU8: {=(IF($H8=$M$4,N$4*$I8,N$3*$I8)+(INDEX(_xlfn._xlws.FILTER('Service Duration by unit'!$D$1:$D$400,('Service Duration by unit'!$A$1:$A$400=$J8)*('Service Duration by unit'!$C$1:$C$400=_xlfn.MINIFS('Service Duration by unit'!$C$1:$C$400,'Service Duration by unit'!$A$1:$A$400,$J8,'Service Duration by unit'!$C$1:$C$400,">="&IF($H8=$M$4,N$4,N$3)))),1))*$L8/3600)*(1+$M8)} -> 0 | DV8: {=(IF($H8=$M$4,N$4*$I8,N$3*$I8)+(INDEX(_xlfn._xlws.FILTER('Service Duration by unit'!$D$1:$D$400,('Service Duration by unit'!$A$1:$A$400=$J8)*('Service Duration by unit'!$C$1:$C$400=_xlfn.MINIFS('Service Duration by unit'!$C$1:$C$400,'Service Duration by unit'!$A$1:$A$400,$J8,'Service Duration by unit'!$C$1:$C$400,">="&IF($H8=$M$4,N$4,N$3)))),1))*$L8/3600)*(1+$M8)} -> 0 | DW8: {=(IF($H8=$M$4,N$4*$I8,N$3*$I8)+(INDEX(_xlfn._xlws.FILTER('Service Duration by unit'!$D$1:$D$400,('Service Duration by unit'!$A$1:$A$400=$J8)*('Service Duration by unit'!$C$1:$C$400=_xlfn.MINIFS('Service Duration by unit'!$C$1:$C$400,'Service Duration by unit'!$A$1:$A$400,$J8,'Service Duration by unit'!$C$1:$C$400,">="&IF($H8=$M$4,N$4,N$3)))),1))*$L8/3600)*(1+$M8)} -> 0 | DX8: {=(IF($H8=$M$4,N$4*$I8,N$3*$I8)+(INDEX(_xlfn._xlws.FILTER('Service Duration by unit'!$D$1:$D$400,('Service Duration by unit'!$A$1:$A$400=$J8)*('Service Duration by unit'!$C$1:$C$400=_xlfn.MINIFS('Service Duration by unit'!$C$1:$C$400,'Service Duration by unit'!$A$1:$A$400,$J8,'Service Duration by unit'!$C$1:$C$400,">="&IF($H8=$M$4,N$4,N$3)))),1))*$L8/3600)*(1+$M8)} -> 0 | DY8: {=(IF($H8=$M$4,N$4*$I8,N$3*$I8)+(INDEX(_xlfn._xlws.FILTER('Service Duration by unit'!$D$1:$D$400,('Service Duration by unit'!$A$1:$A$400=$J8)*('Service Duration by unit'!$C$1:$C$400=_xlfn.MINIFS('Service Duration by unit'!$C$1:$C$400,'Service Duration by unit'!$A$1:$A$400,$J8,'Service Duration by unit'!$C$1:$C$400,">="&IF($H8=$M$4,N$4,N$3)))),1))*$L8/3600)*(1+$M8)} -> 0 | DZ8: {=(IF($H8=$M$4,N$4*$I8,N$3*$I8)+(INDEX(_xlfn._xlws.FILTER('Service Duration by unit'!$D$1:$D$400,('Service Duration by unit'!$A$1:$A$400=$J8)*('Service Duration by unit'!$C$1:$C$400=_xlfn.MINIFS('Service Duration by unit'!$C$1:$C$400,'Service Duration by unit'!$A$1:$A$400,$J8,'Service Duration by unit'!$C$1:$C$400,">="&IF($H8=$M$4,N$4,N$3)))),1))*$L8/3600)*(1+$M8)} -> 0 | EA8: {=(IF($H8=$M$4,N$4*$I8,N$3*$I8)+(INDEX(_xlfn._xlws.FILTER('Service Duration by unit'!$D$1:$D$400,('Service Duration by unit'!$A$1:$A$400=$J8)*('Service Duration by unit'!$C$1:$C$400=_xlfn.MINIFS('Service Duration by unit'!$C$1:$C$400,'Service Duration by unit'!$A$1:$A$400,$J8,'Service Duration by unit'!$C$1:$C$400,">="&IF($H8=$M$4,N$4,N$3)))),1))*$L8/3600)*(1+$M8)} -> 0 | EB8: {=(IF($H8=$M$4,N$4*$I8,N$3*$I8)+(INDEX(_xlfn._xlws.FILTER('Service Duration by unit'!$D$1:$D$400,('Service Duration by unit'!$A$1:$A$400=$J8)*('Service Duration by unit'!$C$1:$C$400=_xlfn.MINIFS('Service Duration by unit'!$C$1:$C$400,'Service Duration by unit'!$A$1:$A$400,$J8,'Service Duration by unit'!$C$1:$C$400,">="&IF($H8=$M$4,N$4,N$3)))),1))*$L8/3600)*(1+$M8)} -> 0 | EC8: {=(IF($H8=$M$4,N$4*$I8,N$3*$I8)+(INDEX(_xlfn._xlws.FILTER('Service Duration by unit'!$D$1:$D$400,('Service Duration by unit'!$A$1:$A$400=$J8)*('Service Duration by unit'!$C$1:$C$400=_xlfn.MINIFS('Service Duration by unit'!$C$1:$C$400,'Service Duration by unit'!$A$1:$A$400,$J8,'Service Duration by unit'!$C$1:$C$400,">="&IF($H8=$M$4,N$4,N$3)))),1))*$L8/3600)*(1+$M8)} -> 0 | ED8: {=(IF($H8=$M$4,N$4*$I8,N$3*$I8)+(INDEX(_xlfn._xlws.FILTER('Service Duration by unit'!$D$1:$D$400,('Service Duration by unit'!$A$1:$A$400=$J8)*('Service Duration by unit'!$C$1:$C$400=_xlfn.MINIFS('Service Duration by unit'!$C$1:$C$400,'Service Duration by unit'!$A$1:$A$400,$J8,'Service Duration by unit'!$C$1:$C$400,">="&IF($H8=$M$4,N$4,N$3)))),1))*$L8/3600)*(1+$M8)} -> 0 | EE8: {=(IF($H8=$M$4,N$4*$I8,N$3*$I8)+(INDEX(_xlfn._xlws.FILTER('Service Duration by unit'!$D$1:$D$400,('Service Duration by unit'!$A$1:$A$400=$J8)*('Service Duration by unit'!$C$1:$C$400=_xlfn.MINIFS('Service Duration by unit'!$C$1:$C$400,'Service Duration by unit'!$A$1:$A$400,$J8,'Service Duration by unit'!$C$1:$C$400,">="&IF($H8=$M$4,N$4,N$3)))),1))*$L8/3600)*(1+$M8)} -> 0 | EF8: {=(IF($H8=$M$4,N$4*$I8,N$3*$I8)+(INDEX(_xlfn._xlws.FILTER('Service Duration by unit'!$D$1:$D$400,('Service Duration by unit'!$A$1:$A$400=$J8)*('Service Duration by unit'!$C$1:$C$400=_xlfn.MINIFS('Service Duration by unit'!$C$1:$C$400,'Service Duration by unit'!$A$1:$A$400,$J8,'Service Duration by unit'!$C$1:$C$400,">="&IF($H8=$M$4,N$4,N$3)))),1))*$L8/3600)*(1+$M8)} -> 0 | EG8: {=(IF($H8=$M$4,N$4*$I8,N$3*$I8)+(INDEX(_xlfn._xlws.FILTER('Service Duration by unit'!$D$1:$D$400,('Service Duration by unit'!$A$1:$A$400=$J8)*('Service Duration by unit'!$C$1:$C$400=_xlfn.MINIFS('Service Duration by unit'!$C$1:$C$400,'Service Duration by unit'!$A$1:$A$400,$J8,'Service Duration by unit'!$C$1:$C$400,">="&IF($H8=$M$4,N$4,N$3)))),1))*$L8/3600)*(1+$M8)} -> 0 | EH8: {=(IF($H8=$M$4,N$4*$I8,N$3*$I8)+(INDEX(_xlfn._xlws.FILTER('Service Duration by unit'!$D$1:$D$400,('Service Duration by unit'!$A$1:$A$400=$J8)*('Service Duration by unit'!$C$1:$C$400=_xlfn.MINIFS('Service Duration by unit'!$C$1:$C$400,'Service Duration by unit'!$A$1:$A$400,$J8,'Service Duration by unit'!$C$1:$C$400,">="&IF($H8=$M$4,N$4,N$3)))),1))*$L8/3600)*(1+$M8)} -> 0 | EI8: {=(IF($H8=$M$4,N$4*$I8,N$3*$I8)+(INDEX(_xlfn._xlws.FILTER('Service Duration by unit'!$D$1:$D$400,('Service Duration by unit'!$A$1:$A$400=$J8)*('Service Duration by unit'!$C$1:$C$400=_xlfn.MINIFS('Service Duration by unit'!$C$1:$C$400,'Service Duration by unit'!$A$1:$A$400,$J8,'Service Duration by unit'!$C$1:$C$400,">="&IF($H8=$M$4,N$4,N$3)))),1))*$L8/3600)*(1+$M8)} -> 0 | EJ8: {=(IF($H8=$M$4,N$4*$I8,N$3*$I8)+(INDEX(_xlfn._xlws.FILTER('Service Duration by unit'!$D$1:$D$400,('Service Duration by unit'!$A$1:$A$400=$J8)*('Service Duration by unit'!$C$1:$C$400=_xlfn.MINIFS('Service Duration by unit'!$C$1:$C$400,'Service Duration by unit'!$A$1:$A$400,$J8,'Service Duration by unit'!$C$1:$C$400,">="&IF($H8=$M$4,N$4,N$3)))),1))*$L8/3600)*(1+$M8)} -> 0 | EK8: {=(IF($H8=$M$4,N$4*$I8,N$3*$I8)+(INDEX(_xlfn._xlws.FILTER('Service Duration by unit'!$D$1:$D$400,('Service Duration by unit'!$A$1:$A$400=$J8)*('Service Duration by unit'!$C$1:$C$400=_xlfn.MINIFS('Service Duration by unit'!$C$1:$C$400,'Service Duration by unit'!$A$1:$A$400,$J8,'Service Duration by unit'!$C$1:$C$400,">="&IF($H8=$M$4,N$4,N$3)))),1))*$L8/3600)*(1+$M8)} -> 0 | EL8: {=(IF($H8=$M$4,N$4*$I8,N$3*$I8)+(INDEX(_xlfn._xlws.FILTER('Service Duration by unit'!$D$1:$D$400,('Service Duration by unit'!$A$1:$A$400=$J8)*('Service Duration by unit'!$C$1:$C$400=_xlfn.MINIFS('Service Duration by unit'!$C$1:$C$400,'Service Duration by unit'!$A$1:$A$400,$J8,'Service Duration by unit'!$C$1:$C$400,">="&IF($H8=$M$4,N$4,N$3)))),1))*$L8/3600)*(1+$M8)} -> 0 | EM8: {=(IF($H8=$M$4,N$4*$I8,N$3*$I8)+(INDEX(_xlfn._xlws.FILTER('Service Duration by unit'!$D$1:$D$400,('Service Duration by unit'!$A$1:$A$400=$J8)*('Service Duration by unit'!$C$1:$C$400=_xlfn.MINIFS('Service Duration by unit'!$C$1:$C$400,'Service Duration by unit'!$A$1:$A$400,$J8,'Service Duration by unit'!$C$1:$C$400,">="&IF($H8=$M$4,N$4,N$3)))),1))*$L8/3600)*(1+$M8)} -> 0 | EN8: {=(IF($H8=$M$4,N$4*$I8,N$3*$I8)+(INDEX(_xlfn._xlws.FILTER('Service Duration by unit'!$D$1:$D$400,('Service Duration by unit'!$A$1:$A$400=$J8)*('Service Duration by unit'!$C$1:$C$400=_xlfn.MINIFS('Service Duration by unit'!$C$1:$C$400,'Service Duration by unit'!$A$1:$A$400,$J8,'Service Duration by unit'!$C$1:$C$400,">="&IF($H8=$M$4,N$4,N$3)))),1))*$L8/3600)*(1+$M8)} -> 0 | EO8: {=(IF($H8=$M$4,N$4*$I8,N$3*$I8)+(INDEX(_xlfn._xlws.FILTER('Service Duration by unit'!$D$1:$D$400,('Service Duration by unit'!$A$1:$A$400=$J8)*('Service Duration by unit'!$C$1:$C$400=_xlfn.MINIFS('Service Duration by unit'!$C$1:$C$400,'Service Duration by unit'!$A$1:$A$400,$J8,'Service Duration by unit'!$C$1:$C$400,">="&IF($H8=$M$4,N$4,N$3)))),1))*$L8/3600)*(1+$M8)} -> 0 | EP8: {=(IF($H8=$M$4,N$4*$I8,N$3*$I8)+(INDEX(_xlfn._xlws.FILTER('Service Duration by unit'!$D$1:$D$400,('Service Duration by unit'!$A$1:$A$400=$J8)*('Service Duration by unit'!$C$1:$C$400=_xlfn.MINIFS('Service Duration by unit'!$C$1:$C$400,'Service Duration by unit'!$A$1:$A$400,$J8,'Service Duration by unit'!$C$1:$C$400,">="&IF($H8=$M$4,N$4,N$3)))),1))*$L8/3600)*(1+$M8)} -> 0 | EQ8: {=(IF($H8=$M$4,N$4*$I8,N$3*$I8)+(INDEX(_xlfn._xlws.FILTER('Service Duration by unit'!$D$1:$D$400,('Service Duration by unit'!$A$1:$A$400=$J8)*('Service Duration by unit'!$C$1:$C$400=_xlfn.MINIFS('Service Duration by unit'!$C$1:$C$400,'Service Duration by unit'!$A$1:$A$400,$J8,'Service Duration by unit'!$C$1:$C$400,">="&IF($H8=$M$4,N$4,N$3)))),1))*$L8/3600)*(1+$M8)} -> 0 | ER8: {=(IF($H8=$M$4,N$4*$I8,N$3*$I8)+(INDEX(_xlfn._xlws.FILTER('Service Duration by unit'!$D$1:$D$400,('Service Duration by unit'!$A$1:$A$400=$J8)*('Service Duration by unit'!$C$1:$C$400=_xlfn.MINIFS('Service Duration by unit'!$C$1:$C$400,'Service Duration by unit'!$A$1:$A$400,$J8,'Service Duration by unit'!$C$1:$C$400,">="&IF($H8=$M$4,N$4,N$3)))),1))*$L8/3600)*(1+$M8)} -> 0 | ES8: {=(IF($H8=$M$4,N$4*$I8,N$3*$I8)+(INDEX(_xlfn._xlws.FILTER('Service Duration by unit'!$D$1:$D$400,('Service Duration by unit'!$A$1:$A$400=$J8)*('Service Duration by unit'!$C$1:$C$400=_xlfn.MINIFS('Service Duration by unit'!$C$1:$C$400,'Service Duration by unit'!$A$1:$A$400,$J8,'Service Duration by unit'!$C$1:$C$400,">="&IF($H8=$M$4,N$4,N$3)))),1))*$L8/3600)*(1+$M8)} -> 0 | ET8: {=(IF($H8=$M$4,N$4*$I8,N$3*$I8)+(INDEX(_xlfn._xlws.FILTER('Service Duration by unit'!$D$1:$D$400,('Service Duration by unit'!$A$1:$A$400=$J8)*('Service Duration by unit'!$C$1:$C$400=_xlfn.MINIFS('Service Duration by unit'!$C$1:$C$400,'Service Duration by unit'!$A$1:$A$400,$J8,'Service Duration by unit'!$C$1:$C$400,">="&IF($H8=$M$4,N$4,N$3)))),1))*$L8/3600)*(1+$M8)} -> 0 | EU8: {=(IF($H8=$M$4,N$4*$I8,N$3*$I8)+(INDEX(_xlfn._xlws.FILTER('Service Duration by unit'!$D$1:$D$400,('Service Duration by unit'!$A$1:$A$400=$J8)*('Service Duration by unit'!$C$1:$C$400=_xlfn.MINIFS('Service Duration by unit'!$C$1:$C$400,'Service Duration by unit'!$A$1:$A$400,$J8,'Service Duration by unit'!$C$1:$C$400,">="&IF($H8=$M$4,N$4,N$3)))),1))*$L8/3600)*(1+$M8)} -> 0 | EV8: {=(IF($H8=$M$4,N$4*$I8,N$3*$I8)+(INDEX(_xlfn._xlws.FILTER('Service Duration by unit'!$D$1:$D$400,('Service Duration by unit'!$A$1:$A$400=$J8)*('Service Duration by unit'!$C$1:$C$400=_xlfn.MINIFS('Service Duration by unit'!$C$1:$C$400,'Service Duration by unit'!$A$1:$A$400,$J8,'Service Duration by unit'!$C$1:$C$400,">="&IF($H8=$M$4,N$4,N$3)))),1))*$L8/3600)*(1+$M8)} -> 0 | EW8: {=(IF($H8=$M$4,N$4*$I8,N$3*$I8)+(INDEX(_xlfn._xlws.FILTER('Service Duration by unit'!$D$1:$D$400,('Service Duration by unit'!$A$1:$A$400=$J8)*('Service Duration by unit'!$C$1:$C$400=_xlfn.MINIFS('Service Duration by unit'!$C$1:$C$400,'Service Duration by unit'!$A$1:$A$400,$J8,'Service Duration by unit'!$C$1:$C$400,">="&IF($H8=$M$4,N$4,N$3)))),1))*$L8/3600)*(1+$M8)} -> 0 | EX8: {=(IF($H8=$M$4,N$4*$I8,N$3*$I8)+(INDEX(_xlfn._xlws.FILTER('Service Duration by unit'!$D$1:$D$400,('Service Duration by unit'!$A$1:$A$400=$J8)*('Service Duration by unit'!$C$1:$C$400=_xlfn.MINIFS('Service Duration by unit'!$C$1:$C$400,'Service Duration by unit'!$A$1:$A$400,$J8,'Service Duration by unit'!$C$1:$C$400,">="&IF($H8=$M$4,N$4,N$3)))),1))*$L8/3600)*(1+$M8)} -> 0 | EY8: {=(IF($H8=$M$4,N$4*$I8,N$3*$I8)+(INDEX(_xlfn._xlws.FILTER('Service Duration by unit'!$D$1:$D$400,('Service Duration by unit'!$A$1:$A$400=$J8)*('Service Duration by unit'!$C$1:$C$400=_xlfn.MINIFS('Service Duration by unit'!$C$1:$C$400,'Service Duration by unit'!$A$1:$A$400,$J8,'Service Duration by unit'!$C$1:$C$400,">="&IF($H8=$M$4,N$4,N$3)))),1))*$L8/3600)*(1+$M8)} -> 0 | EZ8: {=(IF($H8=$M$4,N$4*$I8,N$3*$I8)+(INDEX(_xlfn._xlws.FILTER('Service Duration by unit'!$D$1:$D$400,('Service Duration by unit'!$A$1:$A$400=$J8)*('Service Duration by unit'!$C$1:$C$400=_xlfn.MINIFS('Service Duration by unit'!$C$1:$C$400,'Service Duration by unit'!$A$1:$A$400,$J8,'Service Duration by unit'!$C$1:$C$400,">="&IF($H8=$M$4,N$4,N$3)))),1))*$L8/3600)*(1+$M8)} -> 0 | FA8: {=(IF($H8=$M$4,N$4*$I8,N$3*$I8)+(INDEX(_xlfn._xlws.FILTER('Service Duration by unit'!$D$1:$D$400,('Service Duration by unit'!$A$1:$A$400=$J8)*('Service Duration by unit'!$C$1:$C$400=_xlfn.MINIFS('Service Duration by unit'!$C$1:$C$400,'Service Duration by unit'!$A$1:$A$400,$J8,'Service Duration by unit'!$C$1:$C$400,">="&IF($H8=$M$4,N$4,N$3)))),1))*$L8/3600)*(1+$M8)} -> 0 | FB8: {=(IF($H8=$M$4,N$4*$I8,N$3*$I8)+(INDEX(_xlfn._xlws.FILTER('Service Duration by unit'!$D$1:$D$400,('Service Duration by unit'!$A$1:$A$400=$J8)*('Service Duration by unit'!$C$1:$C$400=_xlfn.MINIFS('Service Duration by unit'!$C$1:$C$400,'Service Duration by unit'!$A$1:$A$400,$J8,'Service Duration by unit'!$C$1:$C$400,">="&IF($H8=$M$4,N$4,N$3)))),1))*$L8/3600)*(1+$M8)} -> 0 | FC8: {=(IF($H8=$M$4,N$4*$I8,N$3*$I8)+(INDEX(_xlfn._xlws.FILTER('Service Duration by unit'!$D$1:$D$400,('Service Duration by unit'!$A$1:$A$400=$J8)*('Service Duration by unit'!$C$1:$C$400=_xlfn.MINIFS('Service Duration by unit'!$C$1:$C$400,'Service Duration by unit'!$A$1:$A$400,$J8,'Service Duration by unit'!$C$1:$C$400,">="&IF($H8=$M$4,N$4,N$3)))),1))*$L8/3600)*(1+$M8)} -> 0 | FD8: {=(IF($H8=$M$4,N$4*$I8,N$3*$I8)+(INDEX(_xlfn._xlws.FILTER('Service Duration by unit'!$D$1:$D$400,('Service Duration by unit'!$A$1:$A$400=$J8)*('Service Duration by unit'!$C$1:$C$400=_xlfn.MINIFS('Service Duration by unit'!$C$1:$C$400,'Service Duration by unit'!$A$1:$A$400,$J8,'Service Duration by unit'!$C$1:$C$400,">="&IF($H8=$M$4,N$4,N$3)))),1))*$L8/3600)*(1+$M8)} -> 0 | FE8: {=(IF($H8=$M$4,N$4*$I8,N$3*$I8)+(INDEX(_xlfn._xlws.FILTER('Service Duration by unit'!$D$1:$D$400,('Service Duration by unit'!$A$1:$A$400=$J8)*('Service Duration by unit'!$C$1:$C$400=_xlfn.MINIFS('Service Duration by unit'!$C$1:$C$400,'Service Duration by unit'!$A$1:$A$400,$J8,'Service Duration by unit'!$C$1:$C$400,">="&IF($H8=$M$4,N$4,N$3)))),1))*$L8/3600)*(1+$M8)} -> 0 | FF8: {=(IF($H8=$M$4,N$4*$I8,N$3*$I8)+(INDEX(_xlfn._xlws.FILTER('Service Duration by unit'!$D$1:$D$400,('Service Duration by unit'!$A$1:$A$400=$J8)*('Service Duration by unit'!$C$1:$C$400=_xlfn.MINIFS('Service Duration by unit'!$C$1:$C$400,'Service Duration by unit'!$A$1:$A$400,$J8,'Service Duration by unit'!$C$1:$C$400,">="&IF($H8=$M$4,N$4,N$3)))),1))*$L8/3600)*(1+$M8)} -> 0
